Workbook

Sheet 01 Tổng quan
A1: Bộ dữ liệu tài chính NIKE, Inc. FY2020–FY2026
A2: Cơ sở số liệu cho đề tài “Đổi mới và tái cân bằng chiến lược phân phối tại Nike: Từ Direct-to-Consumer (D2C) đến bán buôn và những biến động tài chính giai đoạn FY2020–FY2026”.
A4: Thông tin chung
A5: Mục đích | B5: Tập hợp số liệu chính thức về doanh thu theo kênh phân phối (NIKE Direct, bán buôn) và kết quả tài chính hợp nhất của NIKE, Inc. để nhóm dùng trong báo cáo, thuyết trình và dashboard.
A6: Kỳ nghiên cứu | B6: FY2020–FY2026. Năm tài chính của NIKE kết thúc ngày 31/5, ví dụ FY2026 = 01/06/2025 – 31/05/2026. FY không trùng với năm dương lịch.
A7: Đơn vị | B7: Triệu USD, trừ khi cột “Đơn vị” ghi khác (tỷ USD cho doanh số Digital; % cho tỷ lệ). Không quy đổi sang VND.
A8: Nguồn | B8: 7 báo cáo thường niên Form 10-K của NIKE, Inc. nộp Ủy ban Chứng khoán Mỹ (SEC), FY2020–FY2026. Không dùng trang tổng hợp tài chính của bên thứ ba.
A9: Thứ tự ưu tiên nguồn | B9: (1) Báo cáo tài chính đã kiểm toán và thuyết minh (Item 8), lấy từ dữ liệu XBRL đi kèm chính báo cáo 10-K. (2) Phần MD&A (Item 7) của cùng báo cáo, cho các số non-GAAP và số do ban điều hành nêu: EBIT, tăng trưởng loại trừ tỷ giá, doanh số Digital. (3) Dữ liệu XBRL do SEC công bố chỉ dùng để đối chiếu.
A10: Quy tắc chọn số | B10: Số liệu của mỗi năm tài chính được lấy từ báo cáo 10-K của chính năm đó. “Giá trị năm trước” là số của năm trước được in kèm trong cùng báo cáo để so sánh, dùng để tính tăng trưởng giống cách NIKE tự tính. Nếu báo cáo năm sau trình bày lại số liệu, phần chênh lệch được ghi ở cột “Trình bày lại ở 10-K sau”, số gốc giữ nguyên.
A11: Tình trạng dữ liệu | B11: Trích xuất tự động ngày 23/10/2026. 203 số liệu: 202 khớp nguồn chính thức, 1 không được công bố.
A13: Cách sử dụng
A14: 1. Đọc số liệu | B14: Sheet 02 (hợp nhất NIKE, Inc.) và 03 (kênh phân phối NIKE Brand). Mỗi dòng là một số liệu của một năm. Dùng nút lọc ở dòng tiêu đề để chọn chỉ tiêu hoặc năm.
A15: 2. Kiểm tra nguồn | B15: Bấm liên kết ở cột “Tài liệu nguồn” để mở 10-K trên SEC EDGAR. Tìm số trang ở cột “Trang” (số in ở chân trang, dạng “2026 FORM 10-K 83”) rồi đối chiếu với cột “Số hoặc câu hiển thị trong tài liệu”.
A16: 3. Ghi nhận xác minh | B16: Sau khi tự đối chiếu, chọn “Đã xác minh (người)” ở cột “Trạng thái dữ liệu” và điền tên, ngày ở các cột nền vàng.
A17: 4. Xem chỉ số | B17: Sheet 04 tính các tỷ lệ bằng công thức Excel từ sheet 02–03. Cột “Công thức” giải thích cách tính từng chỉ số, mục D–E là phần kiểm tra.
A18: 5. Tra cứu | B18: Sheet 05: danh mục 10-K, thuật ngữ, các số liệu còn thiếu và các lần NIKE trình bày lại số liệu.
A20: Quy ước trình bày
A21: Chữ xanh dương | B21: Số liệu nhập từ tài liệu nguồn (không phải công thức).
A22: Chữ xanh lá | B22: Công thức lấy số liệu từ sheet khác.
A23: Chữ đen | B23: Công thức tính toán.
A24: Số âm | B24: Trong ngoặc đơn, ví dụ (50), theo cách trình bày của NIKE. Tỷ lệ % dùng dấu trừ.
A25: Ô trống | B25: Đi kèm trạng thái “Thiếu / không công bố”, nghĩa là NIKE không công bố số liệu đó. Ô để trống chứ không điền số 0. Ở sheet 04, “–” nghĩa là không tính được vì thiếu số đầu vào.
A26: Tỷ lệ % | B26: Lưu dạng thập phân (0,14 hiển thị 14%) để dùng được trong công thức.
A27: Cột tiêu đề nền vàng | B27: Dành cho nhóm điền: người xác minh, ngày xác minh, ghi chú.
A29: Lưu ý khi dùng cho nghiên cứu
A30: Không suy ra nhân quả | B30: Các chỉ số chỉ cho thấy số liệu thay đổi trong cùng giai đoạn, không chứng minh việc thay đổi chiến lược kênh là nguyên nhân.
A31: Không có lợi nhuận theo kênh | B31: NIKE không công bố lợi nhuận hay chi phí riêng của NIKE Direct và bán buôn. SG&A là chi phí chung của cả công ty.
A32: Không trộn phạm vi | B32: Tỷ trọng các kênh tính trên doanh thu NIKE Brand, còn biên lợi nhuận tính trên doanh thu NIKE, Inc.
A33: Trích dẫn | B33: Khi dùng số liệu, trích dẫn 10-K gốc (năm, trang) thay vì trích dẫn file này.
A35: Liên kết dashboard | B35: https://miurikyasakytg2006-dot.github.io/nike-financial-dashboard/

Sheet 02 Dữ liệu tài chính
A1: Dữ liệu tài chính hợp nhất – NIKE, Inc.
A2: Báo cáo kết quả kinh doanh, hàng tồn kho, EBIT và tăng trưởng doanh thu NIKE công bố. Mỗi dòng là một chỉ tiêu của một năm tài chính.
A4: Năm tài chính | B4: Chỉ tiêu | C4: Giá trị | D4: Giá trị năm trước (cùng 10-K) | E4: Đơn vị | F4: Phạm vi báo cáo | G4: Kênh | H4: Loại số liệu | I4: Trạng thái dữ liệu | J4: Tài liệu nguồn (mở trên SEC) | K4: Trang | L4: Mục trong 10-K | M4: Vị trí chi tiết | N4: Số hoặc câu hiển thị trong tài liệu | O4: Đối chiếu tự động | P4: Trình bày lại ở 10-K sau | Q4: Người xác minh | R4: Ngày xác minh | S4: Ghi chú của nhóm | T4: Dòng trong 10-K (tiếng Anh) | U4: Thẻ XBRL | V4: Kỳ báo cáo | W4: Ngày nộp SEC | X4: Số accession | Y4: Mã chỉ tiêu | Z4: Mã quan sát
A5: FY2020 | B5: Doanh thu | C5: 37403 | D5: 39117 | E5: triệu USD | F5: NIKE, Inc. | G5: — | H5: GAAP – BCTC đã kiểm toán | I5: Khớp nguồn chính thức | J5: 10-K FY2020 | K5: 56 | L5: CONSOLIDATED STATEMENTS OF INCOME | M5: Item 8 – Consolidated Statements of Income, dòng “Revenues” | N5: 37,403 | O5: Khớp với dữ liệu XBRL do SEC công bố (cùng số accession). | P5: Không thay đổi khi trình bày lại trong 10-K FY2021, FY2022. | T5: Revenues | U5: us-gaap:RevenueFromContractWithCustomerExcludingAssessedTax | V5: 01/06/2019 – 31/05/2020 | W5: 24/07/2020 | X5: 0000320187-20-000047 | Y5: revenues | Z5: FY2020|revenues
A6: FY2021 | B6: Doanh thu | C6: 44538 | D6: 37403 | E6: triệu USD | F6: NIKE, Inc. | G6: — | H6: GAAP – BCTC đã kiểm toán | I6: Khớp nguồn chính thức | J6: 10-K FY2021 | K6: 57 | L6: CONSOLIDATED STATEMENTS OF INCOME | M6: Item 8 – Consolidated Statements of Income, dòng “Revenues” | N6: 44,538 | O6: Khớp với dữ liệu XBRL do SEC công bố (cùng số accession). | P6: Không thay đổi khi trình bày lại trong 10-K FY2022, FY2023. | T6: Revenues | U6: us-gaap:RevenueFromContractWithCustomerExcludingAssessedTax | V6: 01/06/2020 – 31/05/2021 | W6: 20/07/2021 | X6: 0000320187-21-000028 | Y6: revenues | Z6: FY2021|revenues
A7: FY2022 | B7: Doanh thu | C7: 46710 | D7: 44538 | E7: triệu USD | F7: NIKE, Inc. | G7: — | H7: GAAP – BCTC đã kiểm toán | I7: Khớp nguồn chính thức | J7: 10-K FY2022 | K7: 56 | L7: CONSOLIDATED STATEMENTS OF INCOME | M7: Item 8 – Consolidated Statements of Income, dòng “Revenues” | N7: 46,710 | O7: Khớp với dữ liệu XBRL do SEC công bố (cùng số accession). | P7: Không thay đổi khi trình bày lại trong 10-K FY2023, FY2024. | T7: Revenues | U7: us-gaap:RevenueFromContractWithCustomerExcludingAssessedTax | V7: 01/06/2021 – 31/05/2022 | W7: 21/07/2022 | X7: 0000320187-22-000038 | Y7: revenues | Z7: FY2022|revenues
A8: FY2023 | B8: Doanh thu | C8: 51217 | D8: 46710 | E8: triệu USD | F8: NIKE, Inc. | G8: — | H8: GAAP – BCTC đã kiểm toán | I8: Khớp nguồn chính thức | J8: 10-K FY2023 | K8: 55 | L8: CONSOLIDATED STATEMENTS OF INCOME | M8: Item 8 – Consolidated Statements of Income, dòng “Revenues” | N8: 51,217 | O8: Khớp với dữ liệu XBRL do SEC công bố (cùng số accession). | P8: Không thay đổi khi trình bày lại trong 10-K FY2024, FY2025. | T8: Revenues | U8: us-gaap:RevenueFromContractWithCustomerExcludingAssessedTax | V8: 01/06/2022 – 31/05/2023 | W8: 20/07/2023 | X8: 0000320187-23-000039 | Y8: revenues | Z8: FY2023|revenues
A9: FY2024 | B9: Doanh thu | C9: 51362 | D9: 51217 | E9: triệu USD | F9: NIKE, Inc. | G9: — | H9: GAAP – BCTC đã kiểm toán | I9: Khớp nguồn chính thức | J9: 10-K FY2024 | K9: 57 | L9: CONSOLIDATED STATEMENTS OF INCOME | M9: Item 8 – Consolidated Statements of Income, dòng “Revenues” | N9: 51,362 | O9: Khớp với dữ liệu XBRL do SEC công bố (cùng số accession). | P9: Không thay đổi khi trình bày lại trong 10-K FY2025, FY2026. | T9: Revenues | U9: us-gaap:RevenueFromContractWithCustomerExcludingAssessedTax | V9: 01/06/2023 – 31/05/2024 | W9: 25/07/2024 | X9: 0000320187-24-000044 | Y9: revenues | Z9: FY2024|revenues
A10: FY2025 | B10: Doanh thu | C10: 46309 | D10: 51362 | E10: triệu USD | F10: NIKE, Inc. | G10: — | H10: GAAP – BCTC đã kiểm toán | I10: Khớp nguồn chính thức | J10: 10-K FY2025 | K10: 56 | L10: CONSOLIDATED STATEMENTS OF INCOME | M10: Item 8 – Consolidated Statements of Income, dòng “Revenues” | N10: 46,309 | O10: Khớp với dữ liệu XBRL do SEC công bố (cùng số accession). | P10: Không thay đổi khi trình bày lại trong 10-K FY2026. | T10: Revenues | U10: us-gaap:RevenueFromContractWithCustomerExcludingAssessedTax | V10: 01/06/2024 – 31/05/2025 | W10: 17/07/2025 | X10: 0000320187-25-000047 | Y10: revenues | Z10: FY2025|revenues
A11: FY2026 | B11: Doanh thu | C11: 46398 | D11: 46309 | E11: triệu USD | F11: NIKE, Inc. | G11: — | H11: GAAP – BCTC đã kiểm toán | I11: Khớp nguồn chính thức | J11: 10-K FY2026 | K11: 55 | L11: CONSOLIDATED STATEMENTS OF INCOME | M11: Item 8 – Consolidated Statements of Income, dòng “Revenues” | N11: 46,398 | O11: Khớp với dữ liệu XBRL do SEC công bố (cùng số accession). | P11: Chưa có 10-K năm sau để so sánh. | T11: Revenues | U11: us-gaap:RevenueFromContractWithCustomerExcludingAssessedTax | V11: 01/06/2025 – 31/05/2026 | W11: 15/07/2026 | X11: 0000320187-26-000088 | Y11: revenues | Z11: FY2026|revenues
A12: FY2020 | B12: Giá vốn hàng bán | C12: 21162 | D12: 21643 | E12: triệu USD | F12: NIKE, Inc. | G12: — | H12: GAAP – BCTC đã kiểm toán | I12: Khớp nguồn chính thức | J12: 10-K FY2020 | K12: 56 | L12: CONSOLIDATED STATEMENTS OF INCOME | M12: Item 8 – Consolidated Statements of Income, dòng “Cost of sales” | N12: 21,162 | O12: Khớp với dữ liệu XBRL do SEC công bố (cùng số accession). | P12: Không thay đổi khi trình bày lại trong 10-K FY2021, FY2022. | T12: Cost of sales | U12: us-gaap:CostOfGoodsAndServicesSold | V12: 01/06/2019 – 31/05/2020 | W12: 24/07/2020 | X12: 0000320187-20-000047 | Y12: cost_of_sales | Z12: FY2020|cost_of_sales
A13: FY2021 | B13: Giá vốn hàng bán | C13: 24576 | D13: 21162 | E13: triệu USD | F13: NIKE, Inc. | G13: — | H13: GAAP – BCTC đã kiểm toán | I13: Khớp nguồn chính thức | J13: 10-K FY2021 | K13: 57 | L13: CONSOLIDATED STATEMENTS OF INCOME | M13: Item 8 – Consolidated Statements of Income, dòng “Cost of sales” | N13: 24,576 | O13: Khớp với dữ liệu XBRL do SEC công bố (cùng số accession). | P13: Không thay đổi khi trình bày lại trong 10-K FY2022, FY2023. | T13: Cost of sales | U13: us-gaap:CostOfGoodsAndServicesSold | V13: 01/06/2020 – 31/05/2021 | W13: 20/07/2021 | X13: 0000320187-21-000028 | Y13: cost_of_sales | Z13: FY2021|cost_of_sales
A14: FY2022 | B14: Giá vốn hàng bán | C14: 25231 | D14: 24576 | E14: triệu USD | F14: NIKE, Inc. | G14: — | H14: GAAP – BCTC đã kiểm toán | I14: Khớp nguồn chính thức | J14: 10-K FY2022 | K14: 56 | L14: CONSOLIDATED STATEMENTS OF INCOME | M14: Item 8 – Consolidated Statements of Income, dòng “Cost of sales” | N14: 25,231 | O14: Khớp với dữ liệu XBRL do SEC công bố (cùng số accession). | P14: Không thay đổi khi trình bày lại trong 10-K FY2023, FY2024. | T14: Cost of sales | U14: us-gaap:CostOfGoodsAndServicesSold | V14: 01/06/2021 – 31/05/2022 | W14: 21/07/2022 | X14: 0000320187-22-000038 | Y14: cost_of_sales | Z14: FY2022|cost_of_sales
A15: FY2023 | B15: Giá vốn hàng bán | C15: 28925 | D15: 25231 | E15: triệu USD | F15: NIKE, Inc. | G15: — | H15: GAAP – BCTC đã kiểm toán | I15: Khớp nguồn chính thức | J15: 10-K FY2023 | K15: 55 | L15: CONSOLIDATED STATEMENTS OF INCOME | M15: Item 8 – Consolidated Statements of Income, dòng “Cost of sales” | N15: 28,925 | O15: Khớp với dữ liệu XBRL do SEC công bố (cùng số accession). | P15: Không thay đổi khi trình bày lại trong 10-K FY2024, FY2025. | T15: Cost of sales | U15: us-gaap:CostOfGoodsAndServicesSold | V15: 01/06/2022 – 31/05/2023 | W15: 20/07/2023 | X15: 0000320187-23-000039 | Y15: cost_of_sales | Z15: FY2023|cost_of_sales
A16: FY2024 | B16: Giá vốn hàng bán | C16: 28475 | D16: 28925 | E16: triệu USD | F16: NIKE, Inc. | G16: — | H16: GAAP – BCTC đã kiểm toán | I16: Khớp nguồn chính thức | J16: 10-K FY2024 | K16: 57 | L16: CONSOLIDATED STATEMENTS OF INCOME | M16: Item 8 – Consolidated Statements of Income, dòng “Cost of sales” | N16: 28,475 | O16: Khớp với dữ liệu XBRL do SEC công bố (cùng số accession). | P16: Không thay đổi khi trình bày lại trong 10-K FY2025, FY2026. | T16: Cost of sales | U16: us-gaap:CostOfGoodsAndServicesSold | V16: 01/06/2023 – 31/05/2024 | W16: 25/07/2024 | X16: 0000320187-24-000044 | Y16: cost_of_sales | Z16: FY2024|cost_of_sales
... A95: FY2026 | B95: EBIT do NIKE công bố | C95: 3850 | D95: 3778 | E95: triệu USD | F95: NIKE, Inc. | G95: — | H95: Non-GAAP – NIKE định nghĩa | I95: Khớp nguồn chính thức | J95: 10-K FY2026 | K95: 36 | L95: ITEM 7 – MD&A | M95: Item 7 – MD&A, bảng “Total NIKE, Inc. EBIT” (mục Use of Non-GAAP Financial Measures / Operating Segments) | N95: TOTAL NIKE, INC. EBIT(1) | 3,850 | 3,778 | 2 | 6,539 | -42 | O95: Khớp với giá trị tự tính từ BCTC (chênh 0 triệu USD, ngưỡng ±1 triệu USD). | P95: Chưa có 10-K năm sau để so sánh. | T95: Total NIKE, Inc. Earnings Before Interest and Taxes (EBIT) | U95: Không gắn thẻ XBRL (MD&A) | V95: 01/06/2025 – 31/05/2026 | W95: 15/07/2026 | X95: 0000320187-26-000088 | Y95: ebit_reported | Z95: FY2026|ebit_reported
A96: FY2020 | B96: % thay đổi doanh thu (NIKE công bố, đã làm tròn) | C96: -0.04 | E96: % | F96: NIKE, Inc. | G96: — | H96: MD&A – % tính từ số GAAP | I96: Khớp nguồn chính thức | J96: 10-K FY2020 | K96: 31 | L96: ITEM 7 – MD&A | M96: Item 7 – MD&A, bảng doanh thu NIKE, Inc., cột “% CHANGE” | N96: TOTAL NIKE, INC. REVENUES | 37,403 | 39,117 | -4 | -2 | 36,397 | 7 | 11 | O96: Khớp với giá trị tự tính từ BCTC (chênh −0,38 điểm %, ngưỡng ±1 điểm %). | P96: Không áp dụng: tỷ lệ % chỉ lấy từ 10-K của chính năm đó. | T96: TOTAL NIKE, INC. REVENUES – % change | U96: Không gắn thẻ XBRL (MD&A) | V96: 01/06/2019 – 31/05/2020 | W96: 24/07/2020 | X96: 0000320187-20-000047 | Y96: revenues_pct_change_reported | Z96: FY2020|revenues_pct_change_reported
A97: FY2021 | B97: % thay đổi doanh thu (NIKE công bố, đã làm tròn) | C97: 0.19 | E97: % | F97: NIKE, Inc. | G97: — | H97: MD&A – % tính từ số GAAP | I97: Khớp nguồn chính thức | J97: 10-K FY2021 | K97: 32 | L97: ITEM 7 – MD&A | M97: Item 7 – MD&A, bảng doanh thu NIKE, Inc., cột “% CHANGE” | N97: TOTAL NIKE, INC. REVENUES | 44,538 | 37,403 | 19 | 17 | 39,117 | -4 | -2 | O97: Khớp với giá trị tự tính từ BCTC (chênh +0,08 điểm %, ngưỡng ±1 điểm %). | P97: Không áp dụng: tỷ lệ % chỉ lấy từ 10-K của chính năm đó. | T97: TOTAL NIKE, INC. REVENUES – % change | U97: Không gắn thẻ XBRL (MD&A) | V97: 01/06/2020 – 31/05/2021 | W97: 20/07/2021 | X97: 0000320187-21-000028 | Y97: revenues_pct_change_reported | Z97: FY2021|revenues_pct_change_reported
A98: FY2022 | B98: % thay đổi doanh thu (NIKE công bố, đã làm tròn) | C98: 0.05 | E98: % | F98: NIKE, Inc. | G98: — | H98: MD&A – % tính từ số GAAP | I98: Khớp nguồn chính thức | J98: 10-K FY2022 | K98: 32 | L98: ITEM 7 – MD&A | M98: Item 7 – MD&A, bảng doanh thu NIKE, Inc., cột “% CHANGE” | N98: TOTAL NIKE, INC. REVENUES | 46,710 | 44,538 | 5 | 6 | 37,403 | 19 | 17 | O98: Khớp với giá trị tự tính từ BCTC (chênh −0,12 điểm %, ngưỡng ±1 điểm %). | P98: Không áp dụng: tỷ lệ % chỉ lấy từ 10-K của chính năm đó. | T98: TOTAL NIKE, INC. REVENUES – % change | U98: Không gắn thẻ XBRL (MD&A) | V98: 01/06/2021 – 31/05/2022 | W98: 21/07/2022 | X98: 0000320187-22-000038 | Y98: revenues_pct_change_reported | Z98: FY2022|revenues_pct_change_reported
A99: FY2023 | B99: % thay đổi doanh thu (NIKE công bố, đã làm tròn) | C99: 0.1 | E99: % | F99: NIKE, Inc. | G99: — | H99: MD&A – % tính từ số GAAP | I99: Khớp nguồn chính thức | J99: 10-K FY2023 | K99: 32 | L99: ITEM 7 – MD&A | M99: Item 7 – MD&A, bảng doanh thu NIKE, Inc., cột “% CHANGE” | N99: TOTAL NIKE, INC. REVENUES | 51,217 | 46,710 | 10 | 16 | 44,538 | 5 | 6 | O99: Khớp với giá trị tự tính từ BCTC (chênh −0,35 điểm %, ngưỡng ±1 điểm %). | P99: Không áp dụng: tỷ lệ % chỉ lấy từ 10-K của chính năm đó. | T99: TOTAL NIKE, INC. REVENUES – % change | U99: Không gắn thẻ XBRL (MD&A) | V99: 01/06/2022 – 31/05/2023 | W99: 20/07/2023 | X99: 0000320187-23-000039 | Y99: revenues_pct_change_reported | Z99: FY2023|revenues_pct_change_reported
A100: FY2024 | B100: % thay đổi doanh thu (NIKE công bố, đã làm tròn) | C100: 0 | E100: % | F100: NIKE, Inc. | G100: — | H100: MD&A – % tính từ số GAAP | I100: Khớp nguồn chính thức | J100: 10-K FY2024 | K100: 34 | L100: ITEM 7 – MD&A | M100: Item 7 – MD&A, bảng doanh thu NIKE, Inc., cột “% CHANGE” | N100: TOTAL NIKE, INC. REVENUES | 51,362 | 51,217 | 0 | 1 | 46,710 | 10 | 16 | O100: Khớp với giá trị tự tính từ BCTC (chênh +0,28 điểm %, ngưỡng ±1 điểm %). | P100: Không áp dụng: tỷ lệ % chỉ lấy từ 10-K của chính năm đó. | T100: TOTAL NIKE, INC. REVENUES – % change | U100: Không gắn thẻ XBRL (MD&A) | V100: 01/06/2023 – 31/05/2024 | W100: 25/07/2024 | X100: 0000320187-24-000044 | Y100: revenues_pct_change_reported | Z100: FY2024|revenues_pct_change_reported
A101: FY2025 | B101: % thay đổi doanh thu (NIKE công bố, đã làm tròn) | C101: -0.1 | E101: % | F101: NIKE, Inc. | G101: — | H101: MD&A – % tính từ số GAAP | I101: Khớp nguồn chính thức | J101: 10-K FY2025 | K101: 33 | L101: ITEM 7 – MD&A | M101: Item 7 – MD&A, bảng doanh thu NIKE, Inc., cột “% CHANGE” | N101: TOTAL NIKE, INC. REVENUES | 46,309 | 51,362 | -10 | -9 | 51,217 | 0 | 1 | O101: Khớp với giá trị tự tính từ BCTC (chênh +0,16 điểm %, ngưỡng ±1 điểm %). | P101: Không áp dụng: tỷ lệ % chỉ lấy từ 10-K của chính năm đó. | T101: TOTAL NIKE, INC. REVENUES – % change | U101: Không gắn thẻ XBRL (MD&A) | V101: 01/06/2024 – 31/05/2025 | W101: 17/07/2025 | X101: 0000320187-25-000047 | Y101: revenues_pct_change_reported | Z101: FY2025|revenues_pct_change_reported
A102: FY2026 | B102: % thay đổi doanh thu (NIKE công bố, đã làm tròn) | C102: 0 | E102: % | F102: NIKE, Inc. | G102: — | H102: MD&A – % tính từ số GAAP | I102: Khớp nguồn chính thức | J102: 10-K FY2026 | K102: 32 | L102: ITEM 7 – MD&A | M102: Item 7 – MD&A, bảng doanh thu NIKE, Inc., cột “% CHANGE” | N102: TOTAL NIKE, INC. REVENUES | 46,398 | 46,309 | 0 | -2 | 51,362 | -10 | -9 | O102: Khớp với giá trị tự tính từ BCTC (chênh +0,19 điểm %, ngưỡng ±1 điểm %). | P102: Không áp dụng: tỷ lệ % chỉ lấy từ 10-K của chính năm đó. | T102: TOTAL NIKE, INC. REVENUES – % change | U102: Không gắn thẻ XBRL (MD&A) | V102: 01/06/2025 – 31/05/2026 | W102: 15/07/2026 | X102: 0000320187-26-000088 | Y102: revenues_pct_change_reported | Z102: FY2026|revenues_pct_change_reported
A103: FY2020 | B103: % thay đổi doanh thu loại trừ tỷ giá | C103: -0.02 | E103: % | F103: NIKE, Inc. | G103: — | H103: Non-GAAP – NIKE định nghĩa | I103: Khớp nguồn chính thức | J103: 10-K FY2020 | K103: 31 | L103: ITEM 7 – MD&A | M103: Item 7 – MD&A, bảng doanh thu NIKE, Inc., cột “% CHANGE EXCLUDING CURRENCY CHANGES” | N103: TOTAL NIKE, INC. REVENUES | 37,403 | 39,117 | -4 | -2 | 36,397 | 7 | 11 | O103: Đã đọc lại ngay trên trang 10-K (tr. 31): khớp. Ảnh chụp đối chiếu: handover/bang-chung-doi-chieu/FY2020-bang-doanh-thu-tr31.png. | P103: Không áp dụng: tỷ lệ % chỉ lấy từ 10-K của chính năm đó. | T103: TOTAL NIKE, INC. REVENUES – % change excluding currency changes | U103: Không gắn thẻ XBRL (MD&A) | V103: 01/06/2019 – 31/05/2020 | W103: 24/07/2020 | X103: 0000320187-20-000047 | Y103: revenues_pct_change_cn | Z103: FY2020|revenues_pct_change_cn
A104: FY2021 | B104: % thay đổi doanh thu loại trừ tỷ giá | C104: 0.17 | E104: % | F104: NIKE, Inc. | G104: — | H104: Non-GAAP – NIKE định nghĩa | I104: Khớp nguồn chính thức | J104: 10-K FY2021 | K104: 32 | L104: ITEM 7 – MD&A | M104: Item 7 – MD&A, bảng doanh thu NIKE, Inc., cột “% CHANGE EXCLUDING CURRENCY CHANGES” | N104: TOTAL NIKE, INC. REVENUES | 44,538 | 37,403 | 19 | 17 | 39,117 | -4 | -2 | O104: Đã đọc lại ngay trên trang 10-K (tr. 32): khớp. Ảnh chụp đối chiếu: handover/bang-chung-doi-chieu/FY2021-bang-doanh-thu-tr32.png. | P104: Không áp dụng: tỷ lệ % chỉ lấy từ 10-K của chính năm đó. | T104: TOTAL NIKE, INC. REVENUES – % change excluding currency changes | U104: Không gắn thẻ XBRL (MD&A) | V104: 01/06/2020 – 31/05/2021 | W104: 20/07/2021 | X104: 0000320187-21-000028 | Y104: revenues_pct_change_cn | Z104: FY2021|revenues_pct_change_cn
A105: FY2022 | B105: % thay đổi doanh thu loại trừ tỷ giá | C105: 0.06 | E105: % | F105: NIKE, Inc. | G105: — | H105: Non-GAAP – NIKE định nghĩa | I105: Khớp nguồn chính thức | J105: 10-K FY2022 | K105: 32 | L105: ITEM 7 – MD&A | M105: Item 7 – MD&A, bảng doanh thu NIKE, Inc., cột “% CHANGE EXCLUDING CURRENCY CHANGES” | N105: TOTAL NIKE, INC. REVENUES | 46,710 | 44,538 | 5 | 6 | 37,403 | 19 | 17 | O105: Đã đọc lại ngay trên trang 10-K (tr. 32): khớp. Ảnh chụp đối chiếu: handover/bang-chung-doi-chieu/FY2022-bang-doanh-thu-tr32.png. | P105: Không áp dụng: tỷ lệ % chỉ lấy từ 10-K của chính năm đó. | T105: TOTAL NIKE, INC. REVENUES – % change excluding currency changes | U105: Không gắn thẻ XBRL (MD&A) | V105: 01/06/2021 – 31/05/2022 | W105: 21/07/2022 | X105: 0000320187-22-000038 | Y105: revenues_pct_change_cn | Z105: FY2022|revenues_pct_change_cn
A106: FY2023 | B106: % thay đổi doanh thu loại trừ tỷ giá | C106: 0.16 | E106: % | F106: NIKE, Inc. | G106: — | H106: Non-GAAP – NIKE định nghĩa | I106: Khớp nguồn chính thức | J106: 10-K FY2023 | K106: 32 | L106: ITEM 7 – MD&A | M106: Item 7 – MD&A, bảng doanh thu NIKE, Inc., cột “% CHANGE EXCLUDING CURRENCY CHANGES” | N106: TOTAL NIKE, INC. REVENUES | 51,217 | 46,710 | 10 | 16 | 44,538 | 5 | 6 | O106: Đã đọc lại ngay trên trang 10-K (tr. 32): khớp. Ảnh chụp đối chiếu: handover/bang-chung-doi-chieu/FY2023-bang-doanh-thu-tr32.png. | P106: Không áp dụng: tỷ lệ % chỉ lấy từ 10-K của chính năm đó. | T106: TOTAL NIKE, INC. REVENUES – % change excluding currency changes | U106: Không gắn thẻ XBRL (MD&A) | V106: 01/06/2022 – 31/05/2023 | W106: 20/07/2023 | X106: 0000320187-23-000039 | Y106: revenues_pct_change_cn | Z106: FY2023|revenues_pct_change_cn
A107: FY2024 | B107: % thay đổi doanh thu loại trừ tỷ giá | C107: 0.01 | E107: % | F107: NIKE, Inc. | G107: — | H107: Non-GAAP – NIKE định nghĩa | I107: Khớp nguồn chính thức | J107: 10-K FY2024 | K107: 34 | L107: ITEM 7 – MD&A | M107: Item 7 – MD&A, bảng doanh thu NIKE, Inc., cột “% CHANGE EXCLUDING CURRENCY CHANGES” | N107: TOTAL NIKE, INC. REVENUES | 51,362 | 51,217 | 0 | 1 | 46,710 | 10 | 16 | O107: Đã đọc lại ngay trên trang 10-K (tr. 34): khớp. Ảnh chụp đối chiếu: handover/bang-chung-doi-chieu/FY2024-bang-doanh-thu-tr34.png. | P107: Không áp dụng: tỷ lệ % chỉ lấy từ 10-K của chính năm đó. | T107: TOTAL NIKE, INC. REVENUES – % change excluding currency changes | U107: Không gắn thẻ XBRL (MD&A) | V107: 01/06/2023 – 31/05/2024 | W107: 25/07/2024 | X107: 0000320187-24-000044 | Y107: revenues_pct_change_cn | Z107: FY2024|revenues_pct_change_cn
... A109: FY2026 | B109: % thay đổi doanh thu loại trừ tỷ giá | C109: -0.02 | E109: % | F109: NIKE, Inc. | G109: — | H109: Non-GAAP – NIKE định nghĩa | I109: Khớp nguồn chính thức | J109: 10-K FY2026 | K109: 32 | L109: ITEM 7 – MD&A | M109: Item 7 – MD&A, bảng doanh thu NIKE, Inc., cột “% CHANGE EXCLUDING CURRENCY CHANGES” | N109: TOTAL NIKE, INC. REVENUES | 46,398 | 46,309 | 0 | -2 | 51,362 | -10 | -9 | O109: Đã đọc lại ngay trên trang 10-K (tr. 32): khớp. Ảnh chụp đối chiếu: handover/bang-chung-doi-chieu/FY2026-bang-doanh-thu-tr32.png. | P109: Không áp dụng: tỷ lệ % chỉ lấy từ 10-K của chính năm đó. | T109: TOTAL NIKE, INC. REVENUES – % change excluding currency changes | U109: Không gắn thẻ XBRL (MD&A) | V109: 01/06/2025 – 31/05/2026 | W109: 15/07/2026 | X109: 0000320187-26-000088 | Y109: revenues_pct_change_cn | Z109: FY2026|revenues_pct_change_cn

Sheet 03 Kênh phân phối
A1: Kênh phân phối – NIKE Brand
A2: Doanh thu NIKE Direct, bán buôn, Global Brand Divisions, doanh số Digital và tăng trưởng theo kênh NIKE công bố. Converse và Corporate chỉ để đối chiếu.
A4: Năm tài chính | B4: Chỉ tiêu | C4: Giá trị | D4: Giá trị năm trước (cùng 10-K) | E4: Đơn vị | F4: Phạm vi báo cáo | G4: Kênh | H4: Loại số liệu | I4: Trạng thái dữ liệu | J4: Tài liệu nguồn (mở trên SEC) | K4: Trang | L4: Mục trong 10-K | M4: Vị trí chi tiết | N4: Số hoặc câu hiển thị trong tài liệu | O4: Đối chiếu tự động | P4: Trình bày lại ở 10-K sau | Q4: Người xác minh | R4: Ngày xác minh | S4: Ghi chú của nhóm | T4: Dòng trong 10-K (tiếng Anh) | U4: Thẻ XBRL | V4: Kỳ báo cáo | W4: Ngày nộp SEC | X4: Số accession | Y4: Mã chỉ tiêu | Z4: Mã quan sát
A5: FY2020 | B5: Doanh thu NIKE Direct | C5: 12382 | D5: 11753 | E5: triệu USD | F5: NIKE Brand | G5: NIKE Direct | H5: GAAP – BCTC đã kiểm toán | I5: Khớp nguồn chính thức | J5: 10-K FY2020 | K5: 88 | L5: NOTE 16 — REVENUES | M5: Item 8 – Note “Revenues”, bảng phân tách doanh thu, cột “Total NIKE Brand”, dòng “Sales through Direct to Consumer” | N5: 12,382 | O5: Khớp bảng doanh thu trong MD&A (trang 31). | P5: Không thay đổi khi trình bày lại trong 10-K FY2021, FY2022. | T5: Sales through Direct to Consumer (NIKE Brand) | U5: us-gaap:RevenueFromContractWithCustomerExcludingAssessedTax [ConsolidationItemsAxis=OperatingSegmentsMember; ContractWithCustomerSalesChannelAxis=SalesChannelDirectlyToConsumerMember; StatementBusinessSegmentsAxis=NIKEBrandMember] | V5: 01/06/2019 – 31/05/2020 | W5: 24/07/2020 | X5: 0000320187-20-000047 | Y5: nike_direct_revenue | Z5: FY2020|nike_direct_revenue
A6: FY2021 | B6: Doanh thu NIKE Direct | C6: 16370 | D6: 12382 | E6: triệu USD | F6: NIKE Brand | G6: NIKE Direct | H6: GAAP – BCTC đã kiểm toán | I6: Khớp nguồn chính thức | J6: 10-K FY2021 | K6: 86 | L6: NOTE 16 — REVENUES | M6: Item 8 – Note “Revenues”, bảng phân tách doanh thu, cột “Total NIKE Brand”, dòng “Sales through Direct to Consumer” | N6: 16,370 | O6: Khớp bảng doanh thu trong MD&A (trang 32). | P6: Không thay đổi khi trình bày lại trong 10-K FY2022, FY2023. | T6: Sales through Direct to Consumer (NIKE Brand) | U6: us-gaap:RevenueFromContractWithCustomerExcludingAssessedTax [ConsolidationItemsAxis=OperatingSegmentsMember; ContractWithCustomerSalesChannelAxis=SalesChannelDirectlyToConsumerMember; StatementBusinessSegmentsAxis=NIKEBrandMember] | V6: 01/06/2020 – 31/05/2021 | W6: 20/07/2021 | X6: 0000320187-21-000028 | Y6: nike_direct_revenue | Z6: FY2021|nike_direct_revenue
A7: FY2022 | B7: Doanh thu NIKE Direct | C7: 18726 | D7: 16370 | E7: triệu USD | F7: NIKE Brand | G7: NIKE Direct | H7: GAAP – BCTC đã kiểm toán | I7: Khớp nguồn chính thức | J7: 10-K FY2022 | K7: 85 | L7: NOTE 16 — REVENUES | M7: Item 8 – Note “Revenues”, bảng phân tách doanh thu, cột “Total NIKE Brand”, dòng “Sales through Direct to Consumer” | N7: 18,726 | O7: Khớp bảng doanh thu trong MD&A (trang 32). | P7: Không thay đổi khi trình bày lại trong 10-K FY2023, FY2024. | T7: Sales through Direct to Consumer (NIKE Brand) | U7: us-gaap:RevenueFromContractWithCustomerExcludingAssessedTax [ConsolidationItemsAxis=OperatingSegmentsMember; ContractWithCustomerSalesChannelAxis=SalesChannelDirectlyToConsumerMember; StatementBusinessSegmentsAxis=NIKEBrandMember] | V7: 01/06/2021 – 31/05/2022 | W7: 21/07/2022 | X7: 0000320187-22-000038 | Y7: nike_direct_revenue | Z7: FY2022|nike_direct_revenue
A8: FY2023 | B8: Doanh thu NIKE Direct | C8: 21308 | D8: 18726 | E8: triệu USD | F8: NIKE Brand | G8: NIKE Direct | H8: GAAP – BCTC đã kiểm toán | I8: Khớp nguồn chính thức | J8: 10-K FY2023 | K8: 83 | L8: NOTE 14 — REVENUES | M8: Item 8 – Note “Revenues”, bảng phân tách doanh thu, cột “Total NIKE Brand”, dòng “Sales through Direct to Consumer” | N8: 21,308 | O8: Khớp bảng doanh thu trong MD&A (trang 32). | P8: Không thay đổi khi trình bày lại trong 10-K FY2024, FY2025. | T8: Sales through Direct to Consumer (NIKE Brand) | U8: us-gaap:RevenueFromContractWithCustomerExcludingAssessedTax [ConsolidationItemsAxis=OperatingSegmentsMember; ContractWithCustomerSalesChannelAxis=SalesChannelDirectlyToConsumerMember; StatementBusinessSegmentsAxis=NIKEBrandMember] | V8: 01/06/2022 – 31/05/2023 | W8: 20/07/2023 | X8: 0000320187-23-000039 | Y8: nike_direct_revenue | Z8: FY2023|nike_direct_revenue
A9: FY2024 | B9: Doanh thu NIKE Direct | C9: 21519 | D9: 21308 | E9: triệu USD | F9: NIKE Brand | G9: NIKE Direct | H9: GAAP – BCTC đã kiểm toán | I9: Khớp nguồn chính thức | J9: 10-K FY2024 | K9: 84 | L9: NOTE 14 — REVENUES | M9: Item 8 – Note “Revenues”, bảng phân tách doanh thu, cột “Total NIKE Brand”, dòng “Sales through Direct to Consumer” | N9: 21,519 | O9: Khớp bảng doanh thu trong MD&A (trang 34). | P9: Không thay đổi khi trình bày lại trong 10-K FY2025, FY2026. | T9: Sales through Direct to Consumer (NIKE Brand) | U9: us-gaap:RevenueFromContractWithCustomerExcludingAssessedTax [ConsolidationItemsAxis=OperatingSegmentsMember; ContractWithCustomerSalesChannelAxis=SalesChannelDirectlyToConsumerMember; StatementBusinessSegmentsAxis=NIKEBrandMember] | V9: 01/06/2023 – 31/05/2024 | W9: 25/07/2024 | X9: 0000320187-24-000044 | Y9: nike_direct_revenue | Z9: FY2024|nike_direct_revenue
A10: FY2025 | B10: Doanh thu NIKE Direct | C10: 18783 | D10: 21519 | E10: triệu USD | F10: NIKE Brand | G10: NIKE Direct | H10: GAAP – BCTC đã kiểm toán | I10: Khớp nguồn chính thức | J10: 10-K FY2025 | K10: 82 | L10: NOTE 14 — REVENUES | M10: Item 8 – Note “Revenues”, bảng phân tách doanh thu, cột “Total NIKE Brand”, dòng “Sales through Direct to Consumer” | N10: 18,783 | O10: Khớp bảng doanh thu trong MD&A (trang 33). | P10: Không thay đổi khi trình bày lại trong 10-K FY2026. | T10: Sales through Direct to Consumer (NIKE Brand) | U10: us-gaap:RevenueFromContractWithCustomerExcludingAssessedTax [ConsolidationItemsAxis=OperatingSegmentsMember; ContractWithCustomerSalesChannelAxis=SalesChannelDirectlyToConsumerMember; StatementBusinessSegmentsAxis=NIKEBrandMember] | V10: 01/06/2024 – 31/05/2025 | W10: 17/07/2025 | X10: 0000320187-25-000047 | Y10: nike_direct_revenue | Z10: FY2025|nike_direct_revenue
A11: FY2026 | B11: Doanh thu NIKE Direct | C11: 17720 | D11: 18783 | E11: triệu USD | F11: NIKE Brand | G11: NIKE Direct | H11: GAAP – BCTC đã kiểm toán | I11: Khớp nguồn chính thức | J11: 10-K FY2026 | K11: 83 | L11: NOTE 14 — REVENUES | M11: Item 8 – Note “Revenues”, bảng phân tách doanh thu, cột “Total NIKE Brand”, dòng “Sales through Direct to Consumer” | N11: 17,720 | O11: Khớp bảng doanh thu trong MD&A (trang 32). | P11: Chưa có 10-K năm sau để so sánh. | T11: Sales through Direct to Consumer (NIKE Brand) | U11: us-gaap:RevenueFromContractWithCustomerExcludingAssessedTax [ConsolidationItemsAxis=OperatingSegmentsMember; ContractWithCustomerSalesChannelAxis=SalesChannelDirectlyToConsumerMember; StatementBusinessSegmentsAxis=NIKEBrandMember] | V11: 01/06/2025 – 31/05/2026 | W11: 15/07/2026 | X11: 0000320187-26-000088 | Y11: nike_direct_revenue | Z11: FY2026|nike_direct_revenue
A12: FY2020 | B12: Doanh thu bán buôn NIKE Brand | C12: 23156 | D12: 25423 | E12: triệu USD | F12: NIKE Brand | G12: Bán buôn (Wholesale) | H12: GAAP – BCTC đã kiểm toán | I12: Khớp nguồn chính thức | J12: 10-K FY2020 | K12: 88 | L12: NOTE 16 — REVENUES | M12: Item 8 – Note “Revenues”, bảng phân tách doanh thu, cột “Total NIKE Brand”, dòng “Sales to Wholesale Customers” | N12: 23,156 | O12: Khớp bảng doanh thu trong MD&A (trang 31). | P12: Không thay đổi khi trình bày lại trong 10-K FY2021, FY2022. | T12: Sales to Wholesale Customers (NIKE Brand) | U12: us-gaap:RevenueFromContractWithCustomerExcludingAssessedTax [ConsolidationItemsAxis=OperatingSegmentsMember; ContractWithCustomerSalesChannelAxis=SalesChannelWholesaleMember; StatementBusinessSegmentsAxis=NIKEBrandMember] | V12: 01/06/2019 – 31/05/2020 | W12: 24/07/2020 | X12: 0000320187-20-000047 | Y12: nike_brand_wholesale_revenue | Z12: FY2020|nike_brand_wholesale_revenue
A13: FY2021 | B13: Doanh thu bán buôn NIKE Brand | C13: 25898 | D13: 23156 | E13: triệu USD | F13: NIKE Brand | G13: Bán buôn (Wholesale) | H13: GAAP – BCTC đã kiểm toán | I13: Khớp nguồn chính thức | J13: 10-K FY2021 | K13: 86 | L13: NOTE 16 — REVENUES | M13: Item 8 – Note “Revenues”, bảng phân tách doanh thu, cột “Total NIKE Brand”, dòng “Sales to Wholesale Customers” | N13: 25,898 | O13: Khớp bảng doanh thu trong MD&A (trang 32). | P13: Không thay đổi khi trình bày lại trong 10-K FY2022, FY2023. | T13: Sales to Wholesale Customers (NIKE Brand) | U13: us-gaap:RevenueFromContractWithCustomerExcludingAssessedTax [ConsolidationItemsAxis=OperatingSegmentsMember; ContractWithCustomerSalesChannelAxis=SalesChannelWholesaleMember; StatementBusinessSegmentsAxis=NIKEBrandMember] | V13: 01/06/2020 – 31/05/2021 | W13: 20/07/2021 | X13: 0000320187-21-000028 | Y13: nike_brand_wholesale_revenue | Z13: FY2021|nike_brand_wholesale_revenue
A14: FY2022 | B14: Doanh thu bán buôn NIKE Brand | C14: 25608 | D14: 25898 | E14: triệu USD | F14: NIKE Brand | G14: Bán buôn (Wholesale) | H14: GAAP – BCTC đã kiểm toán | I14: Khớp nguồn chính thức | J14: 10-K FY2022 | K14: 85 | L14: NOTE 16 — REVENUES | M14: Item 8 – Note “Revenues”, bảng phân tách doanh thu, cột “Total NIKE Brand”, dòng “Sales to Wholesale Customers” | N14: 25,608 | O14: Khớp bảng doanh thu trong MD&A (trang 32). | P14: Không thay đổi khi trình bày lại trong 10-K FY2023, FY2024. | T14: Sales to Wholesale Customers (NIKE Brand) | U14: us-gaap:RevenueFromContractWithCustomerExcludingAssessedTax [ConsolidationItemsAxis=OperatingSegmentsMember; ContractWithCustomerSalesChannelAxis=SalesChannelWholesaleMember; StatementBusinessSegmentsAxis=NIKEBrandMember] | V14: 01/06/2021 – 31/05/2022 | W14: 21/07/2022 | X14: 0000320187-22-000038 | Y14: nike_brand_wholesale_revenue | Z14: FY2022|nike_brand_wholesale_revenue
A15: FY2023 | B15: Doanh thu bán buôn NIKE Brand | C15: 27397 | D15: 25608 | E15: triệu USD | F15: NIKE Brand | G15: Bán buôn (Wholesale) | H15: GAAP – BCTC đã kiểm toán | I15: Khớp nguồn chính thức | J15: 10-K FY2023 | K15: 83 | L15: NOTE 14 — REVENUES | M15: Item 8 – Note “Revenues”, bảng phân tách doanh thu, cột “Total NIKE Brand”, dòng “Sales to Wholesale Customers” | N15: 27,397 | O15: Khớp bảng doanh thu trong MD&A (trang 32). | P15: Không thay đổi khi trình bày lại trong 10-K FY2024, FY2025. | T15: Sales to Wholesale Customers (NIKE Brand) | U15: us-gaap:RevenueFromContractWithCustomerExcludingAssessedTax [ConsolidationItemsAxis=OperatingSegmentsMember; ContractWithCustomerSalesChannelAxis=SalesChannelWholesaleMember; StatementBusinessSegmentsAxis=NIKEBrandMember] | V15: 01/06/2022 – 31/05/2023 | W15: 20/07/2023 | X15: 0000320187-23-000039 | Y15: nike_brand_wholesale_revenue | Z15: FY2023|nike_brand_wholesale_revenue
A16: FY2024 | B16: Doanh thu bán buôn NIKE Brand | C16: 27758 | D16: 27397 | E16: triệu USD | F16: NIKE Brand | G16: Bán buôn (Wholesale) | H16: GAAP – BCTC đã kiểm toán | I16: Khớp nguồn chính thức | J16: 10-K FY2024 | K16: 84 | L16: NOTE 14 — REVENUES | M16: Item 8 – Note “Revenues”, bảng phân tách doanh thu, cột “Total NIKE Brand”, dòng “Sales to Wholesale Customers” | N16: 27,758 | O16: Khớp bảng doanh thu trong MD&A (trang 34). | P16: Không thay đổi khi trình bày lại trong 10-K FY2025, FY2026. | T16: Sales to Wholesale Customers (NIKE Brand) | U16: us-gaap:RevenueFromContractWithCustomerExcludingAssessedTax [ConsolidationItemsAxis=OperatingSegmentsMember; ContractWithCustomerSalesChannelAxis=SalesChannelWholesaleMember; StatementBusinessSegmentsAxis=NIKEBrandMember] | V16: 01/06/2023 – 31/05/2024 | W16: 25/07/2024 | X16: 0000320187-24-000044 | Y16: nike_brand_wholesale_revenue | Z16: FY2024|nike_brand_wholesale_revenue
... A53: FY2026 | B53: Doanh số NIKE Brand Digital | C53: 8.6 | D53: 9.6 | E53: tỷ USD | F53: NIKE Brand | G53: NIKE Direct – Digital | H53: MD&A – ban điều hành nêu, không kiểm toán | I53: Khớp nguồn chính thức | J53: 10-K FY2026 | K53: 33 | L53: ITEM 7 – MD&A | M53: Item 7 – MD&A, đoạn văn về NIKE Direct (câu trích ở cột “Số hoặc câu hiển thị trong tài liệu”) | N53: NIKE Brand Digital sales were $8.6 billion in fiscal 2026 compared to $9.6 billion in fiscal 2025, with declines primarily due to reduced traffic. | O53: Đã đọc lại ngay trên trang 10-K (tr. 33): khớp. Ảnh chụp đối chiếu: handover/bang-chung-doi-chieu/FY2026-digital-tr33.png. | P53: Chưa có 10-K năm sau để so sánh. | T53: NIKE Brand Digital sales (FY2020–21: “Digital commerce sales”) | U53: Không gắn thẻ XBRL (MD&A) | V53: 01/06/2025 – 31/05/2026 | W53: 15/07/2026 | X53: 0000320187-26-000088 | Y53: nike_brand_digital_sales | Z53: FY2026|nike_brand_digital_sales
A54: FY2020 | B54: Tỷ trọng NIKE Direct do NIKE nêu (xấp xỉ) | C54: 0.35 | E54: % | F54: NIKE Brand | G54: NIKE Direct | H54: MD&A – ban điều hành nêu, không kiểm toán | I54: Khớp nguồn chính thức | J54: 10-K FY2020 | K54: 32 | L54: ITEM 7 – MD&A | M54: Item 7 – MD&A, câu “NIKE Direct revenues represented approximately …% of total NIKE Brand revenues” | N54: On a reported basis, NIKE Direct revenues represented approximately 35% of our total NIKE Brand revenues for fiscal 2020, compared to 32% for fiscal 2019. | O54: Khớp với giá trị tự tính từ BCTC (chênh −0,19 điểm %, ngưỡng ±1 điểm %). | P54: Không thay đổi khi trình bày lại trong 10-K FY2021. | T54: NIKE Direct as approx. % of total NIKE Brand revenues (as stated) | U54: Không gắn thẻ XBRL (MD&A) | V54: 01/06/2019 – 31/05/2020 | W54: 24/07/2020 | X54: 0000320187-20-000047 | Y54: nike_direct_share_stated | Z54: FY2020|nike_direct_share_stated
A55: FY2021 | B55: Tỷ trọng NIKE Direct do NIKE nêu (xấp xỉ) | C55: 0.39 | E55: % | F55: NIKE Brand | G55: NIKE Direct | H55: MD&A – ban điều hành nêu, không kiểm toán | I55: Khớp nguồn chính thức | J55: 10-K FY2021 | K55: 33 | L55: ITEM 7 – MD&A | M55: Item 7 – MD&A, câu “NIKE Direct revenues represented approximately …% of total NIKE Brand revenues” | N55: On a reported basis, NIKE Direct revenues represented approximately 39% of our total NIKE Brand revenues for fiscal 2021 compared to 35% for fiscal 2020. | O55: Khớp với giá trị tự tính từ BCTC (chênh −0,29 điểm %, ngưỡng ±1 điểm %). | P55: Không thay đổi khi trình bày lại trong 10-K FY2022. | T55: NIKE Direct as approx. % of total NIKE Brand revenues (as stated) | U55: Không gắn thẻ XBRL (MD&A) | V55: 01/06/2020 – 31/05/2021 | W55: 20/07/2021 | X55: 0000320187-21-000028 | Y55: nike_direct_share_stated | Z55: FY2021|nike_direct_share_stated
A56: FY2022 | B56: Tỷ trọng NIKE Direct do NIKE nêu (xấp xỉ) | C56: 0.42 | E56: % | F56: NIKE Brand | G56: NIKE Direct | H56: MD&A – ban điều hành nêu, không kiểm toán | I56: Khớp nguồn chính thức | J56: 10-K FY2022 | K56: 28 | L56: ITEM 7 – MD&A | M56: Item 7 – MD&A, câu “NIKE Direct revenues represented approximately …% of total NIKE Brand revenues” | N56: Over the last several years, as we have executed against the Consumer Direct Acceleration, we have grown our NIKE Direct business to be approximately 42% of total NIKE Brand revenues for fiscal 2022, and we have reduced the number of wholesale accounts globally. | O56: Khớp với giá trị tự tính từ BCTC (chênh +0,14 điểm %, ngưỡng ±1 điểm %). | P56: 10-K năm sau không trình bày lại số này. | T56: NIKE Direct as approx. % of total NIKE Brand revenues (as stated) | U56: Không gắn thẻ XBRL (MD&A) | V56: 01/06/2021 – 31/05/2022 | W56: 21/07/2022 | X56: 0000320187-22-000038 | Y56: nike_direct_share_stated | Z56: FY2022|nike_direct_share_stated
A57: FY2023 | B57: Tỷ trọng NIKE Direct do NIKE nêu (xấp xỉ) | C57: 0.44 | E57: % | F57: NIKE Brand | G57: NIKE Direct | H57: MD&A – ban điều hành nêu, không kiểm toán | I57: Khớp nguồn chính thức | J57: 10-K FY2023 | K57: 28 | L57: ITEM 7 – MD&A | M57: Item 7 – MD&A, câu “NIKE Direct revenues represented approximately …% of total NIKE Brand revenues” | N57: NIKE Direct revenues grew 14% from $18.7 billion in fiscal 2022 to $21.3 billion in fiscal 2023, and represented approximately 44% of total NIKE Brand revenues for fiscal 2023 | O57: Khớp với giá trị tự tính từ BCTC (chênh −0,30 điểm %, ngưỡng ±1 điểm %). | P57: 10-K năm sau không trình bày lại số này. | T57: NIKE Direct as approx. % of total NIKE Brand revenues (as stated) | U57: Không gắn thẻ XBRL (MD&A) | V57: 01/06/2022 – 31/05/2023 | W57: 20/07/2023 | X57: 0000320187-23-000039 | Y57: nike_direct_share_stated | Z57: FY2023|nike_direct_share_stated
A58: FY2024 | B58: Tỷ trọng NIKE Direct do NIKE nêu (xấp xỉ) | C58: 0.44 | E58: % | F58: NIKE Brand | G58: NIKE Direct | H58: MD&A – ban điều hành nêu, không kiểm toán | I58: Khớp nguồn chính thức | J58: 10-K FY2024 | K58: 30 | L58: ITEM 7 – MD&A | M58: Item 7 – MD&A, câu “NIKE Direct revenues represented approximately …% of total NIKE Brand revenues” | N58: NIKE Direct revenues grew 1% from $21.3 billion in fiscal 2023 to $21.5 billion in fiscal 2024, and represented approximately 44% of total NIKE Brand revenues for fiscal 2024 | O58: Khớp với giá trị tự tính từ BCTC (chênh −0,37 điểm %, ngưỡng ±1 điểm %). | P58: 10-K năm sau không trình bày lại số này. | T58: NIKE Direct as approx. % of total NIKE Brand revenues (as stated) | U58: Không gắn thẻ XBRL (MD&A) | V58: 01/06/2023 – 31/05/2024 | W58: 25/07/2024 | X58: 0000320187-24-000044 | Y58: nike_direct_share_stated | Z58: FY2024|nike_direct_share_stated
A59: FY2025 | B59: Tỷ trọng NIKE Direct do NIKE nêu (xấp xỉ) | C59: 0.42 | E59: % | F59: NIKE Brand | G59: NIKE Direct | H59: MD&A – ban điều hành nêu, không kiểm toán | I59: Khớp nguồn chính thức | J59: 10-K FY2025 | K59: 29 | L59: ITEM 7 – MD&A | M59: Item 7 – MD&A, câu “NIKE Direct revenues represented approximately …% of total NIKE Brand revenues” | N59: NIKE Direct revenues declined 13% from $21.5 billion in fiscal 2024 to $18.8 billion in fiscal 2025, and represented approximately 42% of total NIKE Brand revenues for fiscal 2025 | O59: Khớp với giá trị tự tính từ BCTC (chênh +0,01 điểm %, ngưỡng ±1 điểm %). | P59: 10-K năm sau không trình bày lại số này. | T59: NIKE Direct as approx. % of total NIKE Brand revenues (as stated) | U59: Không gắn thẻ XBRL (MD&A) | V59: 01/06/2024 – 31/05/2025 | W59: 17/07/2025 | X59: 0000320187-25-000047 | Y59: nike_direct_share_stated | Z59: FY2025|nike_direct_share_stated
A60: FY2026 | B60: Tỷ trọng NIKE Direct do NIKE nêu (xấp xỉ) | E60: % | F60: NIKE Brand | G60: NIKE Direct | H60: MD&A – ban điều hành nêu, không kiểm toán | I60: Thiếu / không công bố | J60: 10-K FY2026 | L60: — | M60: Item 7 – MD&A, câu “NIKE Direct revenues represented approximately …% of total NIKE Brand revenues” | N60: — | O60: 10-K FY2026 không công bố chỉ tiêu này. | P60: — | T60: NIKE Direct as approx. % of total NIKE Brand revenues (as stated) | U60: Không gắn thẻ XBRL (MD&A) | V60: 01/06/2025 – 31/05/2026 | W60: 15/07/2026 | X60: 0000320187-26-000088 | Y60: nike_direct_share_stated | Z60: FY2026|nike_direct_share_stated
A61: FY2020 | B61: % thay đổi NIKE Direct (NIKE công bố, đã làm tròn) | C61: 0.05 | E61: % | F61: NIKE Brand | G61: NIKE Direct | H61: MD&A – % tính từ số GAAP | I61: Khớp nguồn chính thức | J61: 10-K FY2020 | K61: 31 | L61: ITEM 7 – MD&A | M61: Item 7 – MD&A, bảng doanh thu, mục Supplemental NIKE Brand Revenues Details, cột “% CHANGE” | N61: Sales through NIKE Direct | 12,382 | 11,753 | 5 | 8 | 10,428 | 13 | 16 | O61: Khớp với giá trị tự tính từ BCTC (chênh +0,35 điểm %, ngưỡng ±1 điểm %). | P61: Không áp dụng: tỷ lệ % chỉ lấy từ 10-K của chính năm đó. | T61: Sales through NIKE Direct – % change | U61: Không gắn thẻ XBRL (MD&A) | V61: 01/06/2019 – 31/05/2020 | W61: 24/07/2020 | X61: 0000320187-20-000047 | Y61: nike_direct_pct_change_reported | Z61: FY2020|nike_direct_pct_change_reported
A62: FY2021 | B62: % thay đổi NIKE Direct (NIKE công bố, đã làm tròn) | C62: 0.32 | E62: % | F62: NIKE Brand | G62: NIKE Direct | H62: MD&A – % tính từ số GAAP | I62: Khớp nguồn chính thức | J62: 10-K FY2021 | K62: 32 | L62: ITEM 7 – MD&A | M62: Item 7 – MD&A, bảng doanh thu, mục Supplemental NIKE Brand Revenues Details, cột “% CHANGE” | N62: Sales through NIKE Direct | 16,370 | 12,382 | 32 | 30 | 11,753 | 5 | 8 | O62: Khớp với giá trị tự tính từ BCTC (chênh +0,21 điểm %, ngưỡng ±1 điểm %). | P62: Không áp dụng: tỷ lệ % chỉ lấy từ 10-K của chính năm đó. | T62: Sales through NIKE Direct – % change | U62: Không gắn thẻ XBRL (MD&A) | V62: 01/06/2020 – 31/05/2021 | W62: 20/07/2021 | X62: 0000320187-21-000028 | Y62: nike_direct_pct_change_reported | Z62: FY2021|nike_direct_pct_change_reported
A63: FY2022 | B63: % thay đổi NIKE Direct (NIKE công bố, đã làm tròn) | C63: 0.14 | E63: % | F63: NIKE Brand | G63: NIKE Direct | H63: MD&A – % tính từ số GAAP | I63: Khớp nguồn chính thức | J63: 10-K FY2022 | K63: 32 | L63: ITEM 7 – MD&A | M63: Item 7 – MD&A, bảng doanh thu, mục Supplemental NIKE Brand Revenues Details, cột “% CHANGE” | N63: Sales through NIKE Direct | 18,726 | 16,370 | 14 | 15 | 12,382 | 32 | 30 | O63: Khớp với giá trị tự tính từ BCTC (chênh +0,39 điểm %, ngưỡng ±1 điểm %). | P63: Không áp dụng: tỷ lệ % chỉ lấy từ 10-K của chính năm đó. | T63: Sales through NIKE Direct – % change | U63: Không gắn thẻ XBRL (MD&A) | V63: 01/06/2021 – 31/05/2022 | W63: 21/07/2022 | X63: 0000320187-22-000038 | Y63: nike_direct_pct_change_reported | Z63: FY2022|nike_direct_pct_change_reported
A64: FY2023 | B64: % thay đổi NIKE Direct (NIKE công bố, đã làm tròn) | C64: 0.14 | E64: % | F64: NIKE Brand | G64: NIKE Direct | H64: MD&A – % tính từ số GAAP | I64: Khớp nguồn chính thức | J64: 10-K FY2023 | K64: 32 | L64: ITEM 7 – MD&A | M64: Item 7 – MD&A, bảng doanh thu, mục Supplemental NIKE Brand Revenues Details, cột “% CHANGE” | N64: Sales through NIKE Direct | 21,308 | 18,726 | 14 | 20 | 16,370 | 14 | 15 | O64: Khớp với giá trị tự tính từ BCTC (chênh −0,21 điểm %, ngưỡng ±1 điểm %). | P64: Không áp dụng: tỷ lệ % chỉ lấy từ 10-K của chính năm đó. | T64: Sales through NIKE Direct – % change | U64: Không gắn thẻ XBRL (MD&A) | V64: 01/06/2022 – 31/05/2023 | W64: 20/07/2023 | X64: 0000320187-23-000039 | Y64: nike_direct_pct_change_reported | Z64: FY2023|nike_direct_pct_change_reported
A65: FY2024 | B65: % thay đổi NIKE Direct (NIKE công bố, đã làm tròn) | C65: 0.01 | E65: % | F65: NIKE Brand | G65: NIKE Direct | H65: MD&A – % tính từ số GAAP | I65: Khớp nguồn chính thức | J65: 10-K FY2024 | K65: 34 | L65: ITEM 7 – MD&A | M65: Item 7 – MD&A, bảng doanh thu, mục Supplemental NIKE Brand Revenues Details, cột “% CHANGE” | N65: Sales through NIKE Direct | 21,519 | 21,308 | 1 | 1 | 18,726 | 14 | 20 | O65: Khớp với giá trị tự tính từ BCTC (chênh −0,01 điểm %, ngưỡng ±1 điểm %). | P65: Không áp dụng: tỷ lệ % chỉ lấy từ 10-K của chính năm đó. | T65: Sales through NIKE Direct – % change | U65: Không gắn thẻ XBRL (MD&A) | V65: 01/06/2023 – 31/05/2024 | W65: 25/07/2024 | X65: 0000320187-24-000044 | Y65: nike_direct_pct_change_reported | Z65: FY2024|nike_direct_pct_change_reported
A66: FY2025 | B66: % thay đổi NIKE Direct (NIKE công bố, đã làm tròn) | C66: -0.13 | E66: % | F66: NIKE Brand | G66: NIKE Direct | H66: MD&A – % tính từ số GAAP | I66: Khớp nguồn chính thức | J66: 10-K FY2025 | K66: 33 | L66: ITEM 7 – MD&A | M66: Item 7 – MD&A, bảng doanh thu, mục Supplemental NIKE Brand Revenues Details, cột “% CHANGE” | N66: Sales through NIKE Direct | 18,783 | 21,519 | -13 | -12 | 21,308 | 1 | 1 | O66: Khớp với giá trị tự tính từ BCTC (chênh +0,29 điểm %, ngưỡng ±1 điểm %). | P66: Không áp dụng: tỷ lệ % chỉ lấy từ 10-K của chính năm đó. | T66: Sales through NIKE Direct – % change | U66: Không gắn thẻ XBRL (MD&A) | V66: 01/06/2024 – 31/05/2025 | W66: 17/07/2025 | X66: 0000320187-25-000047 | Y66: nike_direct_pct_change_reported | Z66: FY2025|nike_direct_pct_change_reported
A67: FY2026 | B67: % thay đổi NIKE Direct (NIKE công bố, đã làm tròn) | C67: -0.06 | E67: % | F67: NIKE Brand | G67: NIKE Direct | H67: MD&A – % tính từ số GAAP | I67: Khớp nguồn chính thức | J67: 10-K FY2026 | K67: 32 | L67: ITEM 7 – MD&A | M67: Item 7 – MD&A, bảng doanh thu, mục Supplemental NIKE Brand Revenues Details, cột “% CHANGE” | N67: Sales through NIKE Direct | 17,720 | 18,783 | -6 | -8 | 21,519 | -13 | -12 | O67: Khớp với giá trị tự tính từ BCTC (chênh +0,34 điểm %, ngưỡng ±1 điểm %). | P67: Không áp dụng: tỷ lệ % chỉ lấy từ 10-K của chính năm đó. | T67: Sales through NIKE Direct – % change | U67: Không gắn thẻ XBRL (MD&A) | V67: 01/06/2025 – 31/05/2026 | W67: 15/07/2026 | X67: 0000320187-26-000088 | Y67: nike_direct_pct_change_reported | Z67: FY2026|nike_direct_pct_change_reported
A68: FY2020 | B68: % thay đổi NIKE Direct loại trừ tỷ giá | C68: 0.08 | E68: % | F68: NIKE Brand | G68: NIKE Direct | H68: Non-GAAP – NIKE định nghĩa | I68: Khớp nguồn chính thức | J68: 10-K FY2020 | K68: 31 | L68: ITEM 7 – MD&A | M68: Item 7 – MD&A, bảng doanh thu, mục Supplemental NIKE Brand Revenues Details, cột “% CHANGE EXCLUDING CURRENCY CHANGES” | N68: Sales through NIKE Direct | 12,382 | 11,753 | 5 | 8 | 10,428 | 13 | 16 | O68: Đã đọc lại ngay trên trang 10-K (tr. 31): khớp. Ảnh chụp đối chiếu: handover/bang-chung-doi-chieu/FY2020-bang-doanh-thu-tr31.png. | P68: Không áp dụng: tỷ lệ % chỉ lấy từ 10-K của chính năm đó. | T68: Sales through NIKE Direct – % change excluding currency changes | U68: Không gắn thẻ XBRL (MD&A) | V68: 01/06/2019 – 31/05/2020 | W68: 24/07/2020 | X68: 0000320187-20-000047 | Y68: nike_direct_pct_change_cn | Z68: FY2020|nike_direct_pct_change_cn
A69: FY2021 | B69: % thay đổi NIKE Direct loại trừ tỷ giá | C69: 0.3 | E69: % | F69: NIKE Brand | G69: NIKE Direct | H69: Non-GAAP – NIKE định nghĩa | I69: Khớp nguồn chính thức | J69: 10-K FY2021 | K69: 32 | L69: ITEM 7 – MD&A | M69: Item 7 – MD&A, bảng doanh thu, mục Supplemental NIKE Brand Revenues Details, cột “% CHANGE EXCLUDING CURRENCY CHANGES” | N69: Sales through NIKE Direct | 16,370 | 12,382 | 32 | 30 | 11,753 | 5 | 8 | O69: Đã đọc lại ngay trên trang 10-K (tr. 32): khớp. Ảnh chụp đối chiếu: handover/bang-chung-doi-chieu/FY2021-bang-doanh-thu-tr32.png. | P69: Không áp dụng: tỷ lệ % chỉ lấy từ 10-K của chính năm đó. | T69: Sales through NIKE Direct – % change excluding currency changes | U69: Không gắn thẻ XBRL (MD&A) | V69: 01/06/2020 – 31/05/2021 | W69: 20/07/2021 | X69: 0000320187-21-000028 | Y69: nike_direct_pct_change_cn | Z69: FY2021|nike_direct_pct_change_cn
A70: FY2022 | B70: % thay đổi NIKE Direct loại trừ tỷ giá | C70: 0.15 | E70: % | F70: NIKE Brand | G70: NIKE Direct | H70: Non-GAAP – NIKE định nghĩa | I70: Khớp nguồn chính thức | J70: 10-K FY2022 | K70: 32 | L70: ITEM 7 – MD&A | M70: Item 7 – MD&A, bảng doanh thu, mục Supplemental NIKE Brand Revenues Details, cột “% CHANGE EXCLUDING CURRENCY CHANGES” | N70: Sales through NIKE Direct | 18,726 | 16,370 | 14 | 15 | 12,382 | 32 | 30 | O70: Đã đọc lại ngay trên trang 10-K (tr. 32): khớp. Ảnh chụp đối chiếu: handover/bang-chung-doi-chieu/FY2022-bang-doanh-thu-tr32.png. | P70: Không áp dụng: tỷ lệ % chỉ lấy từ 10-K của chính năm đó. | T70: Sales through NIKE Direct – % change excluding currency changes | U70: Không gắn thẻ XBRL (MD&A) | V70: 01/06/2021 – 31/05/2022 | W70: 21/07/2022 | X70: 0000320187-22-000038 | Y70: nike_direct_pct_change_cn | Z70: FY2022|nike_direct_pct_change_cn
A71: FY2023 | B71: % thay đổi NIKE Direct loại trừ tỷ giá | C71: 0.2 | E71: % | F71: NIKE Brand | G71: NIKE Direct | H71: Non-GAAP – NIKE định nghĩa | I71: Khớp nguồn chính thức | J71: 10-K FY2023 | K71: 32 | L71: ITEM 7 – MD&A | M71: Item 7 – MD&A, bảng doanh thu, mục Supplemental NIKE Brand Revenues Details, cột “% CHANGE EXCLUDING CURRENCY CHANGES” | N71: Sales through NIKE Direct | 21,308 | 18,726 | 14 | 20 | 16,370 | 14 | 15 | O71: Đã đọc lại ngay trên trang 10-K (tr. 32): khớp. Ảnh chụp đối chiếu: handover/bang-chung-doi-chieu/FY2023-bang-doanh-thu-tr32.png. | P71: Không áp dụng: tỷ lệ % chỉ lấy từ 10-K của chính năm đó. | T71: Sales through NIKE Direct – % change excluding currency changes | U71: Không gắn thẻ XBRL (MD&A) | V71: 01/06/2022 – 31/05/2023 | W71: 20/07/2023 | X71: 0000320187-23-000039 | Y71: nike_direct_pct_change_cn | Z71: FY2023|nike_direct_pct_change_cn
A72: FY2024 | B72: % thay đổi NIKE Direct loại trừ tỷ giá | C72: 0.01 | E72: % | F72: NIKE Brand | G72: NIKE Direct | H72: Non-GAAP – NIKE định nghĩa | I72: Khớp nguồn chính thức | J72: 10-K FY2024 | K72: 34 | L72: ITEM 7 – MD&A | M72: Item 7 – MD&A, bảng doanh thu, mục Supplemental NIKE Brand Revenues Details, cột “% CHANGE EXCLUDING CURRENCY CHANGES” | N72: Sales through NIKE Direct | 21,519 | 21,308 | 1 | 1 | 18,726 | 14 | 20 | O72: Đã đọc lại ngay trên trang 10-K (tr. 34): khớp. Ảnh chụp đối chiếu: handover/bang-chung-doi-chieu/FY2024-bang-doanh-thu-tr34.png. | P72: Không áp dụng: tỷ lệ % chỉ lấy từ 10-K của chính năm đó. | T72: Sales through NIKE Direct – % change excluding currency changes | U72: Không gắn thẻ XBRL (MD&A) | V72: 01/06/2023 – 31/05/2024 | W72: 25/07/2024 | X72: 0000320187-24-000044 | Y72: nike_direct_pct_change_cn | Z72: FY2024|nike_direct_pct_change_cn
... A102: FY2026 | B102: % thay đổi NIKE Brand loại trừ tỷ giá | C102: -0.01 | E102: % | F102: NIKE Brand | G102: Tổng NIKE Brand | H102: Non-GAAP – NIKE định nghĩa | I102: Khớp nguồn chính thức | J102: 10-K FY2026 | K102: 32 | L102: ITEM 7 – MD&A | M102: Item 7 – MD&A, bảng doanh thu, mục Supplemental NIKE Brand Revenues Details, cột “% CHANGE EXCLUDING CURRENCY CHANGES” | N102: TOTAL NIKE BRAND REVENUES(3) | 45,222 | 44,714 | 1 | -1 | 49,322 | -9 | -9 | O102: Đã đọc lại ngay trên trang 10-K (tr. 32): khớp. Ảnh chụp đối chiếu: handover/bang-chung-doi-chieu/FY2026-bang-doanh-thu-tr32.png. | P102: Không áp dụng: tỷ lệ % chỉ lấy từ 10-K của chính năm đó. | T102: TOTAL NIKE BRAND REVENUES – % change excluding currency changes | U102: Không gắn thẻ XBRL (MD&A) | V102: 01/06/2025 – 31/05/2026 | W102: 15/07/2026 | X102: 0000320187-26-000088 | Y102: nike_brand_pct_change_cn | Z102: FY2026|nike_brand_pct_change_cn

Sheet 04 KPI & Tính toán
A1: Chỉ số tính toán (KPI) và kiểm tra đối chiếu
A2: Mọi ô số trong sheet này là công thức Excel. Số màu xanh lá lấy từ sheet 02/03 theo năm và mã chỉ tiêu, số màu đen được tính ngay trong sheet này. Sửa số liệu ở sheet 02/03 thì sheet này tự cập nhật. “–” nghĩa là thiếu số liệu đầu vào, không phải bằng 0.
A4: Mã | B4: Chỉ tiêu | C4: Đơn vị | D4: FY2020 | E4: FY2021 | F4: FY2022 | G4: FY2023 | H4: FY2024 | I4: FY2025 | J4: FY2026 | K4: Công thức | L4: Ghi chú và cách đọc
B6: A. Số liệu đầu vào (lấy từ sheet 02 và 03)
A7: revenues | B7: Doanh thu | C7: triệu USD | D7: =IF(INDEX('02 Dữ liệu tài chính'!$C$5:$C$401,MATCH(D$4&"|revenues",'02 Dữ liệu tài chính'!$Z$5:$Z$401,0))="","–",INDEX('02 Dữ liệu tài chính'!$C$5:$C$401,MATCH(D$4&"|revenues",'02 Dữ liệu tài chính'!$Z$5:$Z$401,0))) -> 37403 | E7: =IF(INDEX('02 Dữ liệu tài chính'!$C$5:$C$401,MATCH(E$4&"|revenues",'02 Dữ liệu tài chính'!$Z$5:$Z$401,0))="","–",INDEX('02 Dữ liệu tài chính'!$C$5:$C$401,MATCH(E$4&"|revenues",'02 Dữ liệu tài chính'!$Z$5:$Z$401,0))) -> 44538 | F7: =IF(INDEX('02 Dữ liệu tài chính'!$C$5:$C$401,MATCH(F$4&"|revenues",'02 Dữ liệu tài chính'!$Z$5:$Z$401,0))="","–",INDEX('02 Dữ liệu tài chính'!$C$5:$C$401,MATCH(F$4&"|revenues",'02 Dữ liệu tài chính'!$Z$5:$Z$401,0))) -> 46710 | G7: =IF(INDEX('02 Dữ liệu tài chính'!$C$5:$C$401,MATCH(G$4&"|revenues",'02 Dữ liệu tài chính'!$Z$5:$Z$401,0))="","–",INDEX('02 Dữ liệu tài chính'!$C$5:$C$401,MATCH(G$4&"|revenues",'02 Dữ liệu tài chính'!$Z$5:$Z$401,0))) -> 51217 | H7: =IF(INDEX('02 Dữ liệu tài chính'!$C$5:$C$401,MATCH(H$4&"|revenues",'02 Dữ liệu tài chính'!$Z$5:$Z$401,0))="","–",INDEX('02 Dữ liệu tài chính'!$C$5:$C$401,MATCH(H$4&"|revenues",'02 Dữ liệu tài chính'!$Z$5:$Z$401,0))) -> 51362 | I7: =IF(INDEX('02 Dữ liệu tài chính'!$C$5:$C$401,MATCH(I$4&"|revenues",'02 Dữ liệu tài chính'!$Z$5:$Z$401,0))="","–",INDEX('02 Dữ liệu tài chính'!$C$5:$C$401,MATCH(I$4&"|revenues",'02 Dữ liệu tài chính'!$Z$5:$Z$401,0))) -> 46309 | J7: =IF(INDEX('02 Dữ liệu tài chính'!$C$5:$C$401,MATCH(J$4&"|revenues",'02 Dữ liệu tài chính'!$Z$5:$Z$401,0))="","–",INDEX('02 Dữ liệu tài chính'!$C$5:$C$401,MATCH(J$4&"|revenues",'02 Dữ liệu tài chính'!$Z$5:$Z$401,0))) -> 46398 | K7: Tra cứu sheet “02 Dữ liệu tài chính” theo khóa FY|revenues, cột “Giá trị”.
A8: revenues__prior | B8: Doanh thu – năm trước (cùng 10-K) | C8: triệu USD | D8: =IF(INDEX('02 Dữ liệu tài chính'!$D$5:$D$401,MATCH(D$4&"|revenues",'02 Dữ liệu tài chính'!$Z$5:$Z$401,0))="","–",INDEX('02 Dữ liệu tài chính'!$D$5:$D$401,MATCH(D$4&"|revenues",'02 Dữ liệu tài chính'!$Z$5:$Z$401,0))) -> 39117 | E8: =IF(INDEX('02 Dữ liệu tài chính'!$D$5:$D$401,MATCH(E$4&"|revenues",'02 Dữ liệu tài chính'!$Z$5:$Z$401,0))="","–",INDEX('02 Dữ liệu tài chính'!$D$5:$D$401,MATCH(E$4&"|revenues",'02 Dữ liệu tài chính'!$Z$5:$Z$401,0))) -> 37403 | F8: =IF(INDEX('02 Dữ liệu tài chính'!$D$5:$D$401,MATCH(F$4&"|revenues",'02 Dữ liệu tài chính'!$Z$5:$Z$401,0))="","–",INDEX('02 Dữ liệu tài chính'!$D$5:$D$401,MATCH(F$4&"|revenues",'02 Dữ liệu tài chính'!$Z$5:$Z$401,0))) -> 44538 | G8: =IF(INDEX('02 Dữ liệu tài chính'!$D$5:$D$401,MATCH(G$4&"|revenues",'02 Dữ liệu tài chính'!$Z$5:$Z$401,0))="","–",INDEX('02 Dữ liệu tài chính'!$D$5:$D$401,MATCH(G$4&"|revenues",'02 Dữ liệu tài chính'!$Z$5:$Z$401,0))) -> 46710 | H8: =IF(INDEX('02 Dữ liệu tài chính'!$D$5:$D$401,MATCH(H$4&"|revenues",'02 Dữ liệu tài chính'!$Z$5:$Z$401,0))="","–",INDEX('02 Dữ liệu tài chính'!$D$5:$D$401,MATCH(H$4&"|revenues",'02 Dữ liệu tài chính'!$Z$5:$Z$401,0))) -> 51217 | I8: =IF(INDEX('02 Dữ liệu tài chính'!$D$5:$D$401,MATCH(I$4&"|revenues",'02 Dữ liệu tài chính'!$Z$5:$Z$401,0))="","–",INDEX('02 Dữ liệu tài chính'!$D$5:$D$401,MATCH(I$4&"|revenues",'02 Dữ liệu tài chính'!$Z$5:$Z$401,0))) -> 51362 | J8: =IF(INDEX('02 Dữ liệu tài chính'!$D$5:$D$401,MATCH(J$4&"|revenues",'02 Dữ liệu tài chính'!$Z$5:$Z$401,0))="","–",INDEX('02 Dữ liệu tài chính'!$D$5:$D$401,MATCH(J$4&"|revenues",'02 Dữ liệu tài chính'!$Z$5:$Z$401,0))) -> 46309 | K8: Tra cứu sheet “02 Dữ liệu tài chính” theo khóa FY|revenues, cột “Giá trị năm trước (cùng 10-K)”.
A9: cost_of_sales | B9: Giá vốn hàng bán | C9: triệu USD | D9: =IF(INDEX('02 Dữ liệu tài chính'!$C$5:$C$401,MATCH(D$4&"|cost_of_sales",'02 Dữ liệu tài chính'!$Z$5:$Z$401,0))="","–",INDEX('02 Dữ liệu tài chính'!$C$5:$C$401,MATCH(D$4&"|cost_of_sales",'02 Dữ liệu tài chính'!$Z$5:$Z$401,0))) -> 21162 | E9: =IF(INDEX('02 Dữ liệu tài chính'!$C$5:$C$401,MATCH(E$4&"|cost_of_sales",'02 Dữ liệu tài chính'!$Z$5:$Z$401,0))="","–",INDEX('02 Dữ liệu tài chính'!$C$5:$C$401,MATCH(E$4&"|cost_of_sales",'02 Dữ liệu tài chính'!$Z$5:$Z$401,0))) -> 24576 | F9: =IF(INDEX('02 Dữ liệu tài chính'!$C$5:$C$401,MATCH(F$4&"|cost_of_sales",'02 Dữ liệu tài chính'!$Z$5:$Z$401,0))="","–",INDEX('02 Dữ liệu tài chính'!$C$5:$C$401,MATCH(F$4&"|cost_of_sales",'02 Dữ liệu tài chính'!$Z$5:$Z$401,0))) -> 25231 | G9: =IF(INDEX('02 Dữ liệu tài chính'!$C$5:$C$401,MATCH(G$4&"|cost_of_sales",'02 Dữ liệu tài chính'!$Z$5:$Z$401,0))="","–",INDEX('02 Dữ liệu tài chính'!$C$5:$C$401,MATCH(G$4&"|cost_of_sales",'02 Dữ liệu tài chính'!$Z$5:$Z$401,0))) -> 28925 | H9: =IF(INDEX('02 Dữ liệu tài chính'!$C$5:$C$401,MATCH(H$4&"|cost_of_sales",'02 Dữ liệu tài chính'!$Z$5:$Z$401,0))="","–",INDEX('02 Dữ liệu tài chính'!$C$5:$C$401,MATCH(H$4&"|cost_of_sales",'02 Dữ liệu tài chính'!$Z$5:$Z$401,0))) -> 28475 | I9: =IF(INDEX('02 Dữ liệu tài chính'!$C$5:$C$401,MATCH(I$4&"|cost_of_sales",'02 Dữ liệu tài chính'!$Z$5:$Z$401,0))="","–",INDEX('02 Dữ liệu tài chính'!$C$5:$C$401,MATCH(I$4&"|cost_of_sales",'02 Dữ liệu tài chính'!$Z$5:$Z$401,0))) -> 26519 | J9: =IF(INDEX('02 Dữ liệu tài chính'!$C$5:$C$401,MATCH(J$4&"|cost_of_sales",'02 Dữ liệu tài chính'!$Z$5:$Z$401,0))="","–",INDEX('02 Dữ liệu tài chính'!$C$5:$C$401,MATCH(J$4&"|cost_of_sales",'02 Dữ liệu tài chính'!$Z$5:$Z$401,0))) -> 26487 | K9: Tra cứu sheet “02 Dữ liệu tài chính” theo khóa FY|cost_of_sales, cột “Giá trị”.
A10: gross_profit | B10: Lợi nhuận gộp | C10: triệu USD | D10: =IF(INDEX('02 Dữ liệu tài chính'!$C$5:$C$401,MATCH(D$4&"|gross_profit",'02 Dữ liệu tài chính'!$Z$5:$Z$401,0))="","–",INDEX('02 Dữ liệu tài chính'!$C$5:$C$401,MATCH(D$4&"|gross_profit",'02 Dữ liệu tài chính'!$Z$5:$Z$401,0))) -> 16241 | E10: =IF(INDEX('02 Dữ liệu tài chính'!$C$5:$C$401,MATCH(E$4&"|gross_profit",'02 Dữ liệu tài chính'!$Z$5:$Z$401,0))="","–",INDEX('02 Dữ liệu tài chính'!$C$5:$C$401,MATCH(E$4&"|gross_profit",'02 Dữ liệu tài chính'!$Z$5:$Z$401,0))) -> 19962 | F10: =IF(INDEX('02 Dữ liệu tài chính'!$C$5:$C$401,MATCH(F$4&"|gross_profit",'02 Dữ liệu tài chính'!$Z$5:$Z$401,0))="","–",INDEX('02 Dữ liệu tài chính'!$C$5:$C$401,MATCH(F$4&"|gross_profit",'02 Dữ liệu tài chính'!$Z$5:$Z$401,0))) -> 21479 | G10: =IF(INDEX('02 Dữ liệu tài chính'!$C$5:$C$401,MATCH(G$4&"|gross_profit",'02 Dữ liệu tài chính'!$Z$5:$Z$401,0))="","–",INDEX('02 Dữ liệu tài chính'!$C$5:$C$401,MATCH(G$4&"|gross_profit",'02 Dữ liệu tài chính'!$Z$5:$Z$401,0))) -> 22292 | H10: =IF(INDEX('02 Dữ liệu tài chính'!$C$5:$C$401,MATCH(H$4&"|gross_profit",'02 Dữ liệu tài chính'!$Z$5:$Z$401,0))="","–",INDEX('02 Dữ liệu tài chính'!$C$5:$C$401,MATCH(H$4&"|gross_profit",'02 Dữ liệu tài chính'!$Z$5:$Z$401,0))) -> 22887 | I10: =IF(INDEX('02 Dữ liệu tài chính'!$C$5:$C$401,MATCH(I$4&"|gross_profit",'02 Dữ liệu tài chính'!$Z$5:$Z$401,0))="","–",INDEX('02 Dữ liệu tài chính'!$C$5:$C$401,MATCH(I$4&"|gross_profit",'02 Dữ liệu tài chính'!$Z$5:$Z$401,0))) -> 19790 | J10: =IF(INDEX('02 Dữ liệu tài chính'!$C$5:$C$401,MATCH(J$4&"|gross_profit",'02 Dữ liệu tài chính'!$Z$5:$Z$401,0))="","–",INDEX('02 Dữ liệu tài chính'!$C$5:$C$401,MATCH(J$4&"|gross_profit",'02 Dữ liệu tài chính'!$Z$5:$Z$401,0))) -> 19911 | K10: Tra cứu sheet “02 Dữ liệu tài chính” theo khóa FY|gross_profit, cột “Giá trị”.
A11: demand_creation_expense | B11: Chi phí tạo nhu cầu | C11: triệu USD | D11: =IF(INDEX('02 Dữ liệu tài chính'!$C$5:$C$401,MATCH(D$4&"|demand_creation_expense",'02 Dữ liệu tài chính'!$Z$5:$Z$401,0))="","–",INDEX('02 Dữ liệu tài chính'!$C$5:$C$401,MATCH(D$4&"|demand_creation_expense",'02 Dữ liệu tài chính'!$Z$5:$Z$401,0))) -> 3592 | E11: =IF(INDEX('02 Dữ liệu tài chính'!$C$5:$C$401,MATCH(E$4&"|demand_creation_expense",'02 Dữ liệu tài chính'!$Z$5:$Z$401,0))="","–",INDEX('02 Dữ liệu tài chính'!$C$5:$C$401,MATCH(E$4&"|demand_creation_expense",'02 Dữ liệu tài chính'!$Z$5:$Z$401,0))) -> 3114 | F11: =IF(INDEX('02 Dữ liệu tài chính'!$C$5:$C$401,MATCH(F$4&"|demand_creation_expense",'02 Dữ liệu tài chính'!$Z$5:$Z$401,0))="","–",INDEX('02 Dữ liệu tài chính'!$C$5:$C$401,MATCH(F$4&"|demand_creation_expense",'02 Dữ liệu tài chính'!$Z$5:$Z$401,0))) -> 3850 | G11: =IF(INDEX('02 Dữ liệu tài chính'!$C$5:$C$401,MATCH(G$4&"|demand_creation_expense",'02 Dữ liệu tài chính'!$Z$5:$Z$401,0))="","–",INDEX('02 Dữ liệu tài chính'!$C$5:$C$401,MATCH(G$4&"|demand_creation_expense",'02 Dữ liệu tài chính'!$Z$5:$Z$401,0))) -> 4060 | H11: =IF(INDEX('02 Dữ liệu tài chính'!$C$5:$C$401,MATCH(H$4&"|demand_creation_expense",'02 Dữ liệu tài chính'!$Z$5:$Z$401,0))="","–",INDEX('02 Dữ liệu tài chính'!$C$5:$C$401,MATCH(H$4&"|demand_creation_expense",'02 Dữ liệu tài chính'!$Z$5:$Z$401,0))) -> 4285 | I11: =IF(INDEX('02 Dữ liệu tài chính'!$C$5:$C$401,MATCH(I$4&"|demand_creation_expense",'02 Dữ liệu tài chính'!$Z$5:$Z$401,0))="","–",INDEX('02 Dữ liệu tài chính'!$C$5:$C$401,MATCH(I$4&"|demand_creation_expense",'02 Dữ liệu tài chính'!$Z$5:$Z$401,0))) -> 4689 | J11: =IF(INDEX('02 Dữ liệu tài chính'!$C$5:$C$401,MATCH(J$4&"|demand_creation_expense",'02 Dữ liệu tài chính'!$Z$5:$Z$401,0))="","–",INDEX('02 Dữ liệu tài chính'!$C$5:$C$401,MATCH(J$4&"|demand_creation_expense",'02 Dữ liệu tài chính'!$Z$5:$Z$401,0))) -> 4754 | K11: Tra cứu sheet “02 Dữ liệu tài chính” theo khóa FY|demand_creation_expense, cột “Giá trị”.
A12: operating_overhead_expense | B12: Chi phí vận hành chung | C12: triệu USD | D12: =IF(INDEX('02 Dữ liệu tài chính'!$C$5:$C$401,MATCH(D$4&"|operating_overhead_expense",'02 Dữ liệu tài chính'!$Z$5:$Z$401,0))="","–",INDEX('02 Dữ liệu tài chính'!$C$5:$C$401,MATCH(D$4&"|operating_overhead_expense",'02 Dữ liệu tài chính'!$Z$5:$Z$401,0))) -> 9534 | E12: =IF(INDEX('02 Dữ liệu tài chính'!$C$5:$C$401,MATCH(E$4&"|operating_overhead_expense",'02 Dữ liệu tài chính'!$Z$5:$Z$401,0))="","–",INDEX('02 Dữ liệu tài chính'!$C$5:$C$401,MATCH(E$4&"|operating_overhead_expense",'02 Dữ liệu tài chính'!$Z$5:$Z$401,0))) -> 9911 | F12: =IF(INDEX('02 Dữ liệu tài chính'!$C$5:$C$401,MATCH(F$4&"|operating_overhead_expense",'02 Dữ liệu tài chính'!$Z$5:$Z$401,0))="","–",INDEX('02 Dữ liệu tài chính'!$C$5:$C$401,MATCH(F$4&"|operating_overhead_expense",'02 Dữ liệu tài chính'!$Z$5:$Z$401,0))) -> 10954 | G12: =IF(INDEX('02 Dữ liệu tài chính'!$C$5:$C$401,MATCH(G$4&"|operating_overhead_expense",'02 Dữ liệu tài chính'!$Z$5:$Z$401,0))="","–",INDEX('02 Dữ liệu tài chính'!$C$5:$C$401,MATCH(G$4&"|operating_overhead_expense",'02 Dữ liệu tài chính'!$Z$5:$Z$401,0))) -> 12317 | H12: =IF(INDEX('02 Dữ liệu tài chính'!$C$5:$C$401,MATCH(H$4&"|operating_overhead_expense",'02 Dữ liệu tài chính'!$Z$5:$Z$401,0))="","–",INDEX('02 Dữ liệu tài chính'!$C$5:$C$401,MATCH(H$4&"|operating_overhead_expense",'02 Dữ liệu tài chính'!$Z$5:$Z$401,0))) -> 12291 | I12: =IF(INDEX('02 Dữ liệu tài chính'!$C$5:$C$401,MATCH(I$4&"|operating_overhead_expense",'02 Dữ liệu tài chính'!$Z$5:$Z$401,0))="","–",INDEX('02 Dữ liệu tài chính'!$C$5:$C$401,MATCH(I$4&"|operating_overhead_expense",'02 Dữ liệu tài chính'!$Z$5:$Z$401,0))) -> 11399 | J12: =IF(INDEX('02 Dữ liệu tài chính'!$C$5:$C$401,MATCH(J$4&"|operating_overhead_expense",'02 Dữ liệu tài chính'!$Z$5:$Z$401,0))="","–",INDEX('02 Dữ liệu tài chính'!$C$5:$C$401,MATCH(J$4&"|operating_overhead_expense",'02 Dữ liệu tài chính'!$Z$5:$Z$401,0))) -> 11360 | K12: Tra cứu sheet “02 Dữ liệu tài chính” theo khóa FY|operating_overhead_expense, cột “Giá trị”.
A13: total_selling_admin_expense | B13: Tổng chi phí bán hàng và quản lý (SG&A) | C13: triệu USD | D13: =IF(INDEX('02 Dữ liệu tài chính'!$C$5:$C$401,MATCH(D$4&"|total_selling_admin_expense",'02 Dữ liệu tài chính'!$Z$5:$Z$401,0))="","–",INDEX('02 Dữ liệu tài chính'!$C$5:$C$401,MATCH(D$4&"|total_selling_admin_expense",'02 Dữ liệu tài chính'!$Z$5:$Z$401,0))) -> 13126 | E13: =IF(INDEX('02 Dữ liệu tài chính'!$C$5:$C$401,MATCH(E$4&"|total_selling_admin_expense",'02 Dữ liệu tài chính'!$Z$5:$Z$401,0))="","–",INDEX('02 Dữ liệu tài chính'!$C$5:$C$401,MATCH(E$4&"|total_selling_admin_expense",'02 Dữ liệu tài chính'!$Z$5:$Z$401,0))) -> 13025 | F13: =IF(INDEX('02 Dữ liệu tài chính'!$C$5:$C$401,MATCH(F$4&"|total_selling_admin_expense",'02 Dữ liệu tài chính'!$Z$5:$Z$401,0))="","–",INDEX('02 Dữ liệu tài chính'!$C$5:$C$401,MATCH(F$4&"|total_selling_admin_expense",'02 Dữ liệu tài chính'!$Z$5:$Z$401,0))) -> 14804 | G13: =IF(INDEX('02 Dữ liệu tài chính'!$C$5:$C$401,MATCH(G$4&"|total_selling_admin_expense",'02 Dữ liệu tài chính'!$Z$5:$Z$401,0))="","–",INDEX('02 Dữ liệu tài chính'!$C$5:$C$401,MATCH(G$4&"|total_selling_admin_expense",'02 Dữ liệu tài chính'!$Z$5:$Z$401,0))) -> 16377 | H13: =IF(INDEX('02 Dữ liệu tài chính'!$C$5:$C$401,MATCH(H$4&"|total_selling_admin_expense",'02 Dữ liệu tài chính'!$Z$5:$Z$401,0))="","–",INDEX('02 Dữ liệu tài chính'!$C$5:$C$401,MATCH(H$4&"|total_selling_admin_expense",'02 Dữ liệu tài chính'!$Z$5:$Z$401,0))) -> 16576 | I13: =IF(INDEX('02 Dữ liệu tài chính'!$C$5:$C$401,MATCH(I$4&"|total_selling_admin_expense",'02 Dữ liệu tài chính'!$Z$5:$Z$401,0))="","–",INDEX('02 Dữ liệu tài chính'!$C$5:$C$401,MATCH(I$4&"|total_selling_admin_expense",'02 Dữ liệu tài chính'!$Z$5:$Z$401,0))) -> 16088 | J13: =IF(INDEX('02 Dữ liệu tài chính'!$C$5:$C$401,MATCH(J$4&"|total_selling_admin_expense",'02 Dữ liệu tài chính'!$Z$5:$Z$401,0))="","–",INDEX('02 Dữ liệu tài chính'!$C$5:$C$401,MATCH(J$4&"|total_selling_admin_expense",'02 Dữ liệu tài chính'!$Z$5:$Z$401,0))) -> 16114 | K13: Tra cứu sheet “02 Dữ liệu tài chính” theo khóa FY|total_selling_admin_expense, cột “Giá trị”.
A14: interest_expense_net | B14: Chi phí (thu nhập) lãi thuần | C14: triệu USD | D14: =IF(INDEX('02 Dữ liệu tài chính'!$C$5:$C$401,MATCH(D$4&"|interest_expense_net",'02 Dữ liệu tài chính'!$Z$5:$Z$401,0))="","–",INDEX('02 Dữ liệu tài chính'!$C$5:$C$401,MATCH(D$4&"|interest_expense_net",'02 Dữ liệu tài chính'!$Z$5:$Z$401,0))) -> 89 | E14: =IF(INDEX('02 Dữ liệu tài chính'!$C$5:$C$401,MATCH(E$4&"|interest_expense_net",'02 Dữ liệu tài chính'!$Z$5:$Z$401,0))="","–",INDEX('02 Dữ liệu tài chính'!$C$5:$C$401,MATCH(E$4&"|interest_expense_net",'02 Dữ liệu tài chính'!$Z$5:$Z$401,0))) -> 262 | F14: =IF(INDEX('02 Dữ liệu tài chính'!$C$5:$C$401,MATCH(F$4&"|interest_expense_net",'02 Dữ liệu tài chính'!$Z$5:$Z$401,0))="","–",INDEX('02 Dữ liệu tài chính'!$C$5:$C$401,MATCH(F$4&"|interest_expense_net",'02 Dữ liệu tài chính'!$Z$5:$Z$401,0))) -> 205 | G14: =IF(INDEX('02 Dữ liệu tài chính'!$C$5:$C$401,MATCH(G$4&"|interest_expense_net",'02 Dữ liệu tài chính'!$Z$5:$Z$401,0))="","–",INDEX('02 Dữ liệu tài chính'!$C$5:$C$401,MATCH(G$4&"|interest_expense_net",'02 Dữ liệu tài chính'!$Z$5:$Z$401,0))) -> -6 | H14: =IF(INDEX('02 Dữ liệu tài chính'!$C$5:$C$401,MATCH(H$4&"|interest_expense_net",'02 Dữ liệu tài chính'!$Z$5:$Z$401,0))="","–",INDEX('02 Dữ liệu tài chính'!$C$5:$C$401,MATCH(H$4&"|interest_expense_net",'02 Dữ liệu tài chính'!$Z$5:$Z$401,0))) -> -161 | I14: =IF(INDEX('02 Dữ liệu tài chính'!$C$5:$C$401,MATCH(I$4&"|interest_expense_net",'02 Dữ liệu tài chính'!$Z$5:$Z$401,0))="","–",INDEX('02 Dữ liệu tài chính'!$C$5:$C$401,MATCH(I$4&"|interest_expense_net",'02 Dữ liệu tài chính'!$Z$5:$Z$401,0))) -> -107 | J14: =IF(INDEX('02 Dữ liệu tài chính'!$C$5:$C$401,MATCH(J$4&"|interest_expense_net",'02 Dữ liệu tài chính'!$Z$5:$Z$401,0))="","–",INDEX('02 Dữ liệu tài chính'!$C$5:$C$401,MATCH(J$4&"|interest_expense_net",'02 Dữ liệu tài chính'!$Z$5:$Z$401,0))) -> -50 | K14: Tra cứu sheet “02 Dữ liệu tài chính” theo khóa FY|interest_expense_net, cột “Giá trị”.
A15: other_expense_net | B15: Chi phí (thu nhập) khác thuần | C15: triệu USD | D15: =IF(INDEX('02 Dữ liệu tài chính'!$C$5:$C$401,MATCH(D$4&"|other_expense_net",'02 Dữ liệu tài chính'!$Z$5:$Z$401,0))="","–",INDEX('02 Dữ liệu tài chính'!$C$5:$C$401,MATCH(D$4&"|other_expense_net",'02 Dữ liệu tài chính'!$Z$5:$Z$401,0))) -> 139 | E15: =IF(INDEX('02 Dữ liệu tài chính'!$C$5:$C$401,MATCH(E$4&"|other_expense_net",'02 Dữ liệu tài chính'!$Z$5:$Z$401,0))="","–",INDEX('02 Dữ liệu tài chính'!$C$5:$C$401,MATCH(E$4&"|other_expense_net",'02 Dữ liệu tài chính'!$Z$5:$Z$401,0))) -> 14 | F15: =IF(INDEX('02 Dữ liệu tài chính'!$C$5:$C$401,MATCH(F$4&"|other_expense_net",'02 Dữ liệu tài chính'!$Z$5:$Z$401,0))="","–",INDEX('02 Dữ liệu tài chính'!$C$5:$C$401,MATCH(F$4&"|other_expense_net",'02 Dữ liệu tài chính'!$Z$5:$Z$401,0))) -> -181 | G15: =IF(INDEX('02 Dữ liệu tài chính'!$C$5:$C$401,MATCH(G$4&"|other_expense_net",'02 Dữ liệu tài chính'!$Z$5:$Z$401,0))="","–",INDEX('02 Dữ liệu tài chính'!$C$5:$C$401,MATCH(G$4&"|other_expense_net",'02 Dữ liệu tài chính'!$Z$5:$Z$401,0))) -> -280 | H15: =IF(INDEX('02 Dữ liệu tài chính'!$C$5:$C$401,MATCH(H$4&"|other_expense_net",'02 Dữ liệu tài chính'!$Z$5:$Z$401,0))="","–",INDEX('02 Dữ liệu tài chính'!$C$5:$C$401,MATCH(H$4&"|other_expense_net",'02 Dữ liệu tài chính'!$Z$5:$Z$401,0))) -> -228 | I15: =IF(INDEX('02 Dữ liệu tài chính'!$C$5:$C$401,MATCH(I$4&"|other_expense_net",'02 Dữ liệu tài chính'!$Z$5:$Z$401,0))="","–",INDEX('02 Dữ liệu tài chính'!$C$5:$C$401,MATCH(I$4&"|other_expense_net",'02 Dữ liệu tài chính'!$Z$5:$Z$401,0))) -> -76 | J15: =IF(INDEX('02 Dữ liệu tài chính'!$C$5:$C$401,MATCH(J$4&"|other_expense_net",'02 Dữ liệu tài chính'!$Z$5:$Z$401,0))="","–",INDEX('02 Dữ liệu tài chính'!$C$5:$C$401,MATCH(J$4&"|other_expense_net",'02 Dữ liệu tài chính'!$Z$5:$Z$401,0))) -> -53 | K15: Tra cứu sheet “02 Dữ liệu tài chính” theo khóa FY|other_expense_net, cột “Giá trị”.
A16: income_before_taxes | B16: Lợi nhuận trước thuế | C16: triệu USD | D16: =IF(INDEX('02 Dữ liệu tài chính'!$C$5:$C$401,MATCH(D$4&"|income_before_taxes",'02 Dữ liệu tài chính'!$Z$5:$Z$401,0))="","–",INDEX('02 Dữ liệu tài chính'!$C$5:$C$401,MATCH(D$4&"|income_before_taxes",'02 Dữ liệu tài chính'!$Z$5:$Z$401,0))) -> 2887 | E16: =IF(INDEX('02 Dữ liệu tài chính'!$C$5:$C$401,MATCH(E$4&"|income_before_taxes",'02 Dữ liệu tài chính'!$Z$5:$Z$401,0))="","–",INDEX('02 Dữ liệu tài chính'!$C$5:$C$401,MATCH(E$4&"|income_before_taxes",'02 Dữ liệu tài chính'!$Z$5:$Z$401,0))) -> 6661 | F16: =IF(INDEX('02 Dữ liệu tài chính'!$C$5:$C$401,MATCH(F$4&"|income_before_taxes",'02 Dữ liệu tài chính'!$Z$5:$Z$401,0))="","–",INDEX('02 Dữ liệu tài chính'!$C$5:$C$401,MATCH(F$4&"|income_before_taxes",'02 Dữ liệu tài chính'!$Z$5:$Z$401,0))) -> 6651 | G16: =IF(INDEX('02 Dữ liệu tài chính'!$C$5:$C$401,MATCH(G$4&"|income_before_taxes",'02 Dữ liệu tài chính'!$Z$5:$Z$401,0))="","–",INDEX('02 Dữ liệu tài chính'!$C$5:$C$401,MATCH(G$4&"|income_before_taxes",'02 Dữ liệu tài chính'!$Z$5:$Z$401,0))) -> 6201 | H16: =IF(INDEX('02 Dữ liệu tài chính'!$C$5:$C$401,MATCH(H$4&"|income_before_taxes",'02 Dữ liệu tài chính'!$Z$5:$Z$401,0))="","–",INDEX('02 Dữ liệu tài chính'!$C$5:$C$401,MATCH(H$4&"|income_before_taxes",'02 Dữ liệu tài chính'!$Z$5:$Z$401,0))) -> 6700 | I16: =IF(INDEX('02 Dữ liệu tài chính'!$C$5:$C$401,MATCH(I$4&"|income_before_taxes",'02 Dữ liệu tài chính'!$Z$5:$Z$401,0))="","–",INDEX('02 Dữ liệu tài chính'!$C$5:$C$401,MATCH(I$4&"|income_before_taxes",'02 Dữ liệu tài chính'!$Z$5:$Z$401,0))) -> 3885 | J16: =IF(INDEX('02 Dữ liệu tài chính'!$C$5:$C$401,MATCH(J$4&"|income_before_taxes",'02 Dữ liệu tài chính'!$Z$5:$Z$401,0))="","–",INDEX('02 Dữ liệu tài chính'!$C$5:$C$401,MATCH(J$4&"|income_before_taxes",'02 Dữ liệu tài chính'!$Z$5:$Z$401,0))) -> 3900 | K16: Tra cứu sheet “02 Dữ liệu tài chính” theo khóa FY|income_before_taxes, cột “Giá trị”.
A17: income_tax_expense | B17: Chi phí thuế thu nhập | C17: triệu USD | D17: =IF(INDEX('02 Dữ liệu tài chính'!$C$5:$C$401,MATCH(D$4&"|income_tax_expense",'02 Dữ liệu tài chính'!$Z$5:$Z$401,0))="","–",INDEX('02 Dữ liệu tài chính'!$C$5:$C$401,MATCH(D$4&"|income_tax_expense",'02 Dữ liệu tài chính'!$Z$5:$Z$401,0))) -> 348 | E17: =IF(INDEX('02 Dữ liệu tài chính'!$C$5:$C$401,MATCH(E$4&"|income_tax_expense",'02 Dữ liệu tài chính'!$Z$5:$Z$401,0))="","–",INDEX('02 Dữ liệu tài chính'!$C$5:$C$401,MATCH(E$4&"|income_tax_expense",'02 Dữ liệu tài chính'!$Z$5:$Z$401,0))) -> 934 | F17: =IF(INDEX('02 Dữ liệu tài chính'!$C$5:$C$401,MATCH(F$4&"|income_tax_expense",'02 Dữ liệu tài chính'!$Z$5:$Z$401,0))="","–",INDEX('02 Dữ liệu tài chính'!$C$5:$C$401,MATCH(F$4&"|income_tax_expense",'02 Dữ liệu tài chính'!$Z$5:$Z$401,0))) -> 605 | G17: =IF(INDEX('02 Dữ liệu tài chính'!$C$5:$C$401,MATCH(G$4&"|income_tax_expense",'02 Dữ liệu tài chính'!$Z$5:$Z$401,0))="","–",INDEX('02 Dữ liệu tài chính'!$C$5:$C$401,MATCH(G$4&"|income_tax_expense",'02 Dữ liệu tài chính'!$Z$5:$Z$401,0))) -> 1131 | H17: =IF(INDEX('02 Dữ liệu tài chính'!$C$5:$C$401,MATCH(H$4&"|income_tax_expense",'02 Dữ liệu tài chính'!$Z$5:$Z$401,0))="","–",INDEX('02 Dữ liệu tài chính'!$C$5:$C$401,MATCH(H$4&"|income_tax_expense",'02 Dữ liệu tài chính'!$Z$5:$Z$401,0))) -> 1000 | I17: =IF(INDEX('02 Dữ liệu tài chính'!$C$5:$C$401,MATCH(I$4&"|income_tax_expense",'02 Dữ liệu tài chính'!$Z$5:$Z$401,0))="","–",INDEX('02 Dữ liệu tài chính'!$C$5:$C$401,MATCH(I$4&"|income_tax_expense",'02 Dữ liệu tài chính'!$Z$5:$Z$401,0))) -> 666 | J17: =IF(INDEX('02 Dữ liệu tài chính'!$C$5:$C$401,MATCH(J$4&"|income_tax_expense",'02 Dữ liệu tài chính'!$Z$5:$Z$401,0))="","–",INDEX('02 Dữ liệu tài chính'!$C$5:$C$401,MATCH(J$4&"|income_tax_expense",'02 Dữ liệu tài chính'!$Z$5:$Z$401,0))) -> 792 | K17: Tra cứu sheet “02 Dữ liệu tài chính” theo khóa FY|income_tax_expense, cột “Giá trị”.
A18: net_income | B18: Lợi nhuận sau thuế | C18: triệu USD | D18: =IF(INDEX('02 Dữ liệu tài chính'!$C$5:$C$401,MATCH(D$4&"|net_income",'02 Dữ liệu tài chính'!$Z$5:$Z$401,0))="","–",INDEX('02 Dữ liệu tài chính'!$C$5:$C$401,MATCH(D$4&"|net_income",'02 Dữ liệu tài chính'!$Z$5:$Z$401,0))) -> 2539 | E18: =IF(INDEX('02 Dữ liệu tài chính'!$C$5:$C$401,MATCH(E$4&"|net_income",'02 Dữ liệu tài chính'!$Z$5:$Z$401,0))="","–",INDEX('02 Dữ liệu tài chính'!$C$5:$C$401,MATCH(E$4&"|net_income",'02 Dữ liệu tài chính'!$Z$5:$Z$401,0))) -> 5727 | F18: =IF(INDEX('02 Dữ liệu tài chính'!$C$5:$C$401,MATCH(F$4&"|net_income",'02 Dữ liệu tài chính'!$Z$5:$Z$401,0))="","–",INDEX('02 Dữ liệu tài chính'!$C$5:$C$401,MATCH(F$4&"|net_income",'02 Dữ liệu tài chính'!$Z$5:$Z$401,0))) -> 6046 | G18: =IF(INDEX('02 Dữ liệu tài chính'!$C$5:$C$401,MATCH(G$4&"|net_income",'02 Dữ liệu tài chính'!$Z$5:$Z$401,0))="","–",INDEX('02 Dữ liệu tài chính'!$C$5:$C$401,MATCH(G$4&"|net_income",'02 Dữ liệu tài chính'!$Z$5:$Z$401,0))) -> 5070 | H18: =IF(INDEX('02 Dữ liệu tài chính'!$C$5:$C$401,MATCH(H$4&"|net_income",'02 Dữ liệu tài chính'!$Z$5:$Z$401,0))="","–",INDEX('02 Dữ liệu tài chính'!$C$5:$C$401,MATCH(H$4&"|net_income",'02 Dữ liệu tài chính'!$Z$5:$Z$401,0))) -> 5700 | I18: =IF(INDEX('02 Dữ liệu tài chính'!$C$5:$C$401,MATCH(I$4&"|net_income",'02 Dữ liệu tài chính'!$Z$5:$Z$401,0))="","–",INDEX('02 Dữ liệu tài chính'!$C$5:$C$401,MATCH(I$4&"|net_income",'02 Dữ liệu tài chính'!$Z$5:$Z$401,0))) -> 3219 | J18: =IF(INDEX('02 Dữ liệu tài chính'!$C$5:$C$401,MATCH(J$4&"|net_income",'02 Dữ liệu tài chính'!$Z$5:$Z$401,0))="","–",INDEX('02 Dữ liệu tài chính'!$C$5:$C$401,MATCH(J$4&"|net_income",'02 Dữ liệu tài chính'!$Z$5:$Z$401,0))) -> 3108 | K18: Tra cứu sheet “02 Dữ liệu tài chính” theo khóa FY|net_income, cột “Giá trị”.
A19: inventories | B19: Hàng tồn kho cuối kỳ | C19: triệu USD | D19: =IF(INDEX('02 Dữ liệu tài chính'!$C$5:$C$401,MATCH(D$4&"|inventories",'02 Dữ liệu tài chính'!$Z$5:$Z$401,0))="","–",INDEX('02 Dữ liệu tài chính'!$C$5:$C$401,MATCH(D$4&"|inventories",'02 Dữ liệu tài chính'!$Z$5:$Z$401,0))) -> 7367 | E19: =IF(INDEX('02 Dữ liệu tài chính'!$C$5:$C$401,MATCH(E$4&"|inventories",'02 Dữ liệu tài chính'!$Z$5:$Z$401,0))="","–",INDEX('02 Dữ liệu tài chính'!$C$5:$C$401,MATCH(E$4&"|inventories",'02 Dữ liệu tài chính'!$Z$5:$Z$401,0))) -> 6854 | F19: =IF(INDEX('02 Dữ liệu tài chính'!$C$5:$C$401,MATCH(F$4&"|inventories",'02 Dữ liệu tài chính'!$Z$5:$Z$401,0))="","–",INDEX('02 Dữ liệu tài chính'!$C$5:$C$401,MATCH(F$4&"|inventories",'02 Dữ liệu tài chính'!$Z$5:$Z$401,0))) -> 8420 | G19: =IF(INDEX('02 Dữ liệu tài chính'!$C$5:$C$401,MATCH(G$4&"|inventories",'02 Dữ liệu tài chính'!$Z$5:$Z$401,0))="","–",INDEX('02 Dữ liệu tài chính'!$C$5:$C$401,MATCH(G$4&"|inventories",'02 Dữ liệu tài chính'!$Z$5:$Z$401,0))) -> 8454 | H19: =IF(INDEX('02 Dữ liệu tài chính'!$C$5:$C$401,MATCH(H$4&"|inventories",'02 Dữ liệu tài chính'!$Z$5:$Z$401,0))="","–",INDEX('02 Dữ liệu tài chính'!$C$5:$C$401,MATCH(H$4&"|inventories",'02 Dữ liệu tài chính'!$Z$5:$Z$401,0))) -> 7519 | I19: =IF(INDEX('02 Dữ liệu tài chính'!$C$5:$C$401,MATCH(I$4&"|inventories",'02 Dữ liệu tài chính'!$Z$5:$Z$401,0))="","–",INDEX('02 Dữ liệu tài chính'!$C$5:$C$401,MATCH(I$4&"|inventories",'02 Dữ liệu tài chính'!$Z$5:$Z$401,0))) -> 7489 | J19: =IF(INDEX('02 Dữ liệu tài chính'!$C$5:$C$401,MATCH(J$4&"|inventories",'02 Dữ liệu tài chính'!$Z$5:$Z$401,0))="","–",INDEX('02 Dữ liệu tài chính'!$C$5:$C$401,MATCH(J$4&"|inventories",'02 Dữ liệu tài chính'!$Z$5:$Z$401,0))) -> 7501 | K19: Tra cứu sheet “02 Dữ liệu tài chính” theo khóa FY|inventories, cột “Giá trị”.
A20: inventories__prior | B20: Hàng tồn kho cuối kỳ – năm trước (cùng 10-K) | C20: triệu USD | D20: =IF(INDEX('02 Dữ liệu tài chính'!$D$5:$D$401,MATCH(D$4&"|inventories",'02 Dữ liệu tài chính'!$Z$5:$Z$401,0))="","–",INDEX('02 Dữ liệu tài chính'!$D$5:$D$401,MATCH(D$4&"|inventories",'02 Dữ liệu tài chính'!$Z$5:$Z$401,0))) -> 5622 | E20: =IF(INDEX('02 Dữ liệu tài chính'!$D$5:$D$401,MATCH(E$4&"|inventories",'02 Dữ liệu tài chính'!$Z$5:$Z$401,0))="","–",INDEX('02 Dữ liệu tài chính'!$D$5:$D$401,MATCH(E$4&"|inventories",'02 Dữ liệu tài chính'!$Z$5:$Z$401,0))) -> 7367 | F20: =IF(INDEX('02 Dữ liệu tài chính'!$D$5:$D$401,MATCH(F$4&"|inventories",'02 Dữ liệu tài chính'!$Z$5:$Z$401,0))="","–",INDEX('02 Dữ liệu tài chính'!$D$5:$D$401,MATCH(F$4&"|inventories",'02 Dữ liệu tài chính'!$Z$5:$Z$401,0))) -> 6854 | G20: =IF(INDEX('02 Dữ liệu tài chính'!$D$5:$D$401,MATCH(G$4&"|inventories",'02 Dữ liệu tài chính'!$Z$5:$Z$401,0))="","–",INDEX('02 Dữ liệu tài chính'!$D$5:$D$401,MATCH(G$4&"|inventories",'02 Dữ liệu tài chính'!$Z$5:$Z$401,0))) -> 8420 | H20: =IF(INDEX('02 Dữ liệu tài chính'!$D$5:$D$401,MATCH(H$4&"|inventories",'02 Dữ liệu tài chính'!$Z$5:$Z$401,0))="","–",INDEX('02 Dữ liệu tài chính'!$D$5:$D$401,MATCH(H$4&"|inventories",'02 Dữ liệu tài chính'!$Z$5:$Z$401,0))) -> 8454 | I20: =IF(INDEX('02 Dữ liệu tài chính'!$D$5:$D$401,MATCH(I$4&"|inventories",'02 Dữ liệu tài chính'!$Z$5:$Z$401,0))="","–",INDEX('02 Dữ liệu tài chính'!$D$5:$D$401,MATCH(I$4&"|inventories",'02 Dữ liệu tài chính'!$Z$5:$Z$401,0))) -> 7519 | J20: =IF(INDEX('02 Dữ liệu tài chính'!$D$5:$D$401,MATCH(J$4&"|inventories",'02 Dữ liệu tài chính'!$Z$5:$Z$401,0))="","–",INDEX('02 Dữ liệu tài chính'!$D$5:$D$401,MATCH(J$4&"|inventories",'02 Dữ liệu tài chính'!$Z$5:$Z$401,0))) -> 7489 | K20: Tra cứu sheet “02 Dữ liệu tài chính” theo khóa FY|inventories, cột “Giá trị năm trước (cùng 10-K)”.
A21: ebit_reported | B21: EBIT do NIKE công bố | C21: triệu USD | D21: =IF(INDEX('02 Dữ liệu tài chính'!$C$5:$C$401,MATCH(D$4&"|ebit_reported",'02 Dữ liệu tài chính'!$Z$5:$Z$401,0))="","–",INDEX('02 Dữ liệu tài chính'!$C$5:$C$401,MATCH(D$4&"|ebit_reported",'02 Dữ liệu tài chính'!$Z$5:$Z$401,0))) -> 2976 | E21: =IF(INDEX('02 Dữ liệu tài chính'!$C$5:$C$401,MATCH(E$4&"|ebit_reported",'02 Dữ liệu tài chính'!$Z$5:$Z$401,0))="","–",INDEX('02 Dữ liệu tài chính'!$C$5:$C$401,MATCH(E$4&"|ebit_reported",'02 Dữ liệu tài chính'!$Z$5:$Z$401,0))) -> 6923 | F21: =IF(INDEX('02 Dữ liệu tài chính'!$C$5:$C$401,MATCH(F$4&"|ebit_reported",'02 Dữ liệu tài chính'!$Z$5:$Z$401,0))="","–",INDEX('02 Dữ liệu tài chính'!$C$5:$C$401,MATCH(F$4&"|ebit_reported",'02 Dữ liệu tài chính'!$Z$5:$Z$401,0))) -> 6856 | G21: =IF(INDEX('02 Dữ liệu tài chính'!$C$5:$C$401,MATCH(G$4&"|ebit_reported",'02 Dữ liệu tài chính'!$Z$5:$Z$401,0))="","–",INDEX('02 Dữ liệu tài chính'!$C$5:$C$401,MATCH(G$4&"|ebit_reported",'02 Dữ liệu tài chính'!$Z$5:$Z$401,0))) -> 6195 | H21: =IF(INDEX('02 Dữ liệu tài chính'!$C$5:$C$401,MATCH(H$4&"|ebit_reported",'02 Dữ liệu tài chính'!$Z$5:$Z$401,0))="","–",INDEX('02 Dữ liệu tài chính'!$C$5:$C$401,MATCH(H$4&"|ebit_reported",'02 Dữ liệu tài chính'!$Z$5:$Z$401,0))) -> 6539 | I21: =IF(INDEX('02 Dữ liệu tài chính'!$C$5:$C$401,MATCH(I$4&"|ebit_reported",'02 Dữ liệu tài chính'!$Z$5:$Z$401,0))="","–",INDEX('02 Dữ liệu tài chính'!$C$5:$C$401,MATCH(I$4&"|ebit_reported",'02 Dữ liệu tài chính'!$Z$5:$Z$401,0))) -> 3778 | J21: =IF(INDEX('02 Dữ liệu tài chính'!$C$5:$C$401,MATCH(J$4&"|ebit_reported",'02 Dữ liệu tài chính'!$Z$5:$Z$401,0))="","–",INDEX('02 Dữ liệu tài chính'!$C$5:$C$401,MATCH(J$4&"|ebit_reported",'02 Dữ liệu tài chính'!$Z$5:$Z$401,0))) -> 3850 | K21: Tra cứu sheet “02 Dữ liệu tài chính” theo khóa FY|ebit_reported, cột “Giá trị”.
A22: revenues_pct_change_reported | B22: % thay đổi doanh thu (NIKE công bố, đã làm tròn) | C22: % | D22: =IF(INDEX('02 Dữ liệu tài chính'!$C$5:$C$401,MATCH(D$4&"|revenues_pct_change_reported",'02 Dữ liệu tài chính'!$Z$5:$Z$401,0))="","–",INDEX('02 Dữ liệu tài chính'!$C$5:$C$401,MATCH(D$4&"|revenues_pct_change_reported",'02 Dữ liệu tài chính'!$Z$5:$Z$401,0))) -> -0.04 | E22: =IF(INDEX('02 Dữ liệu tài chính'!$C$5:$C$401,MATCH(E$4&"|revenues_pct_change_reported",'02 Dữ liệu tài chính'!$Z$5:$Z$401,0))="","–",INDEX('02 Dữ liệu tài chính'!$C$5:$C$401,MATCH(E$4&"|revenues_pct_change_reported",'02 Dữ liệu tài chính'!$Z$5:$Z$401,0))) -> 0.19 | F22: =IF(INDEX('02 Dữ liệu tài chính'!$C$5:$C$401,MATCH(F$4&"|revenues_pct_change_reported",'02 Dữ liệu tài chính'!$Z$5:$Z$401,0))="","–",INDEX('02 Dữ liệu tài chính'!$C$5:$C$401,MATCH(F$4&"|revenues_pct_change_reported",'02 Dữ liệu tài chính'!$Z$5:$Z$401,0))) -> 0.05 | G22: =IF(INDEX('02 Dữ liệu tài chính'!$C$5:$C$401,MATCH(G$4&"|revenues_pct_change_reported",'02 Dữ liệu tài chính'!$Z$5:$Z$401,0))="","–",INDEX('02 Dữ liệu tài chính'!$C$5:$C$401,MATCH(G$4&"|revenues_pct_change_reported",'02 Dữ liệu tài chính'!$Z$5:$Z$401,0))) -> 0.1 | H22: =IF(INDEX('02 Dữ liệu tài chính'!$C$5:$C$401,MATCH(H$4&"|revenues_pct_change_reported",'02 Dữ liệu tài chính'!$Z$5:$Z$401,0))="","–",INDEX('02 Dữ liệu tài chính'!$C$5:$C$401,MATCH(H$4&"|revenues_pct_change_reported",'02 Dữ liệu tài chính'!$Z$5:$Z$401,0))) -> 0 | I22: =IF(INDEX('02 Dữ liệu tài chính'!$C$5:$C$401,MATCH(I$4&"|revenues_pct_change_reported",'02 Dữ liệu tài chính'!$Z$5:$Z$401,0))="","–",INDEX('02 Dữ liệu tài chính'!$C$5:$C$401,MATCH(I$4&"|revenues_pct_change_reported",'02 Dữ liệu tài chính'!$Z$5:$Z$401,0))) -> -0.1 | J22: =IF(INDEX('02 Dữ liệu tài chính'!$C$5:$C$401,MATCH(J$4&"|revenues_pct_change_reported",'02 Dữ liệu tài chính'!$Z$5:$Z$401,0))="","–",INDEX('02 Dữ liệu tài chính'!$C$5:$C$401,MATCH(J$4&"|revenues_pct_change_reported",'02 Dữ liệu tài chính'!$Z$5:$Z$401,0))) -> 0 | K22: Tra cứu sheet “02 Dữ liệu tài chính” theo khóa FY|revenues_pct_change_reported, cột “Giá trị”.
A23: nike_direct_revenue | B23: Doanh thu NIKE Direct | C23: triệu USD | D23: =IF(INDEX('03 Kênh phân phối'!$C$5:$C$401,MATCH(D$4&"|nike_direct_revenue",'03 Kênh phân phối'!$Z$5:$Z$401,0))="","–",INDEX('03 Kênh phân phối'!$C$5:$C$401,MATCH(D$4&"|nike_direct_revenue",'03 Kênh phân phối'!$Z$5:$Z$401,0))) -> 12382 | E23: =IF(INDEX('03 Kênh phân phối'!$C$5:$C$401,MATCH(E$4&"|nike_direct_revenue",'03 Kênh phân phối'!$Z$5:$Z$401,0))="","–",INDEX('03 Kênh phân phối'!$C$5:$C$401,MATCH(E$4&"|nike_direct_revenue",'03 Kênh phân phối'!$Z$5:$Z$401,0))) -> 16370 | F23: =IF(INDEX('03 Kênh phân phối'!$C$5:$C$401,MATCH(F$4&"|nike_direct_revenue",'03 Kênh phân phối'!$Z$5:$Z$401,0))="","–",INDEX('03 Kênh phân phối'!$C$5:$C$401,MATCH(F$4&"|nike_direct_revenue",'03 Kênh phân phối'!$Z$5:$Z$401,0))) -> 18726 | G23: =IF(INDEX('03 Kênh phân phối'!$C$5:$C$401,MATCH(G$4&"|nike_direct_revenue",'03 Kênh phân phối'!$Z$5:$Z$401,0))="","–",INDEX('03 Kênh phân phối'!$C$5:$C$401,MATCH(G$4&"|nike_direct_revenue",'03 Kênh phân phối'!$Z$5:$Z$401,0))) -> 21308 | H23: =IF(INDEX('03 Kênh phân phối'!$C$5:$C$401,MATCH(H$4&"|nike_direct_revenue",'03 Kênh phân phối'!$Z$5:$Z$401,0))="","–",INDEX('03 Kênh phân phối'!$C$5:$C$401,MATCH(H$4&"|nike_direct_revenue",'03 Kênh phân phối'!$Z$5:$Z$401,0))) -> 21519 | I23: =IF(INDEX('03 Kênh phân phối'!$C$5:$C$401,MATCH(I$4&"|nike_direct_revenue",'03 Kênh phân phối'!$Z$5:$Z$401,0))="","–",INDEX('03 Kênh phân phối'!$C$5:$C$401,MATCH(I$4&"|nike_direct_revenue",'03 Kênh phân phối'!$Z$5:$Z$401,0))) -> 18783 | J23: =IF(INDEX('03 Kênh phân phối'!$C$5:$C$401,MATCH(J$4&"|nike_direct_revenue",'03 Kênh phân phối'!$Z$5:$Z$401,0))="","–",INDEX('03 Kênh phân phối'!$C$5:$C$401,MATCH(J$4&"|nike_direct_revenue",'03 Kênh phân phối'!$Z$5:$Z$401,0))) -> 17720 | K23: Tra cứu sheet “03 Kênh phân phối” theo khóa FY|nike_direct_revenue, cột “Giá trị”.
A24: nike_direct_revenue__prior | B24: Doanh thu NIKE Direct – năm trước (cùng 10-K) | C24: triệu USD | D24: =IF(INDEX('03 Kênh phân phối'!$D$5:$D$401,MATCH(D$4&"|nike_direct_revenue",'03 Kênh phân phối'!$Z$5:$Z$401,0))="","–",INDEX('03 Kênh phân phối'!$D$5:$D$401,MATCH(D$4&"|nike_direct_revenue",'03 Kênh phân phối'!$Z$5:$Z$401,0))) -> 11753 | E24: =IF(INDEX('03 Kênh phân phối'!$D$5:$D$401,MATCH(E$4&"|nike_direct_revenue",'03 Kênh phân phối'!$Z$5:$Z$401,0))="","–",INDEX('03 Kênh phân phối'!$D$5:$D$401,MATCH(E$4&"|nike_direct_revenue",'03 Kênh phân phối'!$Z$5:$Z$401,0))) -> 12382 | F24: =IF(INDEX('03 Kênh phân phối'!$D$5:$D$401,MATCH(F$4&"|nike_direct_revenue",'03 Kênh phân phối'!$Z$5:$Z$401,0))="","–",INDEX('03 Kênh phân phối'!$D$5:$D$401,MATCH(F$4&"|nike_direct_revenue",'03 Kênh phân phối'!$Z$5:$Z$401,0))) -> 16370 | G24: =IF(INDEX('03 Kênh phân phối'!$D$5:$D$401,MATCH(G$4&"|nike_direct_revenue",'03 Kênh phân phối'!$Z$5:$Z$401,0))="","–",INDEX('03 Kênh phân phối'!$D$5:$D$401,MATCH(G$4&"|nike_direct_revenue",'03 Kênh phân phối'!$Z$5:$Z$401,0))) -> 18726 | H24: =IF(INDEX('03 Kênh phân phối'!$D$5:$D$401,MATCH(H$4&"|nike_direct_revenue",'03 Kênh phân phối'!$Z$5:$Z$401,0))="","–",INDEX('03 Kênh phân phối'!$D$5:$D$401,MATCH(H$4&"|nike_direct_revenue",'03 Kênh phân phối'!$Z$5:$Z$401,0))) -> 21308 | I24: =IF(INDEX('03 Kênh phân phối'!$D$5:$D$401,MATCH(I$4&"|nike_direct_revenue",'03 Kênh phân phối'!$Z$5:$Z$401,0))="","–",INDEX('03 Kênh phân phối'!$D$5:$D$401,MATCH(I$4&"|nike_direct_revenue",'03 Kênh phân phối'!$Z$5:$Z$401,0))) -> 21519 | J24: =IF(INDEX('03 Kênh phân phối'!$D$5:$D$401,MATCH(J$4&"|nike_direct_revenue",'03 Kênh phân phối'!$Z$5:$Z$401,0))="","–",INDEX('03 Kênh phân phối'!$D$5:$D$401,MATCH(J$4&"|nike_direct_revenue",'03 Kênh phân phối'!$Z$5:$Z$401,0))) -> 18783 | K24: Tra cứu sheet “03 Kênh phân phối” theo khóa FY|nike_direct_revenue, cột “Giá trị năm trước (cùng 10-K)”.
A25: nike_brand_wholesale_revenue | B25: Doanh thu bán buôn NIKE Brand | C25: triệu USD | D25: =IF(INDEX('03 Kênh phân phối'!$C$5:$C$401,MATCH(D$4&"|nike_brand_wholesale_revenue",'03 Kênh phân phối'!$Z$5:$Z$401,0))="","–",INDEX('03 Kênh phân phối'!$C$5:$C$401,MATCH(D$4&"|nike_brand_wholesale_revenue",'03 Kênh phân phối'!$Z$5:$Z$401,0))) -> 23156 | E25: =IF(INDEX('03 Kênh phân phối'!$C$5:$C$401,MATCH(E$4&"|nike_brand_wholesale_revenue",'03 Kênh phân phối'!$Z$5:$Z$401,0))="","–",INDEX('03 Kênh phân phối'!$C$5:$C$401,MATCH(E$4&"|nike_brand_wholesale_revenue",'03 Kênh phân phối'!$Z$5:$Z$401,0))) -> 25898 | F25: =IF(INDEX('03 Kênh phân phối'!$C$5:$C$401,MATCH(F$4&"|nike_brand_wholesale_revenue",'03 Kênh phân phối'!$Z$5:$Z$401,0))="","–",INDEX('03 Kênh phân phối'!$C$5:$C$401,MATCH(F$4&"|nike_brand_wholesale_revenue",'03 Kênh phân phối'!$Z$5:$Z$401,0))) -> 25608 | G25: =IF(INDEX('03 Kênh phân phối'!$C$5:$C$401,MATCH(G$4&"|nike_brand_wholesale_revenue",'03 Kênh phân phối'!$Z$5:$Z$401,0))="","–",INDEX('03 Kênh phân phối'!$C$5:$C$401,MATCH(G$4&"|nike_brand_wholesale_revenue",'03 Kênh phân phối'!$Z$5:$Z$401,0))) -> 27397 | H25: =IF(INDEX('03 Kênh phân phối'!$C$5:$C$401,MATCH(H$4&"|nike_brand_wholesale_revenue",'03 Kênh phân phối'!$Z$5:$Z$401,0))="","–",INDEX('03 Kênh phân phối'!$C$5:$C$401,MATCH(H$4&"|nike_brand_wholesale_revenue",'03 Kênh phân phối'!$Z$5:$Z$401,0))) -> 27758 | I25: =IF(INDEX('03 Kênh phân phối'!$C$5:$C$401,MATCH(I$4&"|nike_brand_wholesale_revenue",'03 Kênh phân phối'!$Z$5:$Z$401,0))="","–",INDEX('03 Kênh phân phối'!$C$5:$C$401,MATCH(I$4&"|nike_brand_wholesale_revenue",'03 Kênh phân phối'!$Z$5:$Z$401,0))) -> 25883 | J25: =IF(INDEX('03 Kênh phân phối'!$C$5:$C$401,MATCH(J$4&"|nike_brand_wholesale_revenue",'03 Kênh phân phối'!$Z$5:$Z$401,0))="","–",INDEX('03 Kênh phân phối'!$C$5:$C$401,MATCH(J$4&"|nike_brand_wholesale_revenue",'03 Kênh phân phối'!$Z$5:$Z$401,0))) -> 27453 | K25: Tra cứu sheet “03 Kênh phân phối” theo khóa FY|nike_brand_wholesale_revenue, cột “Giá trị”.
A26: nike_brand_wholesale_revenue__prior | B26: Doanh thu bán buôn NIKE Brand – năm trước (cùng 10-K) | C26: triệu USD | D26: =IF(INDEX('03 Kênh phân phối'!$D$5:$D$401,MATCH(D$4&"|nike_brand_wholesale_revenue",'03 Kênh phân phối'!$Z$5:$Z$401,0))="","–",INDEX('03 Kênh phân phối'!$D$5:$D$401,MATCH(D$4&"|nike_brand_wholesale_revenue",'03 Kênh phân phối'!$Z$5:$Z$401,0))) -> 25423 | E26: =IF(INDEX('03 Kênh phân phối'!$D$5:$D$401,MATCH(E$4&"|nike_brand_wholesale_revenue",'03 Kênh phân phối'!$Z$5:$Z$401,0))="","–",INDEX('03 Kênh phân phối'!$D$5:$D$401,MATCH(E$4&"|nike_brand_wholesale_revenue",'03 Kênh phân phối'!$Z$5:$Z$401,0))) -> 23156 | F26: =IF(INDEX('03 Kênh phân phối'!$D$5:$D$401,MATCH(F$4&"|nike_brand_wholesale_revenue",'03 Kênh phân phối'!$Z$5:$Z$401,0))="","–",INDEX('03 Kênh phân phối'!$D$5:$D$401,MATCH(F$4&"|nike_brand_wholesale_revenue",'03 Kênh phân phối'!$Z$5:$Z$401,0))) -> 25898 | G26: =IF(INDEX('03 Kênh phân phối'!$D$5:$D$401,MATCH(G$4&"|nike_brand_wholesale_revenue",'03 Kênh phân phối'!$Z$5:$Z$401,0))="","–",INDEX('03 Kênh phân phối'!$D$5:$D$401,MATCH(G$4&"|nike_brand_wholesale_revenue",'03 Kênh phân phối'!$Z$5:$Z$401,0))) -> 25608 | H26: =IF(INDEX('03 Kênh phân phối'!$D$5:$D$401,MATCH(H$4&"|nike_brand_wholesale_revenue",'03 Kênh phân phối'!$Z$5:$Z$401,0))="","–",INDEX('03 Kênh phân phối'!$D$5:$D$401,MATCH(H$4&"|nike_brand_wholesale_revenue",'03 Kênh phân phối'!$Z$5:$Z$401,0))) -> 27397 | I26: =IF(INDEX('03 Kênh phân phối'!$D$5:$D$401,MATCH(I$4&"|nike_brand_wholesale_revenue",'03 Kênh phân phối'!$Z$5:$Z$401,0))="","–",INDEX('03 Kênh phân phối'!$D$5:$D$401,MATCH(I$4&"|nike_brand_wholesale_revenue",'03 Kênh phân phối'!$Z$5:$Z$401,0))) -> 27758 | J26: =IF(INDEX('03 Kênh phân phối'!$D$5:$D$401,MATCH(J$4&"|nike_brand_wholesale_revenue",'03 Kênh phân phối'!$Z$5:$Z$401,0))="","–",INDEX('03 Kênh phân phối'!$D$5:$D$401,MATCH(J$4&"|nike_brand_wholesale_revenue",'03 Kênh phân phối'!$Z$5:$Z$401,0))) -> 25883 | K26: Tra cứu sheet “03 Kênh phân phối” theo khóa FY|nike_brand_wholesale_revenue, cột “Giá trị năm trước (cùng 10-K)”.
A27: global_brand_divisions_revenue | B27: Doanh thu Global Brand Divisions | C27: triệu USD | D27: =IF(INDEX('03 Kênh phân phối'!$C$5:$C$401,MATCH(D$4&"|global_brand_divisions_revenue",'03 Kênh phân phối'!$Z$5:$Z$401,0))="","–",INDEX('03 Kênh phân phối'!$C$5:$C$401,MATCH(D$4&"|global_brand_divisions_revenue",'03 Kênh phân phối'!$Z$5:$Z$401,0))) -> 30 | E27: =IF(INDEX('03 Kênh phân phối'!$C$5:$C$401,MATCH(E$4&"|global_brand_divisions_revenue",'03 Kênh phân phối'!$Z$5:$Z$401,0))="","–",INDEX('03 Kênh phân phối'!$C$5:$C$401,MATCH(E$4&"|global_brand_divisions_revenue",'03 Kênh phân phối'!$Z$5:$Z$401,0))) -> 25 | F27: =IF(INDEX('03 Kênh phân phối'!$C$5:$C$401,MATCH(F$4&"|global_brand_divisions_revenue",'03 Kênh phân phối'!$Z$5:$Z$401,0))="","–",INDEX('03 Kênh phân phối'!$C$5:$C$401,MATCH(F$4&"|global_brand_divisions_revenue",'03 Kênh phân phối'!$Z$5:$Z$401,0))) -> 102 | G27: =IF(INDEX('03 Kênh phân phối'!$C$5:$C$401,MATCH(G$4&"|global_brand_divisions_revenue",'03 Kênh phân phối'!$Z$5:$Z$401,0))="","–",INDEX('03 Kênh phân phối'!$C$5:$C$401,MATCH(G$4&"|global_brand_divisions_revenue",'03 Kênh phân phối'!$Z$5:$Z$401,0))) -> 58 | H27: =IF(INDEX('03 Kênh phân phối'!$C$5:$C$401,MATCH(H$4&"|global_brand_divisions_revenue",'03 Kênh phân phối'!$Z$5:$Z$401,0))="","–",INDEX('03 Kênh phân phối'!$C$5:$C$401,MATCH(H$4&"|global_brand_divisions_revenue",'03 Kênh phân phối'!$Z$5:$Z$401,0))) -> 45 | I27: =IF(INDEX('03 Kênh phân phối'!$C$5:$C$401,MATCH(I$4&"|global_brand_divisions_revenue",'03 Kênh phân phối'!$Z$5:$Z$401,0))="","–",INDEX('03 Kênh phân phối'!$C$5:$C$401,MATCH(I$4&"|global_brand_divisions_revenue",'03 Kênh phân phối'!$Z$5:$Z$401,0))) -> 48 | J27: =IF(INDEX('03 Kênh phân phối'!$C$5:$C$401,MATCH(J$4&"|global_brand_divisions_revenue",'03 Kênh phân phối'!$Z$5:$Z$401,0))="","–",INDEX('03 Kênh phân phối'!$C$5:$C$401,MATCH(J$4&"|global_brand_divisions_revenue",'03 Kênh phân phối'!$Z$5:$Z$401,0))) -> 49 | K27: Tra cứu sheet “03 Kênh phân phối” theo khóa FY|global_brand_divisions_revenue, cột “Giá trị”.
A28: nike_brand_revenue | B28: Tổng doanh thu NIKE Brand | C28: triệu USD | D28: =IF(INDEX('03 Kênh phân phối'!$C$5:$C$401,MATCH(D$4&"|nike_brand_revenue",'03 Kênh phân phối'!$Z$5:$Z$401,0))="","–",INDEX('03 Kênh phân phối'!$C$5:$C$401,MATCH(D$4&"|nike_brand_revenue",'03 Kênh phân phối'!$Z$5:$Z$401,0))) -> 35568 | E28: =IF(INDEX('03 Kênh phân phối'!$C$5:$C$401,MATCH(E$4&"|nike_brand_revenue",'03 Kênh phân phối'!$Z$5:$Z$401,0))="","–",INDEX('03 Kênh phân phối'!$C$5:$C$401,MATCH(E$4&"|nike_brand_revenue",'03 Kênh phân phối'!$Z$5:$Z$401,0))) -> 42293 | F28: =IF(INDEX('03 Kênh phân phối'!$C$5:$C$401,MATCH(F$4&"|nike_brand_revenue",'03 Kênh phân phối'!$Z$5:$Z$401,0))="","–",INDEX('03 Kênh phân phối'!$C$5:$C$401,MATCH(F$4&"|nike_brand_revenue",'03 Kênh phân phối'!$Z$5:$Z$401,0))) -> 44436 | G28: =IF(INDEX('03 Kênh phân phối'!$C$5:$C$401,MATCH(G$4&"|nike_brand_revenue",'03 Kênh phân phối'!$Z$5:$Z$401,0))="","–",INDEX('03 Kênh phân phối'!$C$5:$C$401,MATCH(G$4&"|nike_brand_revenue",'03 Kênh phân phối'!$Z$5:$Z$401,0))) -> 48763 | H28: =IF(INDEX('03 Kênh phân phối'!$C$5:$C$401,MATCH(H$4&"|nike_brand_revenue",'03 Kênh phân phối'!$Z$5:$Z$401,0))="","–",INDEX('03 Kênh phân phối'!$C$5:$C$401,MATCH(H$4&"|nike_brand_revenue",'03 Kênh phân phối'!$Z$5:$Z$401,0))) -> 49322 | I28: =IF(INDEX('03 Kênh phân phối'!$C$5:$C$401,MATCH(I$4&"|nike_brand_revenue",'03 Kênh phân phối'!$Z$5:$Z$401,0))="","–",INDEX('03 Kênh phân phối'!$C$5:$C$401,MATCH(I$4&"|nike_brand_revenue",'03 Kênh phân phối'!$Z$5:$Z$401,0))) -> 44714 | J28: =IF(INDEX('03 Kênh phân phối'!$C$5:$C$401,MATCH(J$4&"|nike_brand_revenue",'03 Kênh phân phối'!$Z$5:$Z$401,0))="","–",INDEX('03 Kênh phân phối'!$C$5:$C$401,MATCH(J$4&"|nike_brand_revenue",'03 Kênh phân phối'!$Z$5:$Z$401,0))) -> 45222 | K28: Tra cứu sheet “03 Kênh phân phối” theo khóa FY|nike_brand_revenue, cột “Giá trị”.
A29: nike_brand_revenue__prior | B29: Tổng doanh thu NIKE Brand – năm trước (cùng 10-K) | C29: triệu USD | D29: =IF(INDEX('03 Kênh phân phối'!$D$5:$D$401,MATCH(D$4&"|nike_brand_revenue",'03 Kênh phân phối'!$Z$5:$Z$401,0))="","–",INDEX('03 Kênh phân phối'!$D$5:$D$401,MATCH(D$4&"|nike_brand_revenue",'03 Kênh phân phối'!$Z$5:$Z$401,0))) -> 37218 | E29: =IF(INDEX('03 Kênh phân phối'!$D$5:$D$401,MATCH(E$4&"|nike_brand_revenue",'03 Kênh phân phối'!$Z$5:$Z$401,0))="","–",INDEX('03 Kênh phân phối'!$D$5:$D$401,MATCH(E$4&"|nike_brand_revenue",'03 Kênh phân phối'!$Z$5:$Z$401,0))) -> 35568 | F29: =IF(INDEX('03 Kênh phân phối'!$D$5:$D$401,MATCH(F$4&"|nike_brand_revenue",'03 Kênh phân phối'!$Z$5:$Z$401,0))="","–",INDEX('03 Kênh phân phối'!$D$5:$D$401,MATCH(F$4&"|nike_brand_revenue",'03 Kênh phân phối'!$Z$5:$Z$401,0))) -> 42293 | G29: =IF(INDEX('03 Kênh phân phối'!$D$5:$D$401,MATCH(G$4&"|nike_brand_revenue",'03 Kênh phân phối'!$Z$5:$Z$401,0))="","–",INDEX('03 Kênh phân phối'!$D$5:$D$401,MATCH(G$4&"|nike_brand_revenue",'03 Kênh phân phối'!$Z$5:$Z$401,0))) -> 44436 | H29: =IF(INDEX('03 Kênh phân phối'!$D$5:$D$401,MATCH(H$4&"|nike_brand_revenue",'03 Kênh phân phối'!$Z$5:$Z$401,0))="","–",INDEX('03 Kênh phân phối'!$D$5:$D$401,MATCH(H$4&"|nike_brand_revenue",'03 Kênh phân phối'!$Z$5:$Z$401,0))) -> 48763 | I29: =IF(INDEX('03 Kênh phân phối'!$D$5:$D$401,MATCH(I$4&"|nike_brand_revenue",'03 Kênh phân phối'!$Z$5:$Z$401,0))="","–",INDEX('03 Kênh phân phối'!$D$5:$D$401,MATCH(I$4&"|nike_brand_revenue",'03 Kênh phân phối'!$Z$5:$Z$401,0))) -> 49322 | J29: =IF(INDEX('03 Kênh phân phối'!$D$5:$D$401,MATCH(J$4&"|nike_brand_revenue",'03 Kênh phân phối'!$Z$5:$Z$401,0))="","–",INDEX('03 Kênh phân phối'!$D$5:$D$401,MATCH(J$4&"|nike_brand_revenue",'03 Kênh phân phối'!$Z$5:$Z$401,0))) -> 44714 | K29: Tra cứu sheet “03 Kênh phân phối” theo khóa FY|nike_brand_revenue, cột “Giá trị năm trước (cùng 10-K)”.
A30: converse_revenue | B30: Doanh thu Converse | C30: triệu USD | D30: =IF(INDEX('03 Kênh phân phối'!$C$5:$C$401,MATCH(D$4&"|converse_revenue",'03 Kênh phân phối'!$Z$5:$Z$401,0))="","–",INDEX('03 Kênh phân phối'!$C$5:$C$401,MATCH(D$4&"|converse_revenue",'03 Kênh phân phối'!$Z$5:$Z$401,0))) -> 1846 | E30: =IF(INDEX('03 Kênh phân phối'!$C$5:$C$401,MATCH(E$4&"|converse_revenue",'03 Kênh phân phối'!$Z$5:$Z$401,0))="","–",INDEX('03 Kênh phân phối'!$C$5:$C$401,MATCH(E$4&"|converse_revenue",'03 Kênh phân phối'!$Z$5:$Z$401,0))) -> 2205 | F30: =IF(INDEX('03 Kênh phân phối'!$C$5:$C$401,MATCH(F$4&"|converse_revenue",'03 Kênh phân phối'!$Z$5:$Z$401,0))="","–",INDEX('03 Kênh phân phối'!$C$5:$C$401,MATCH(F$4&"|converse_revenue",'03 Kênh phân phối'!$Z$5:$Z$401,0))) -> 2346 | G30: =IF(INDEX('03 Kênh phân phối'!$C$5:$C$401,MATCH(G$4&"|converse_revenue",'03 Kênh phân phối'!$Z$5:$Z$401,0))="","–",INDEX('03 Kênh phân phối'!$C$5:$C$401,MATCH(G$4&"|converse_revenue",'03 Kênh phân phối'!$Z$5:$Z$401,0))) -> 2427 | H30: =IF(INDEX('03 Kênh phân phối'!$C$5:$C$401,MATCH(H$4&"|converse_revenue",'03 Kênh phân phối'!$Z$5:$Z$401,0))="","–",INDEX('03 Kênh phân phối'!$C$5:$C$401,MATCH(H$4&"|converse_revenue",'03 Kênh phân phối'!$Z$5:$Z$401,0))) -> 2082 | I30: =IF(INDEX('03 Kênh phân phối'!$C$5:$C$401,MATCH(I$4&"|converse_revenue",'03 Kênh phân phối'!$Z$5:$Z$401,0))="","–",INDEX('03 Kênh phân phối'!$C$5:$C$401,MATCH(I$4&"|converse_revenue",'03 Kênh phân phối'!$Z$5:$Z$401,0))) -> 1692 | J30: =IF(INDEX('03 Kênh phân phối'!$C$5:$C$401,MATCH(J$4&"|converse_revenue",'03 Kênh phân phối'!$Z$5:$Z$401,0))="","–",INDEX('03 Kênh phân phối'!$C$5:$C$401,MATCH(J$4&"|converse_revenue",'03 Kênh phân phối'!$Z$5:$Z$401,0))) -> 1174 | K30: Tra cứu sheet “03 Kênh phân phối” theo khóa FY|converse_revenue, cột “Giá trị”.
A31: corporate_revenue | B31: Doanh thu Corporate | C31: triệu USD | D31: =IF(INDEX('03 Kênh phân phối'!$C$5:$C$401,MATCH(D$4&"|corporate_revenue",'03 Kênh phân phối'!$Z$5:$Z$401,0))="","–",INDEX('03 Kênh phân phối'!$C$5:$C$401,MATCH(D$4&"|corporate_revenue",'03 Kênh phân phối'!$Z$5:$Z$401,0))) -> -11 | E31: =IF(INDEX('03 Kênh phân phối'!$C$5:$C$401,MATCH(E$4&"|corporate_revenue",'03 Kênh phân phối'!$Z$5:$Z$401,0))="","–",INDEX('03 Kênh phân phối'!$C$5:$C$401,MATCH(E$4&"|corporate_revenue",'03 Kênh phân phối'!$Z$5:$Z$401,0))) -> 40 | F31: =IF(INDEX('03 Kênh phân phối'!$C$5:$C$401,MATCH(F$4&"|corporate_revenue",'03 Kênh phân phối'!$Z$5:$Z$401,0))="","–",INDEX('03 Kênh phân phối'!$C$5:$C$401,MATCH(F$4&"|corporate_revenue",'03 Kênh phân phối'!$Z$5:$Z$401,0))) -> -72 | G31: =IF(INDEX('03 Kênh phân phối'!$C$5:$C$401,MATCH(G$4&"|corporate_revenue",'03 Kênh phân phối'!$Z$5:$Z$401,0))="","–",INDEX('03 Kênh phân phối'!$C$5:$C$401,MATCH(G$4&"|corporate_revenue",'03 Kênh phân phối'!$Z$5:$Z$401,0))) -> 27 | H31: =IF(INDEX('03 Kênh phân phối'!$C$5:$C$401,MATCH(H$4&"|corporate_revenue",'03 Kênh phân phối'!$Z$5:$Z$401,0))="","–",INDEX('03 Kênh phân phối'!$C$5:$C$401,MATCH(H$4&"|corporate_revenue",'03 Kênh phân phối'!$Z$5:$Z$401,0))) -> -42 | I31: =IF(INDEX('03 Kênh phân phối'!$C$5:$C$401,MATCH(I$4&"|corporate_revenue",'03 Kênh phân phối'!$Z$5:$Z$401,0))="","–",INDEX('03 Kênh phân phối'!$C$5:$C$401,MATCH(I$4&"|corporate_revenue",'03 Kênh phân phối'!$Z$5:$Z$401,0))) -> -97 | J31: =IF(INDEX('03 Kênh phân phối'!$C$5:$C$401,MATCH(J$4&"|corporate_revenue",'03 Kênh phân phối'!$Z$5:$Z$401,0))="","–",INDEX('03 Kênh phân phối'!$C$5:$C$401,MATCH(J$4&"|corporate_revenue",'03 Kênh phân phối'!$Z$5:$Z$401,0))) -> 2 | K31: Tra cứu sheet “03 Kênh phân phối” theo khóa FY|corporate_revenue, cột “Giá trị”.
A32: nike_brand_digital_sales | B32: Doanh số NIKE Brand Digital | C32: tỷ USD | D32: =IF(INDEX('03 Kênh phân phối'!$C$5:$C$401,MATCH(D$4&"|nike_brand_digital_sales",'03 Kênh phân phối'!$Z$5:$Z$401,0))="","–",INDEX('03 Kênh phân phối'!$C$5:$C$401,MATCH(D$4&"|nike_brand_digital_sales",'03 Kênh phân phối'!$Z$5:$Z$401,0))) -> 5.5 | E32: =IF(INDEX('03 Kênh phân phối'!$C$5:$C$401,MATCH(E$4&"|nike_brand_digital_sales",'03 Kênh phân phối'!$Z$5:$Z$401,0))="","–",INDEX('03 Kênh phân phối'!$C$5:$C$401,MATCH(E$4&"|nike_brand_digital_sales",'03 Kênh phân phối'!$Z$5:$Z$401,0))) -> 9.1 | F32: =IF(INDEX('03 Kênh phân phối'!$C$5:$C$401,MATCH(F$4&"|nike_brand_digital_sales",'03 Kênh phân phối'!$Z$5:$Z$401,0))="","–",INDEX('03 Kênh phân phối'!$C$5:$C$401,MATCH(F$4&"|nike_brand_digital_sales",'03 Kênh phân phối'!$Z$5:$Z$401,0))) -> 10.7 | G32: =IF(INDEX('03 Kênh phân phối'!$C$5:$C$401,MATCH(G$4&"|nike_brand_digital_sales",'03 Kênh phân phối'!$Z$5:$Z$401,0))="","–",INDEX('03 Kênh phân phối'!$C$5:$C$401,MATCH(G$4&"|nike_brand_digital_sales",'03 Kênh phân phối'!$Z$5:$Z$401,0))) -> 12.6 | H32: =IF(INDEX('03 Kênh phân phối'!$C$5:$C$401,MATCH(H$4&"|nike_brand_digital_sales",'03 Kênh phân phối'!$Z$5:$Z$401,0))="","–",INDEX('03 Kênh phân phối'!$C$5:$C$401,MATCH(H$4&"|nike_brand_digital_sales",'03 Kênh phân phối'!$Z$5:$Z$401,0))) -> 12.1 | I32: =IF(INDEX('03 Kênh phân phối'!$C$5:$C$401,MATCH(I$4&"|nike_brand_digital_sales",'03 Kênh phân phối'!$Z$5:$Z$401,0))="","–",INDEX('03 Kênh phân phối'!$C$5:$C$401,MATCH(I$4&"|nike_brand_digital_sales",'03 Kênh phân phối'!$Z$5:$Z$401,0))) -> 9.6 | J32: =IF(INDEX('03 Kênh phân phối'!$C$5:$C$401,MATCH(J$4&"|nike_brand_digital_sales",'03 Kênh phân phối'!$Z$5:$Z$401,0))="","–",INDEX('03 Kênh phân phối'!$C$5:$C$401,MATCH(J$4&"|nike_brand_digital_sales",'03 Kênh phân phối'!$Z$5:$Z$401,0))) -> 8.6 | K32: Tra cứu sheet “03 Kênh phân phối” theo khóa FY|nike_brand_digital_sales, cột “Giá trị”.
A33: nike_direct_share_stated | B33: Tỷ trọng NIKE Direct do NIKE nêu (xấp xỉ) | C33: % | D33: =IF(INDEX('03 Kênh phân phối'!$C$5:$C$401,MATCH(D$4&"|nike_direct_share_stated",'03 Kênh phân phối'!$Z$5:$Z$401,0))="","–",INDEX('03 Kênh phân phối'!$C$5:$C$401,MATCH(D$4&"|nike_direct_share_stated",'03 Kênh phân phối'!$Z$5:$Z$401,0))) -> 0.35 | E33: =IF(INDEX('03 Kênh phân phối'!$C$5:$C$401,MATCH(E$4&"|nike_direct_share_stated",'03 Kênh phân phối'!$Z$5:$Z$401,0))="","–",INDEX('03 Kênh phân phối'!$C$5:$C$401,MATCH(E$4&"|nike_direct_share_stated",'03 Kênh phân phối'!$Z$5:$Z$401,0))) -> 0.39 | F33: =IF(INDEX('03 Kênh phân phối'!$C$5:$C$401,MATCH(F$4&"|nike_direct_share_stated",'03 Kênh phân phối'!$Z$5:$Z$401,0))="","–",INDEX('03 Kênh phân phối'!$C$5:$C$401,MATCH(F$4&"|nike_direct_share_stated",'03 Kênh phân phối'!$Z$5:$Z$401,0))) -> 0.42 | G33: =IF(INDEX('03 Kênh phân phối'!$C$5:$C$401,MATCH(G$4&"|nike_direct_share_stated",'03 Kênh phân phối'!$Z$5:$Z$401,0))="","–",INDEX('03 Kênh phân phối'!$C$5:$C$401,MATCH(G$4&"|nike_direct_share_stated",'03 Kênh phân phối'!$Z$5:$Z$401,0))) -> 0.44 | H33: =IF(INDEX('03 Kênh phân phối'!$C$5:$C$401,MATCH(H$4&"|nike_direct_share_stated",'03 Kênh phân phối'!$Z$5:$Z$401,0))="","–",INDEX('03 Kênh phân phối'!$C$5:$C$401,MATCH(H$4&"|nike_direct_share_stated",'03 Kênh phân phối'!$Z$5:$Z$401,0))) -> 0.44 | I33: =IF(INDEX('03 Kênh phân phối'!$C$5:$C$401,MATCH(I$4&"|nike_direct_share_stated",'03 Kênh phân phối'!$Z$5:$Z$401,0))="","–",INDEX('03 Kênh phân phối'!$C$5:$C$401,MATCH(I$4&"|nike_direct_share_stated",'03 Kênh phân phối'!$Z$5:$Z$401,0))) -> 0.42 | J33: =IF(INDEX('03 Kênh phân phối'!$C$5:$C$401,MATCH(J$4&"|nike_direct_share_stated",'03 Kênh phân phối'!$Z$5:$Z$401,0))="","–",INDEX('03 Kênh phân phối'!$C$5:$C$401,MATCH(J$4&"|nike_direct_share_stated",'03 Kênh phân phối'!$Z$5:$Z$401,0))) -> – | K33: Tra cứu sheet “03 Kênh phân phối” theo khóa FY|nike_direct_share_stated, cột “Giá trị”.
A34: nike_direct_pct_change_reported | B34: % thay đổi NIKE Direct (NIKE công bố, đã làm tròn) | C34: % | D34: =IF(INDEX('03 Kênh phân phối'!$C$5:$C$401,MATCH(D$4&"|nike_direct_pct_change_reported",'03 Kênh phân phối'!$Z$5:$Z$401,0))="","–",INDEX('03 Kênh phân phối'!$C$5:$C$401,MATCH(D$4&"|nike_direct_pct_change_reported",'03 Kênh phân phối'!$Z$5:$Z$401,0))) -> 0.05 | E34: =IF(INDEX('03 Kênh phân phối'!$C$5:$C$401,MATCH(E$4&"|nike_direct_pct_change_reported",'03 Kênh phân phối'!$Z$5:$Z$401,0))="","–",INDEX('03 Kênh phân phối'!$C$5:$C$401,MATCH(E$4&"|nike_direct_pct_change_reported",'03 Kênh phân phối'!$Z$5:$Z$401,0))) -> 0.32 | F34: =IF(INDEX('03 Kênh phân phối'!$C$5:$C$401,MATCH(F$4&"|nike_direct_pct_change_reported",'03 Kênh phân phối'!$Z$5:$Z$401,0))="","–",INDEX('03 Kênh phân phối'!$C$5:$C$401,MATCH(F$4&"|nike_direct_pct_change_reported",'03 Kênh phân phối'!$Z$5:$Z$401,0))) -> 0.14 | G34: =IF(INDEX('03 Kênh phân phối'!$C$5:$C$401,MATCH(G$4&"|nike_direct_pct_change_reported",'03 Kênh phân phối'!$Z$5:$Z$401,0))="","–",INDEX('03 Kênh phân phối'!$C$5:$C$401,MATCH(G$4&"|nike_direct_pct_change_reported",'03 Kênh phân phối'!$Z$5:$Z$401,0))) -> 0.14 | H34: =IF(INDEX('03 Kênh phân phối'!$C$5:$C$401,MATCH(H$4&"|nike_direct_pct_change_reported",'03 Kênh phân phối'!$Z$5:$Z$401,0))="","–",INDEX('03 Kênh phân phối'!$C$5:$C$401,MATCH(H$4&"|nike_direct_pct_change_reported",'03 Kênh phân phối'!$Z$5:$Z$401,0))) -> 0.01 | I34: =IF(INDEX('03 Kênh phân phối'!$C$5:$C$401,MATCH(I$4&"|nike_direct_pct_change_reported",'03 Kênh phân phối'!$Z$5:$Z$401,0))="","–",INDEX('03 Kênh phân phối'!$C$5:$C$401,MATCH(I$4&"|nike_direct_pct_change_reported",'03 Kênh phân phối'!$Z$5:$Z$401,0))) -> -0.13 | J34: =IF(INDEX('03 Kênh phân phối'!$C$5:$C$401,MATCH(J$4&"|nike_direct_pct_change_reported",'03 Kênh phân phối'!$Z$5:$Z$401,0))="","–",INDEX('03 Kênh phân phối'!$C$5:$C$401,MATCH(J$4&"|nike_direct_pct_change_reported",'03 Kênh phân phối'!$Z$5:$Z$401,0))) -> -0.06 | K34: Tra cứu sheet “03 Kênh phân phối” theo khóa FY|nike_direct_pct_change_reported, cột “Giá trị”.
A35: nike_brand_wholesale_pct_change_reported | B35: % thay đổi bán buôn (NIKE công bố, đã làm tròn) | C35: % | D35: =IF(INDEX('03 Kênh phân phối'!$C$5:$C$401,MATCH(D$4&"|nike_brand_wholesale_pct_change_reported",'03 Kênh phân phối'!$Z$5:$Z$401,0))="","–",INDEX('03 Kênh phân phối'!$C$5:$C$401,MATCH(D$4&"|nike_brand_wholesale_pct_change_reported",'03 Kênh phân phối'!$Z$5:$Z$401,0))) -> -0.09 | E35: =IF(INDEX('03 Kênh phân phối'!$C$5:$C$401,MATCH(E$4&"|nike_brand_wholesale_pct_change_reported",'03 Kênh phân phối'!$Z$5:$Z$401,0))="","–",INDEX('03 Kênh phân phối'!$C$5:$C$401,MATCH(E$4&"|nike_brand_wholesale_pct_change_reported",'03 Kênh phân phối'!$Z$5:$Z$401,0))) -> 0.12 | F35: =IF(INDEX('03 Kênh phân phối'!$C$5:$C$401,MATCH(F$4&"|nike_brand_wholesale_pct_change_reported",'03 Kênh phân phối'!$Z$5:$Z$401,0))="","–",INDEX('03 Kênh phân phối'!$C$5:$C$401,MATCH(F$4&"|nike_brand_wholesale_pct_change_reported",'03 Kênh phân phối'!$Z$5:$Z$401,0))) -> -0.01 | G35: =IF(INDEX('03 Kênh phân phối'!$C$5:$C$401,MATCH(G$4&"|nike_brand_wholesale_pct_change_reported",'03 Kênh phân phối'!$Z$5:$Z$401,0))="","–",INDEX('03 Kênh phân phối'!$C$5:$C$401,MATCH(G$4&"|nike_brand_wholesale_pct_change_reported",'03 Kênh phân phối'!$Z$5:$Z$401,0))) -> 0.07 | H35: =IF(INDEX('03 Kênh phân phối'!$C$5:$C$401,MATCH(H$4&"|nike_brand_wholesale_pct_change_reported",'03 Kênh phân phối'!$Z$5:$Z$401,0))="","–",INDEX('03 Kênh phân phối'!$C$5:$C$401,MATCH(H$4&"|nike_brand_wholesale_pct_change_reported",'03 Kênh phân phối'!$Z$5:$Z$401,0))) -> 0.01 | I35: =IF(INDEX('03 Kênh phân phối'!$C$5:$C$401,MATCH(I$4&"|nike_brand_wholesale_pct_change_reported",'03 Kênh phân phối'!$Z$5:$Z$401,0))="","–",INDEX('03 Kênh phân phối'!$C$5:$C$401,MATCH(I$4&"|nike_brand_wholesale_pct_change_reported",'03 Kênh phân phối'!$Z$5:$Z$401,0))) -> -0.07 | J35: =IF(INDEX('03 Kênh phân phối'!$C$5:$C$401,MATCH(J$4&"|nike_brand_wholesale_pct_change_reported",'03 Kênh phân phối'!$Z$5:$Z$401,0))="","–",INDEX('03 Kênh phân phối'!$C$5:$C$401,MATCH(J$4&"|nike_brand_wholesale_pct_change_reported",'03 Kênh phân phối'!$Z$5:$Z$401,0))) -> 0.06 | K35: Tra cứu sheet “03 Kênh phân phối” theo khóa FY|nike_brand_wholesale_pct_change_reported, cột “Giá trị”.
A36: nike_brand_pct_change_reported | B36: % thay đổi doanh thu NIKE Brand (NIKE công bố, đã làm tròn) | C36: % | D36: =IF(INDEX('03 Kênh phân phối'!$C$5:$C$401,MATCH(D$4&"|nike_brand_pct_change_reported",'03 Kênh phân phối'!$Z$5:$Z$401,0))="","–",INDEX('03 Kênh phân phối'!$C$5:$C$401,MATCH(D$4&"|nike_brand_pct_change_reported",'03 Kênh phân phối'!$Z$5:$Z$401,0))) -> -0.04 | E36: =IF(INDEX('03 Kênh phân phối'!$C$5:$C$401,MATCH(E$4&"|nike_brand_pct_change_reported",'03 Kênh phân phối'!$Z$5:$Z$401,0))="","–",INDEX('03 Kênh phân phối'!$C$5:$C$401,MATCH(E$4&"|nike_brand_pct_change_reported",'03 Kênh phân phối'!$Z$5:$Z$401,0))) -> 0.19 | F36: =IF(INDEX('03 Kênh phân phối'!$C$5:$C$401,MATCH(F$4&"|nike_brand_pct_change_reported",'03 Kênh phân phối'!$Z$5:$Z$401,0))="","–",INDEX('03 Kênh phân phối'!$C$5:$C$401,MATCH(F$4&"|nike_brand_pct_change_reported",'03 Kênh phân phối'!$Z$5:$Z$401,0))) -> 0.05 | G36: =IF(INDEX('03 Kênh phân phối'!$C$5:$C$401,MATCH(G$4&"|nike_brand_pct_change_reported",'03 Kênh phân phối'!$Z$5:$Z$401,0))="","–",INDEX('03 Kênh phân phối'!$C$5:$C$401,MATCH(G$4&"|nike_brand_pct_change_reported",'03 Kênh phân phối'!$Z$5:$Z$401,0))) -> 0.1 | H36: =IF(INDEX('03 Kênh phân phối'!$C$5:$C$401,MATCH(H$4&"|nike_brand_pct_change_reported",'03 Kênh phân phối'!$Z$5:$Z$401,0))="","–",INDEX('03 Kênh phân phối'!$C$5:$C$401,MATCH(H$4&"|nike_brand_pct_change_reported",'03 Kênh phân phối'!$Z$5:$Z$401,0))) -> 0.01 | I36: =IF(INDEX('03 Kênh phân phối'!$C$5:$C$401,MATCH(I$4&"|nike_brand_pct_change_reported",'03 Kênh phân phối'!$Z$5:$Z$401,0))="","–",INDEX('03 Kênh phân phối'!$C$5:$C$401,MATCH(I$4&"|nike_brand_pct_change_reported",'03 Kênh phân phối'!$Z$5:$Z$401,0))) -> -0.09 | J36: =IF(INDEX('03 Kênh phân phối'!$C$5:$C$401,MATCH(J$4&"|nike_brand_pct_change_reported",'03 Kênh phân phối'!$Z$5:$Z$401,0))="","–",INDEX('03 Kênh phân phối'!$C$5:$C$401,MATCH(J$4&"|nike_brand_pct_change_reported",'03 Kênh phân phối'!$Z$5:$Z$401,0))) -> 0.01 | K36: Tra cứu sheet “03 Kênh phân phối” theo khóa FY|nike_brand_pct_change_reported, cột “Giá trị”.
B38: B. Chỉ số kênh phân phối – phạm vi NIKE Brand
A39: direct_share | B39: Tỷ trọng NIKE Direct trong doanh thu NIKE Brand | C39: % | D39: =IF(COUNT(D23,D28)<2,"–",D23/D28) -> 0.34812191 | E39: =IF(COUNT(E23,E28)<2,"–",E23/E28) -> 0.38706169 | F39: =IF(COUNT(F23,F28)<2,"–",F23/F28) -> 0.42141507 | G39: =IF(COUNT(G23,G28)<2,"–",G23/G28) -> 0.43697065 | H39: =IF(COUNT(H23,H28)<2,"–",H23/H28) -> 0.43629618 | I39: =IF(COUNT(I23,I28)<2,"–",I23/I28) -> 0.42006978 | J39: =IF(COUNT(J23,J28)<2,"–",J23/J28) -> 0.39184468 | K39: [Doanh thu NIKE Direct] / [Tổng doanh thu NIKE Brand] | L39: Mẫu số là tổng doanh thu NIKE Brand (cùng cơ sở NIKE dùng khi nêu tỷ trọng), không phải NIKE, Inc.
A40: wholesale_share | B40: Tỷ trọng bán buôn trong doanh thu NIKE Brand | C40: % | D40: =IF(COUNT(D25,D28)<2,"–",D25/D28) -> 0.65103464 | E40: =IF(COUNT(E25,E28)<2,"–",E25/E28) -> 0.6123472 | F40: =IF(COUNT(F25,F28)<2,"–",F25/F28) -> 0.5762895 | G40: =IF(COUNT(G25,G28)<2,"–",G25/G28) -> 0.56183992 | H40: =IF(COUNT(H25,H28)<2,"–",H25/H28) -> 0.56279145 | I40: =IF(COUNT(I25,I28)<2,"–",I25/I28) -> 0.57885673 | J40: =IF(COUNT(J25,J28)<2,"–",J25/J28) -> 0.60707178 | K40: [Doanh thu bán buôn NIKE Brand] / [Tổng doanh thu NIKE Brand] | L40: Direct + Wholesale + Global Brand Divisions = 100% doanh thu NIKE Brand.
A41: gbd_share | B41: Tỷ trọng Global Brand Divisions trong doanh thu NIKE Brand | C41: % | D41: =IF(COUNT(D27,D28)<2,"–",D27/D28) -> 0.00084345479 | E41: =IF(COUNT(E27,E28)<2,"–",E27/E28) -> 0.00059111437 | F41: =IF(COUNT(F27,F28)<2,"–",F27/F28) -> 0.0022954361 | G41: =IF(COUNT(G27,G28)<2,"–",G27/G28) -> 0.0011894264 | H41: =IF(COUNT(H27,H28)<2,"–",H27/H28) -> 0.00091237176 | I41: =IF(COUNT(I27,I28)<2,"–",I27/I28) -> 0.0010734893 | J41: =IF(COUNT(J27,J28)<2,"–",J27/J28) -> 0.0010835434 | K41: [Doanh thu Global Brand Divisions] / [Tổng doanh thu NIKE Brand] | L41: Phần còn lại, chủ yếu là doanh thu cấp phép, dưới 0,3%.
A42: direct_growth | B42: Tăng trưởng doanh thu NIKE Direct (theo báo cáo) | C42: % | D42: =IF(COUNT(D23,D24)<2,"–",D23/D24-1) -> 0.053518251 | E42: =IF(COUNT(E23,E24)<2,"–",E23/E24-1) -> 0.32208044 | F42: =IF(COUNT(F23,F24)<2,"–",F23/F24-1) -> 0.14392181 | G42: =IF(COUNT(G23,G24)<2,"–",G23/G24-1) -> 0.13788316 | H42: =IF(COUNT(H23,H24)<2,"–",H23/H24-1) -> 0.0099023841 | I42: =IF(COUNT(I23,I24)<2,"–",I23/I24-1) -> -0.12714345 | J42: =IF(COUNT(J23,J24)<2,"–",J23/J24-1) -> -0.056593728 | K42: [Doanh thu NIKE Direct] / [Doanh thu NIKE Direct – năm trước] - 1 | L42: So với số năm trước trình bày trong cùng 10-K. Không loại trừ tỷ giá.
A43: wholesale_growth | B43: Tăng trưởng doanh thu bán buôn NIKE Brand (theo báo cáo) | C43: % | D43: =IF(COUNT(D25,D26)<2,"–",D25/D26-1) -> -0.089171223 | E43: =IF(COUNT(E25,E26)<2,"–",E25/E26-1) -> 0.11841423 | F43: =IF(COUNT(F25,F26)<2,"–",F25/F26-1) -> -0.011197776 | G43: =IF(COUNT(G25,G26)<2,"–",G25/G26-1) -> 0.069860981 | H43: =IF(COUNT(H25,H26)<2,"–",H25/H26-1) -> 0.013176625 | I43: =IF(COUNT(I25,I26)<2,"–",I25/I26-1) -> -0.067548094 | J43: =IF(COUNT(J25,J26)<2,"–",J25/J26-1) -> 0.060657574 | K43: [Doanh thu bán buôn NIKE Brand] / [Doanh thu bán buôn NIKE Brand – năm trước] - 1 | L43: So với số năm trước trình bày trong cùng 10-K. Không loại trừ tỷ giá.
A44: nike_brand_growth | B44: Tăng trưởng doanh thu NIKE Brand (theo báo cáo) | C44: % | D44: =IF(COUNT(D28,D29)<2,"–",D28/D29-1) -> -0.044333387 | E44: =IF(COUNT(E28,E29)<2,"–",E28/E29-1) -> 0.18907445 | F44: =IF(COUNT(F28,F29)<2,"–",F28/F29-1) -> 0.050670324 | G44: =IF(COUNT(G28,G29)<2,"–",G28/G29-1) -> 0.097376001 | H44: =IF(COUNT(H28,H29)<2,"–",H28/H29-1) -> 0.01146361 | I44: =IF(COUNT(I28,I29)<2,"–",I28/I29-1) -> -0.093426868 | J44: =IF(COUNT(J28,J29)<2,"–",J28/J29-1) -> 0.011361095 | K44: [Tổng doanh thu NIKE Brand] / [Tổng doanh thu NIKE Brand – năm trước] - 1 | L44: So với số năm trước trình bày trong cùng 10-K.
A45: digital_share_of_direct | B45: Tỷ trọng Digital trong NIKE Direct (xấp xỉ) | C45: % | D45: =IF(COUNT(D32,D23)<2,"–",D32*1000/D23) -> 0.44419318 | E45: =IF(COUNT(E32,E23)<2,"–",E32*1000/E23) -> 0.55589493 | F45: =IF(COUNT(F32,F23)<2,"–",F32*1000/F23) -> 0.57139806 | G45: =IF(COUNT(G32,G23)<2,"–",G32*1000/G23) -> 0.5913272 | H45: =IF(COUNT(H32,H23)<2,"–",H32*1000/H23) -> 0.56229379 | I45: =IF(COUNT(I32,I23)<2,"–",I32*1000/I23) -> 0.51110046 | J45: =IF(COUNT(J32,J23)<2,"–",J32*1000/J23) -> 0.48532731 | K45: [Doanh số NIKE Brand Digital] * 1000 / [Doanh thu NIKE Direct] | L45: Xấp xỉ: doanh số Digital chỉ được công bố làm tròn 0,1 tỷ USD (sai số khoảng ±0,3 điểm %). Nhân 1.000 để đổi tỷ USD sang triệu USD.
B47: C. Chỉ số kết quả tài chính – phạm vi NIKE, Inc.
A48: revenue_growth | B48: Tăng trưởng doanh thu NIKE, Inc. (theo báo cáo) | C48: % | D48: =IF(COUNT(D7,D8)<2,"–",D7/D8-1) -> -0.043817266 | E48: =IF(COUNT(E7,E8)<2,"–",E7/E8-1) -> 0.1907601 | F48: =IF(COUNT(F7,F8)<2,"–",F7/F8-1) -> 0.048767345 | G48: =IF(COUNT(G7,G8)<2,"–",G7/G8-1) -> 0.096488975 | H48: =IF(COUNT(H7,H8)<2,"–",H7/H8-1) -> 0.0028310912 | I48: =IF(COUNT(I7,I8)<2,"–",I7/I8-1) -> -0.098380125 | J48: =IF(COUNT(J7,J8)<2,"–",J7/J8-1) -> 0.0019218726 | K48: [Doanh thu] / [Doanh thu – năm trước] - 1 | L48: So với số năm trước trình bày trong cùng 10-K.
A49: gross_margin | B49: Biên lợi nhuận gộp | C49: % | D49: =IF(COUNT(D10,D7)<2,"–",D10/D7) -> 0.43421651 | E49: =IF(COUNT(E10,E7)<2,"–",E10/E7) -> 0.44820154 | F49: =IF(COUNT(F10,F7)<2,"–",F10/F7) -> 0.45983729 | G49: =IF(COUNT(G10,G7)<2,"–",G10/G7) -> 0.43524611 | H49: =IF(COUNT(H10,H7)<2,"–",H10/H7) -> 0.44560181 | I49: =IF(COUNT(I10,I7)<2,"–",I10/I7) -> 0.42734674 | J49: =IF(COUNT(J10,J7)<2,"–",J10/J7) -> 0.42913488 | K49: [Lợi nhuận gộp] / [Doanh thu] | L49: Lợi nhuận gộp / Doanh thu, cùng phạm vi NIKE, Inc.
A50: sga_ratio | B50: Tỷ lệ chi phí bán hàng và quản lý / doanh thu | C50: % | D50: =IF(COUNT(D13,D7)<2,"–",D13/D7) -> 0.35093442 | E50: =IF(COUNT(E13,E7)<2,"–",E13/E7) -> 0.2924469 | F50: =IF(COUNT(F13,F7)<2,"–",F13/F7) -> 0.31693428 | G50: =IF(COUNT(G13,G7)<2,"–",G13/G7) -> 0.31975711 | H50: =IF(COUNT(H13,H7)<2,"–",H13/H7) -> 0.32272887 | I50: =IF(COUNT(I13,I7)<2,"–",I13/I7) -> 0.34740547 | J50: =IF(COUNT(J13,J7)<2,"–",J13/J7) -> 0.34729945 | K50: [Tổng chi phí bán hàng và quản lý (SG&A)] / [Doanh thu] | L50: Chi phí chung của cả công ty, không phân bổ được theo kênh.
A51: demand_creation_ratio | B51: Tỷ lệ chi phí tạo nhu cầu / doanh thu | C51: % | D51: =IF(COUNT(D11,D7)<2,"–",D11/D7) -> 0.096035077 | E51: =IF(COUNT(E11,E7)<2,"–",E11/E7) -> 0.069917823 | F51: =IF(COUNT(F11,F7)<2,"–",F11/F7) -> 0.082423464 | G51: =IF(COUNT(G11,G7)<2,"–",G11/G7) -> 0.079270555 | H51: =IF(COUNT(H11,H7)<2,"–",H11/H7) -> 0.083427437 | I51: =IF(COUNT(I11,I7)<2,"–",I11/I7) -> 0.10125462 | J51: =IF(COUNT(J11,J7)<2,"–",J11/J7) -> 0.10246131 | K51: [Chi phí tạo nhu cầu] / [Doanh thu] | L51: Phần chi cho marketing trong SG&A.
A52: operating_overhead_ratio | B52: Tỷ lệ chi phí vận hành chung / doanh thu | C52: % | D52: =IF(COUNT(D12,D7)<2,"–",D12/D7) -> 0.25489934 | E52: =IF(COUNT(E12,E7)<2,"–",E12/E7) -> 0.22252908 | F52: =IF(COUNT(F12,F7)<2,"–",F12/F7) -> 0.23451081 | G52: =IF(COUNT(G12,G7)<2,"–",G12/G7) -> 0.24048656 | H52: =IF(COUNT(H12,H7)<2,"–",H12/H7) -> 0.23930143 | I52: =IF(COUNT(I12,I7)<2,"–",I12/I7) -> 0.24615086 | J52: =IF(COUNT(J12,J7)<2,"–",J12/J7) -> 0.24483814 | K52: [Chi phí vận hành chung] / [Doanh thu] | L52: Phần chi phí vận hành trong SG&A.
A53: ebit | B53: EBIT (tự tính theo định nghĩa của NIKE) | C53: triệu USD | D53: =IF(COUNT(D18,D17,D14)<3,"–",D18+D17+D14) -> 2976 | E53: =IF(COUNT(E18,E17,E14)<3,"–",E18+E17+E14) -> 6923 | F53: =IF(COUNT(F18,F17,F14)<3,"–",F18+F17+F14) -> 6856 | G53: =IF(COUNT(G18,G17,G14)<3,"–",G18+G17+G14) -> 6195 | H53: =IF(COUNT(H18,H17,H14)<3,"–",H18+H17+H14) -> 6539 | I53: =IF(COUNT(I18,I17,I14)<3,"–",I18+I17+I14) -> 3778 | J53: =IF(COUNT(J18,J17,J14)<3,"–",J18+J17+J14) -> 3850 | K53: [Lợi nhuận sau thuế] + [Chi phí thuế thu nhập] + [Chi phí (thu nhập) lãi thuần] | L53: Chỉ tiêu non-GAAP. NIKE không trình bày dòng “Operating income” mà dùng EBIT. Số tự tính được đối chiếu với EBIT do NIKE công bố.
A54: ebit_margin | B54: Biên EBIT | C54: % | D54: =IF(COUNT(D53,D7)<2,"–",D53/D7) -> 0.07956581 | E54: =IF(COUNT(E53,E7)<2,"–",E53/E7) -> 0.1554403 | F54: =IF(COUNT(F53,F7)<2,"–",F53/F7) -> 0.14677799 | G54: =IF(COUNT(G53,G7)<2,"–",G53/G7) -> 0.12095593 | H54: =IF(COUNT(H53,H7)<2,"–",H53/H7) -> 0.12731202 | I54: =IF(COUNT(I53,I7)<2,"–",I53/I7) -> 0.081582414 | J54: =IF(COUNT(J53,J7)<2,"–",J53/J7) -> 0.082977715 | K54: [EBIT (tự tính theo định nghĩa của NIKE)] / [Doanh thu] | L54: Non-GAAP. EBIT / Doanh thu NIKE, Inc.
A55: net_income_margin | B55: Biên lợi nhuận sau thuế | C55: % | D55: =IF(COUNT(D18,D7)<2,"–",D18/D7) -> 0.067882255 | E55: =IF(COUNT(E18,E7)<2,"–",E18/E7) -> 0.12858682 | F55: =IF(COUNT(F18,F7)<2,"–",F18/F7) -> 0.12943695 | G55: =IF(COUNT(G18,G7)<2,"–",G18/G7) -> 0.09899057 | H55: =IF(COUNT(H18,H7)<2,"–",H18/H7) -> 0.11097699 | I55: =IF(COUNT(I18,I7)<2,"–",I18/I7) -> 0.069511326 | J55: =IF(COUNT(J18,J7)<2,"–",J18/J7) -> 0.066985646 | K55: [Lợi nhuận sau thuế] / [Doanh thu] | L55: GAAP.
A56: inventory_growth | B56: Thay đổi hàng tồn kho so với đầu kỳ | C56: % | D56: =IF(COUNT(D19,D20)<2,"–",D19/D20-1) -> 0.31038776 | E56: =IF(COUNT(E19,E20)<2,"–",E19/E20-1) -> -0.069634858 | F56: =IF(COUNT(F19,F20)<2,"–",F19/F20-1) -> 0.22847972 | G56: =IF(COUNT(G19,G20)<2,"–",G19/G20-1) -> 0.0040380048 | H56: =IF(COUNT(H19,H20)<2,"–",H19/H20-1) -> -0.11059853 | I56: =IF(COUNT(I19,I20)<2,"–",I19/I20-1) -> -0.0039898923 | J56: =IF(COUNT(J19,J20)<2,"–",J19/J20-1) -> 0.0016023501 | K56: [Hàng tồn kho cuối kỳ] / [Hàng tồn kho cuối kỳ – năm trước] - 1 | L56: Số dư 31/5 năm nay so với 31/5 năm trước.
A57: average_inventory | B57: Hàng tồn kho bình quân | C57: triệu USD | D57: =IF(COUNT(D19,D20)<2,"–",(D19+D20)/2) -> 6494.5 | E57: =IF(COUNT(E19,E20)<2,"–",(E19+E20)/2) -> 7110.5 | F57: =IF(COUNT(F19,F20)<2,"–",(F19+F20)/2) -> 7637 | G57: =IF(COUNT(G19,G20)<2,"–",(G19+G20)/2) -> 8437 | H57: =IF(COUNT(H19,H20)<2,"–",(H19+H20)/2) -> 7986.5 | I57: =IF(COUNT(I19,I20)<2,"–",(I19+I20)/2) -> 7504 | J57: =IF(COUNT(J19,J20)<2,"–",(J19+J20)/2) -> 7495 | K57: ([Hàng tồn kho cuối kỳ] + [Hàng tồn kho cuối kỳ – năm trước]) / 2 | L57: Bình quân số dư đầu kỳ và cuối kỳ.
A58: inventory_turnover | B58: Vòng quay hàng tồn kho | C58: lần | D58: =IF(COUNT(D9,D57)<2,"–",D9/D57) -> 3.2584495 | E58: =IF(COUNT(E9,E57)<2,"–",E9/E57) -> 3.456297 | F58: =IF(COUNT(F9,F57)<2,"–",F9/F57) -> 3.3037842 | G58: =IF(COUNT(G9,G57)<2,"–",G9/G57) -> 3.4283513 | H58: =IF(COUNT(H9,H57)<2,"–",H9/H57) -> 3.5653916 | I58: =IF(COUNT(I9,I57)<2,"–",I9/I57) -> 3.5339819 | J58: =IF(COUNT(J9,J57)<2,"–",J9/J57) -> 3.533956 | K58: [Giá vốn hàng bán] / [Hàng tồn kho bình quân] | L58: Giá vốn hàng bán / Hàng tồn kho bình quân.
A59: days_inventory | B59: Số ngày tồn kho bình quân | C59: ngày | D59: =IF(COUNT(D58)<1,"–",365/D58) -> 112.01647 | E59: =IF(COUNT(E58)<1,"–",365/E58) -> 105.60435 | F59: =IF(COUNT(F58)<1,"–",365/F58) -> 110.47937 | G59: =IF(COUNT(G58)<1,"–",365/G58) -> 106.46517 | H59: =IF(COUNT(H58)<1,"–",365/H58) -> 102.37305 | I59: =IF(COUNT(I58)<1,"–",365/I58) -> 103.28293 | J59: =IF(COUNT(J58)<1,"–",365/J58) -> 103.28369 | K59: 365 / [Vòng quay hàng tồn kho] | L59: 365 / Vòng quay hàng tồn kho.
B61: D. Kiểm tra các phép cộng trừ (đúng thì chênh lệch bằng 0, cột cuối là kết luận)
A62: chk_gross_profit | B62: Doanh thu − Giá vốn − Lợi nhuận gộp | C62: triệu USD | D62: =IF(COUNT(D7,D9,D10)<3,"–",D7-D9-D10) -> 0 | E62: =IF(COUNT(E7,E9,E10)<3,"–",E7-E9-E10) -> 0 | F62: =IF(COUNT(F7,F9,F10)<3,"–",F7-F9-F10) -> 0 | G62: =IF(COUNT(G7,G9,G10)<3,"–",G7-G9-G10) -> 0 | H62: =IF(COUNT(H7,H9,H10)<3,"–",H7-H9-H10) -> 0 | I62: =IF(COUNT(I7,I9,I10)<3,"–",I7-I9-I10) -> 0 | J62: =IF(COUNT(J7,J9,J10)<3,"–",J7-J9-J10) -> 0 | K62: [Doanh thu] - [Giá vốn hàng bán] - [Lợi nhuận gộp] (ngưỡng ±1 triệu USD) | L62: =IF(AND(MAX(D62:J62)<=1,MIN(D62:J62)>=-1),"Đạt","Kiểm tra lại") -> Đạt
A63: chk_sga | B63: Tạo nhu cầu + Vận hành chung − Tổng SG&A | C63: triệu USD | D63: =IF(COUNT(D11,D12,D13)<3,"–",D11+D12-D13) -> 0 | E63: =IF(COUNT(E11,E12,E13)<3,"–",E11+E12-E13) -> 0 | F63: =IF(COUNT(F11,F12,F13)<3,"–",F11+F12-F13) -> 0 | G63: =IF(COUNT(G11,G12,G13)<3,"–",G11+G12-G13) -> 0 | H63: =IF(COUNT(H11,H12,H13)<3,"–",H11+H12-H13) -> 0 | I63: =IF(COUNT(I11,I12,I13)<3,"–",I11+I12-I13) -> 0 | J63: =IF(COUNT(J11,J12,J13)<3,"–",J11+J12-J13) -> 0 | K63: [Chi phí tạo nhu cầu] + [Chi phí vận hành chung] - [Tổng chi phí bán hàng và quản lý (SG&A)] (ngưỡng ±1 triệu USD) | L63: =IF(AND(MAX(D63:J63)<=1,MIN(D63:J63)>=-1),"Đạt","Kiểm tra lại") -> Đạt
A64: chk_pretax | B64: Lợi nhuận gộp − SG&A − Lãi thuần − Khác thuần − LNTT | C64: triệu USD | D64: =IF(COUNT(D10,D13,D14,D15,D16)<5,"–",D10-D13-D14-D15-D16) -> 0 | E64: =IF(COUNT(E10,E13,E14,E15,E16)<5,"–",E10-E13-E14-E15-E16) -> 0 | F64: =IF(COUNT(F10,F13,F14,F15,F16)<5,"–",F10-F13-F14-F15-F16) -> 0 | G64: =IF(COUNT(G10,G13,G14,G15,G16)<5,"–",G10-G13-G14-G15-G16) -> 0 | H64: =IF(COUNT(H10,H13,H14,H15,H16)<5,"–",H10-H13-H14-H15-H16) -> 0 | I64: =IF(COUNT(I10,I13,I14,I15,I16)<5,"–",I10-I13-I14-I15-I16) -> 0 | J64: =IF(COUNT(J10,J13,J14,J15,J16)<5,"–",J10-J13-J14-J15-J16) -> 0 | K64: [Lợi nhuận gộp] - [Tổng chi phí bán hàng và quản lý (SG&A)] - [Chi phí (thu nhập) lãi thuần] - [Chi phí (thu nhập) khác thuần] - [Lợi nhuận trước thuế] (ngưỡng ±2 triệu USD) | L64: =IF(AND(MAX(D64:J64)<=2,MIN(D64:J64)>=-2),"Đạt","Kiểm tra lại") -> Đạt
A65: chk_net_income | B65: LNTT − Thuế − LNST | C65: triệu USD | D65: =IF(COUNT(D16,D17,D18)<3,"–",D16-D17-D18) -> 0 | E65: =IF(COUNT(E16,E17,E18)<3,"–",E16-E17-E18) -> 0 | F65: =IF(COUNT(F16,F17,F18)<3,"–",F16-F17-F18) -> 0 | G65: =IF(COUNT(G16,G17,G18)<3,"–",G16-G17-G18) -> 0 | H65: =IF(COUNT(H16,H17,H18)<3,"–",H16-H17-H18) -> 0 | I65: =IF(COUNT(I16,I17,I18)<3,"–",I16-I17-I18) -> 0 | J65: =IF(COUNT(J16,J17,J18)<3,"–",J16-J17-J18) -> 0 | K65: [Lợi nhuận trước thuế] - [Chi phí thuế thu nhập] - [Lợi nhuận sau thuế] (ngưỡng ±1 triệu USD) | L65: =IF(AND(MAX(D65:J65)<=1,MIN(D65:J65)>=-1),"Đạt","Kiểm tra lại") -> Đạt
A66: chk_channels | B66: Direct + Wholesale + GBD − Tổng NIKE Brand | C66: triệu USD | D66: =IF(COUNT(D23,D25,D27,D28)<4,"–",D23+D25+D27-D28) -> 0 | E66: =IF(COUNT(E23,E25,E27,E28)<4,"–",E23+E25+E27-E28) -> 0 | F66: =IF(COUNT(F23,F25,F27,F28)<4,"–",F23+F25+F27-F28) -> 0 | G66: =IF(COUNT(G23,G25,G27,G28)<4,"–",G23+G25+G27-G28) -> 0 | H66: =IF(COUNT(H23,H25,H27,H28)<4,"–",H23+H25+H27-H28) -> 0 | I66: =IF(COUNT(I23,I25,I27,I28)<4,"–",I23+I25+I27-I28) -> 0 | J66: =IF(COUNT(J23,J25,J27,J28)<4,"–",J23+J25+J27-J28) -> 0 | K66: [Doanh thu NIKE Direct] + [Doanh thu bán buôn NIKE Brand] + [Doanh thu Global Brand Divisions] - [Tổng doanh thu NIKE Brand] (ngưỡng ±1 triệu USD) | L66: =IF(AND(MAX(D66:J66)<=1,MIN(D66:J66)>=-1),"Đạt","Kiểm tra lại") -> Đạt
A67: chk_segments | B67: NIKE Brand + Converse + Corporate − Doanh thu NIKE, Inc. | C67: triệu USD | D67: =IF(COUNT(D28,D30,D31,D7)<4,"–",D28+D30+D31-D7) -> 0 | E67: =IF(COUNT(E28,E30,E31,E7)<4,"–",E28+E30+E31-E7) -> 0 | F67: =IF(COUNT(F28,F30,F31,F7)<4,"–",F28+F30+F31-F7) -> 0 | G67: =IF(COUNT(G28,G30,G31,G7)<4,"–",G28+G30+G31-G7) -> 0 | H67: =IF(COUNT(H28,H30,H31,H7)<4,"–",H28+H30+H31-H7) -> 0 | I67: =IF(COUNT(I28,I30,I31,I7)<4,"–",I28+I30+I31-I7) -> 0 | J67: =IF(COUNT(J28,J30,J31,J7)<4,"–",J28+J30+J31-J7) -> 0 | K67: [Tổng doanh thu NIKE Brand] + [Doanh thu Converse] + [Doanh thu Corporate] - [Doanh thu] (ngưỡng ±1 triệu USD) | L67: =IF(AND(MAX(D67:J67)<=1,MIN(D67:J67)>=-1),"Đạt","Kiểm tra lại") -> Đạt
A68: chk_ebit | B68: EBIT tự tính − EBIT NIKE công bố | C68: triệu USD | D68: =IF(COUNT(D53,D21)<2,"–",D53-D21) -> 0 | E68: =IF(COUNT(E53,E21)<2,"–",E53-E21) -> 0 | F68: =IF(COUNT(F53,F21)<2,"–",F53-F21) -> 0 | G68: =IF(COUNT(G53,G21)<2,"–",G53-G21) -> 0 | H68: =IF(COUNT(H53,H21)<2,"–",H53-H21) -> 0 | I68: =IF(COUNT(I53,I21)<2,"–",I53-I21) -> 0 | J68: =IF(COUNT(J53,J21)<2,"–",J53-J21) -> 0 | K68: [EBIT (tự tính theo định nghĩa của NIKE)] - [EBIT do NIKE công bố] (ngưỡng ±1 triệu USD) | L68: =IF(AND(MAX(D68:J68)<=1,MIN(D68:J68)>=-1),"Đạt","Kiểm tra lại") -> Đạt
B70: E. So với tỷ lệ NIKE tự công bố (các ô là phần chênh lệch, cột cuối là kết luận)
A71: cmp_revenue_growth | B71: Tăng trưởng doanh thu tự tính − % NIKE công bố | C71: điểm % | D71: =IF(COUNT(D48,D22)<2,"–",(D48-D22)*100) -> -0.38172662 | E71: =IF(COUNT(E48,E22)<2,"–",(E48-E22)*100) -> 0.076009946 | F71: =IF(COUNT(F48,F22)<2,"–",(F48-F22)*100) -> -0.12326553 | G71: =IF(COUNT(G48,G22)<2,"–",(G48-G22)*100) -> -0.35110255 | H71: =IF(COUNT(H48,H22)<2,"–",(H48-H22)*100) -> 0.28310912 | I71: =IF(COUNT(I48,I22)<2,"–",(I48-I22)*100) -> 0.16198746 | J71: =IF(COUNT(J48,J22)<2,"–",(J48-J22)*100) -> 0.19218726 | K71: [Tăng trưởng doanh thu NIKE, Inc. (theo báo cáo)] - [% thay đổi doanh thu (NIKE công bố, đã làm tròn)] (ngưỡng ±1 điểm %) | L71: =IF(AND(MAX(D71:J71)<=1,MIN(D71:J71)>=-1),"Đạt","Kiểm tra lại") -> Đạt
A72: cmp_direct_growth | B72: Tăng trưởng NIKE Direct tự tính − % NIKE công bố | C72: điểm % | D72: =IF(COUNT(D42,D34)<2,"–",(D42-D34)*100) -> 0.35182507 | E72: =IF(COUNT(E42,E34)<2,"–",(E42-E34)*100) -> 0.20804393 | F72: =IF(COUNT(F42,F34)<2,"–",(F42-F34)*100) -> 0.39218082 | G72: =IF(COUNT(G42,G34)<2,"–",(G42-G34)*100) -> -0.21168429 | H72: =IF(COUNT(H42,H34)<2,"–",(H42-H34)*100) -> -0.0097615919 | I72: =IF(COUNT(I42,I34)<2,"–",(I42-I34)*100) -> 0.28565454 | J72: =IF(COUNT(J42,J34)<2,"–",(J42-J34)*100) -> 0.34062716 | K72: [Tăng trưởng doanh thu NIKE Direct (theo báo cáo)] - [% thay đổi NIKE Direct (NIKE công bố, đã làm tròn)] (ngưỡng ±1 điểm %) | L72: =IF(AND(MAX(D72:J72)<=1,MIN(D72:J72)>=-1),"Đạt","Kiểm tra lại") -> Đạt
A73: cmp_wholesale_growth | B73: Tăng trưởng bán buôn tự tính − % NIKE công bố | C73: điểm % | D73: =IF(COUNT(D43,D35)<2,"–",(D43-D35)*100) -> 0.082877709 | E73: =IF(COUNT(E43,E35)<2,"–",(E43-E35)*100) -> -0.15857661 | F73: =IF(COUNT(F43,F35)<2,"–",(F43-F35)*100) -> -0.11977759 | G73: =IF(COUNT(G43,G35)<2,"–",(G43-G35)*100) -> -0.013901906 | H73: =IF(COUNT(H43,H35)<2,"–",(H43-H35)*100) -> 0.31766252 | I73: =IF(COUNT(I43,I35)<2,"–",(I43-I35)*100) -> 0.24519058 | J73: =IF(COUNT(J43,J35)<2,"–",(J43-J35)*100) -> 0.065757447 | K73: [Tăng trưởng doanh thu bán buôn NIKE Brand (theo báo cáo)] - [% thay đổi bán buôn (NIKE công bố, đã làm tròn)] (ngưỡng ±1 điểm %) | L73: =IF(AND(MAX(D73:J73)<=1,MIN(D73:J73)>=-1),"Đạt","Kiểm tra lại") -> Đạt
A74: cmp_brand_growth | B74: Tăng trưởng NIKE Brand tự tính − % NIKE công bố | C74: điểm % | D74: =IF(COUNT(D44,D36)<2,"–",(D44-D36)*100) -> -0.43333871 | E74: =IF(COUNT(E44,E36)<2,"–",(E44-E36)*100) -> -0.092555106 | F74: =IF(COUNT(F44,F36)<2,"–",(F44-F36)*100) -> 0.067032369 | G74: =IF(COUNT(G44,G36)<2,"–",(G44-G36)*100) -> -0.26239986 | H74: =IF(COUNT(H44,H36)<2,"–",(H44-H36)*100) -> 0.14636097 | I74: =IF(COUNT(I44,I36)<2,"–",(I44-I36)*100) -> -0.34268683 | J74: =IF(COUNT(J44,J36)<2,"–",(J44-J36)*100) -> 0.1361095 | K74: [Tăng trưởng doanh thu NIKE Brand (theo báo cáo)] - [% thay đổi doanh thu NIKE Brand (NIKE công bố, đã làm tròn)] (ngưỡng ±1 điểm %) | L74: =IF(AND(MAX(D74:J74)<=1,MIN(D74:J74)>=-1),"Đạt","Kiểm tra lại") -> Đạt
A75: cmp_direct_share | B75: Tỷ trọng NIKE Direct tự tính − tỷ trọng NIKE nêu | C75: điểm % | D75: =IF(COUNT(D39,D33)<2,"–",(D39-D33)*100) -> -0.18780927 | E75: =IF(COUNT(E39,E33)<2,"–",(E39-E33)*100) -> -0.29383113 | F75: =IF(COUNT(F39,F33)<2,"–",(F39-F33)*100) -> 0.14150689 | G75: =IF(COUNT(G39,G33)<2,"–",(G39-G33)*100) -> -0.3029346 | H75: =IF(COUNT(H39,H33)<2,"–",(H39-H33)*100) -> -0.37038239 | I75: =IF(COUNT(I39,I33)<2,"–",(I39-I33)*100) -> 0.0069776804 | J75: =IF(COUNT(J39,J33)<2,"–",(J39-J33)*100) -> – | K75: [Tỷ trọng NIKE Direct trong doanh thu NIKE Brand] - [Tỷ trọng NIKE Direct do NIKE nêu (xấp xỉ)] (ngưỡng ±1 điểm %) | L75: =IF(AND(MAX(D75:J75)<=1,MIN(D75:J75)>=-1),"Đạt","Kiểm tra lại") -> Đạt

Sheet 05 Nguồn & Định nghĩa
A1: Nguồn, định nghĩa và giới hạn của dữ liệu
A3: A. Tài liệu nguồn chính thức (Form 10-K nộp SEC)
A4: Năm tài chính và kỳ báo cáo | B4: Tài liệu | C4: Liên kết SEC EDGAR | D4: Bản sao trên NIKE Investor Relations | E4: Ngày nộp SEC | F4: Số accession
A5: FY2020 (01/06/2019 – 31/05/2020) | B5: NIKE, Inc. Form 10-K for the fiscal year ended May 31, 2020 | C5: https://www.sec.gov/Archives/edgar/data/320187/000032018720000047/nke-531202010k.htm | D5: Bản sao trên NIKE Investor Relations | E5: 24/07/2020 | F5: 0000320187-20-000047
A6: FY2021 (01/06/2020 – 31/05/2021) | B6: NIKE, Inc. Form 10-K for the fiscal year ended May 31, 2021 | C6: https://www.sec.gov/Archives/edgar/data/320187/000032018721000028/nke-20210531.htm | D6: Bản sao trên NIKE Investor Relations | E6: 20/07/2021 | F6: 0000320187-21-000028
A7: FY2022 (01/06/2021 – 31/05/2022) | B7: NIKE, Inc. Form 10-K for the fiscal year ended May 31, 2022 | C7: https://www.sec.gov/Archives/edgar/data/320187/000032018722000038/nke-20220531.htm | D7: Bản sao trên NIKE Investor Relations | E7: 21/07/2022 | F7: 0000320187-22-000038
A8: FY2023 (01/06/2022 – 31/05/2023) | B8: NIKE, Inc. Form 10-K for the fiscal year ended May 31, 2023 | C8: https://www.sec.gov/Archives/edgar/data/320187/000032018723000039/nke-20230531.htm | D8: Bản sao trên NIKE Investor Relations | E8: 20/07/2023 | F8: 0000320187-23-000039
A9: FY2024 (01/06/2023 – 31/05/2024) | B9: NIKE, Inc. Form 10-K for the fiscal year ended May 31, 2024 | C9: https://www.sec.gov/Archives/edgar/data/320187/000032018724000044/nke-20240531.htm | D9: Bản sao trên NIKE Investor Relations | E9: 25/07/2024 | F9: 0000320187-24-000044
A10: FY2025 (01/06/2024 – 31/05/2025) | B10: NIKE, Inc. Form 10-K for the fiscal year ended May 31, 2025 | C10: https://www.sec.gov/Archives/edgar/data/320187/000032018725000047/nke-20250531.htm | D10: Bản sao trên NIKE Investor Relations | E10: 17/07/2025 | F10: 0000320187-25-000047
A11: FY2026 (01/06/2025 – 31/05/2026) | B11: NIKE, Inc. Form 10-K for the fiscal year ended May 31, 2026 | C11: https://www.sec.gov/Archives/edgar/data/320187/000032018726000088/nke-20260531.htm | D11: Bản sao trên NIKE Investor Relations | E11: 15/07/2026 | F11: 0000320187-26-000088
A13: B. Thuật ngữ và định nghĩa
A14: Thuật ngữ | B14: Tiếng Anh / tên trong 10-K | C14: Định nghĩa | D14: Lưu ý phạm vi và cách dùng
A15: Năm tài chính (FY) | B15: Fiscal year | C15: Năm tài chính của NIKE kết thúc ngày 31/5. FY2026 là giai đoạn 01/06/2025 – 31/05/2026. | D15: Không quy đổi sang năm dương lịch. Khi so sánh với công ty khác cần lưu ý lệch kỳ.
A16: NIKE, Inc. | B16: NIKE, Inc. (consolidated) | C16: Toàn bộ tập đoàn: NIKE Brand + Converse + Corporate. | D16: Các chỉ tiêu ở sheet 02 (doanh thu, giá vốn, SG&A, EBIT, tồn kho) thuộc phạm vi này.
A17: NIKE Brand | B17: NIKE Brand | C17: Thương hiệu NIKE (gồm cả Jordan Brand), chia theo 4 khu vực địa lý và Global Brand Divisions. Không gồm Converse. | D17: Phạm vi của các chỉ tiêu kênh phân phối ở sheet 03.
A18: NIKE Direct | B18: NIKE Direct / Sales through Direct to Consumer | C18: Doanh thu NIKE Brand bán trực tiếp cho người tiêu dùng qua cửa hàng do NIKE sở hữu và nền tảng số (NIKE Brand Digital). | D18: Là doanh thu, không phải lợi nhuận. NIKE không công bố lợi nhuận riêng của kênh này.
A19: NIKE Brand Digital | B19: NIKE Brand Digital sales (FY2020–21: Digital commerce sales) | C19: Phần doanh số NIKE Direct qua ứng dụng và website của NIKE. | D19: Là một phần của NIKE Direct. Chỉ công bố trong MD&A, làm tròn 0,1 tỷ USD.
A20: Bán buôn (Wholesale) | B20: Sales to Wholesale Customers | C20: Doanh thu NIKE Brand bán cho nhà bán lẻ, nhà phân phối độc lập, bên nhận cấp phép. | D20: Không gồm bán buôn của Converse.
A21: Global Brand Divisions | B21: Global Brand Divisions | C21: Doanh thu cấp phép thương hiệu NIKE và doanh thu khác không thuộc khu vực địa lý. | D21: Rất nhỏ (dưới 0,3% doanh thu NIKE Brand), không thuộc Direct hay Wholesale.
A22: Converse | B22: Converse | C22: Phân khúc kinh doanh riêng của NIKE, Inc., có kênh trực tiếp và bán buôn riêng. | D22: Không nằm trong số liệu NIKE Direct/Wholesale của bộ dữ liệu.
A23: Corporate | B23: Corporate revenues | C23: Chủ yếu là lãi/lỗ phòng ngừa rủi ro tỷ giá liên quan đến doanh thu, quản lý tập trung. | D23: Có thể âm. Chỉ dùng để đối chiếu NIKE Brand + Converse + Corporate = NIKE, Inc.
A24: Biên lợi nhuận gộp | B24: Gross margin | C24: Lợi nhuận gộp / Doanh thu. | D24: Phạm vi NIKE, Inc. NIKE không công bố biên gộp theo kênh.
A25: Chi phí bán hàng và quản lý (SG&A) | B25: Total selling and administrative expense | C25: Tổng của chi phí tạo nhu cầu (Demand creation) và chi phí vận hành chung (Operating overhead). | D25: Chi phí chung của cả công ty. Từ số liệu công bố, không thể phân bổ chính xác cho NIKE Direct hay Wholesale.
... A33: XBRL | B33: eXtensible Business Reporting Language | C33: Nhãn dữ liệu (máy đọc được) gắn vào từng con số trong 10-K nộp SEC. | D33: Cột “Thẻ XBRL” cho biết số liệu lấy từ thẻ nào, dùng cho việc kiểm tra tự động.
A35: C. Số liệu còn thiếu và giới hạn
A36: Vấn đề | B36: Tình trạng | C36: Mô tả | D36: Cách xử lý trong bộ dữ liệu
A37: Lợi nhuận và chi phí theo kênh | B37: Không công bố | C37: NIKE không công bố lợi nhuận, biên gộp hay chi phí riêng của NIKE Direct và Wholesale. SG&A là chi phí chung của cả công ty. | D37: Bộ dữ liệu không tính và không ước lượng các số này. Mọi phân tích lợi nhuận chỉ làm ở phạm vi NIKE, Inc.
A38: Tỷ trọng NIKE Direct FY2026 do NIKE nêu | B38: Thiếu | C38: 10-K FY2026 không có câu “approximately …% of total NIKE Brand revenues”. | D38: Ô để trống, trạng thái “Thiếu / không công bố”. Tỷ trọng do nhóm tự tính ở sheet 04 vẫn có đủ 7 năm.
A39: Doanh số Digital | B39: Độ chính xác thấp | C39: Chỉ công bố trong MD&A, làm tròn đến 0,1 tỷ USD. Số FY2023 được trình bày lại từ 12,6 xuống 12,4 tỷ USD do phân loại lại giữa cửa hàng và Digital. | D39: Giữ số gốc và ghi chú việc trình bày lại. Tỷ trọng Digital trong NIKE Direct được ghi rõ là xấp xỉ.
A40: Tăng trưởng loại trừ tỷ giá | B40: Không tự tính lại được | C40: Do NIKE tính bằng tỷ giá nội bộ, bên ngoài không có dữ liệu để tính lại. | D40: Lấy nguyên văn từ bảng doanh thu trong MD&A, rồi đọc lại trên trang 10-K để đối chiếu (ảnh chụp trong handover/bang-chung-doi-chieu/).
A42: D. Các lần NIKE trình bày lại hoặc phân loại lại số liệu
A43: Tài liệu | B43: Nội dung | C43: Trích dẫn từ 10-K | D43: Ảnh hưởng tới bộ dữ liệu
A44: 10-K FY2024 | B44: NIKE Direct: cửa hàng và Digital | C44: “Within NIKE Direct revenues, there were certain reclassifications made between NIKE-owned retail stores and NIKE Brand Digital in the prior period to conform to current period presentation.” | D44: Doanh số Digital FY2023: 12,6 tỷ USD (10-K FY2023) được trình bày lại thành 12,4 tỷ USD. Tổng NIKE Direct không đổi.
A45: 10-K FY2022, FY2025, FY2026 | B45: Các lần phân loại lại khác | C45: FY2022: doanh thu chia theo nhóm người tiêu dùng Nam, Nữ, Trẻ em (hàng unisex xếp vào Nam) và báo cáo riêng Jordan Brand. FY2025: bỏ chỉ tiêu “wholesale equivalent revenues”. FY2026: phân loại lại một số khoản năm trước (Note 1). | D45: Không làm thay đổi chỉ tiêu nào trong bộ dữ liệu.
A47: E. Trạng thái dữ liệu
A48: Trạng thái | B48: Tiếng Anh | C48: Ý nghĩa | D48: Số lượng hiện tại
A49: Khớp nguồn chính thức | B49: Matched to official source | C49: Số liệu lấy tự động từ 10-K và đã được đối chiếu lại bằng ít nhất một cách khác: so với dữ liệu XBRL do SEC công bố (để chắc chắn đọc đúng chỉ tiêu và đúng kỳ), so với bảng trong MD&A, tính lại từ báo cáo tài chính, hoặc đọc lại ngay trên trang 10-K (có ảnh chụp đối chiếu). | D49: 202
A50: Chờ người kiểm tra | B50: Pending human review | C50: Số liệu chính thức nhưng chưa được đối chiếu lại bằng cách khác. Cần một người mở 10-K để kiểm tra. | D50: 0
A51: Đã xác minh (người) | B51: Human verified | C51: Thành viên nhóm đã tự mở 10-K, tìm đúng trang và xác nhận số liệu, có ghi tên và ngày. | D51: 0
A52: Thiếu / không công bố | B52: Missing or undisclosed | C52: NIKE không công bố số liệu này trong báo cáo 10-K tương ứng. Ô giá trị để trống, không điền số 0. | D52: 1
A53: Bằng chứng mâu thuẫn | B53: Conflicting evidence | C53: Hai nguồn chính thức cho kết quả khác nhau, lần đọc lại trên trang 10-K ra số khác, hoặc số đã xác minh khác số trích xuất mới. Chưa dùng số này cho đến khi xử lý xong. | D53: 0
A55: F. Kiểm tra tự động (lần chạy gần nhất)
A56: Kiểm tra | B56: Kết quả | C56: Chi tiết | D56: Ngày kiểm tra
A57: Đối chiếu với dữ liệu XBRL của SEC | B57: 247/247 khớp | C57: Toàn bộ số hợp nhất (không chia theo kênh) của 7 báo cáo, kể cả cột năm trước, được so với dữ liệu SEC của đúng báo cáo đó (cùng số accession). | D57: 23/10/2026
A58: Thuyết minh XBRL so với bảng MD&A | B58: Khớp toàn bộ | C58: Doanh thu NIKE Direct, bán buôn, Global Brand Divisions, NIKE Brand, Converse, Corporate và NIKE, Inc. ở hai vị trí khác nhau trong cùng 10-K. | D58: 23/10/2026
A59: Kiểm tra cộng trừ và so với tỷ lệ NIKE công bố | B59: Đạt | C59: Xem mục D và E ở sheet 04. | D59: 23/10/2026
A60: Đọc lại trên trang 10-K | B60: 35/35 khớp | C60: Các số chỉ có trong MD&A: mở từng 10-K và tìm trang theo chân trang. 28 tỷ lệ tăng trưởng loại trừ tỷ giá được đọc lại theo vị trí cột “% CHANGE EXCLUDING CURRENCY CHANGES” đầu tiên, 7 số Digital được đọc lại từ câu văn trên đúng trang. Ảnh chụp và bảng so sánh: handover/bang-chung-doi-chieu/doi-chieu-35-so.html (cũng có trên dashboard web). | D60: 24/10/2026
